Workbook

Sheet Indice
A1: ÍNDICE — Libro unificado (3 archivos de origen)
A3: Hoja | B3: Archivo de origen | C3: Filas | D3: Columnas
A4: Corpus_corregido | B4: Corpus_unificado_revision_motivacion_ABR.xlsx | C4: 164 | D4: 58
A5: Marcas_declaradas | B5: Corpus_unificado_revision_motivacion_ABR.xlsx | C5: 166 | D5: 29
A6: Marcas_todas | B6: Corpus_unificado_revision_motivacion_ABR.xlsx | C6: 166 | D6: 29
A7: Resumen_comparado | B7: Corpus_unificado_revision_motivacion_ABR.xlsx | C7: 62 | D7: 8
A8: Cambios_aplicados | B8: Corpus_unificado_revision_motivacion_ABR.xlsx | C8: 156 | D8: 5
A9: Diccionario_causales | B9: Corpus_unificado_revision_motivacion_ABR.xlsx | C9: 27 | D9: 5
A10: Leyenda_estatus | B10: Corpus_unificado_revision_motivacion_ABR.xlsx | C10: 9 | D10: 3
A11: Trazabilidad_fusion | B11: Corpus_unificado_revision_motivacion_ABR.xlsx | C11: 89 | D11: 6
A12: Criterios_y_fuentes | B12: Corpus_unificado_revision_motivacion_ABR.xlsx | C12: 40 | D12: 1
A13: Revision_motivacion_163 | B13: Corpus_unificado_revision_motivacion_ABR.xlsx | C13: 172 | D13: 10
A14: Llamoja_17_ABR18 | B14: Corpus_unificado_revision_motivacion_ABR.xlsx | C14: 26 | D14: 11
A15: Tipologia_Llamoja | B15: corpus_tipologia_llamoja_NULA__CONO.xlsx | C15: 42 | D15: 10
... A17: Sumarisimo_Llamoja | B17: Sumarisimo_Llamoja_17expedientes_SUM.xlsx | C17: 18 | D17: 5

Sheet Corpus_corregido
A1: N° | B1: Clave expediente | C1: Expediente (código de origen) | D1: Corpus / grupo | E1: Materia | F1: Sala | G1: Sentencia de vista | H1: Resolución | I1: Fecha SV | J1: Año SV | K1: Juez A quo | L1: Juez superior ponente | M1: Sentido del fallo / resultado del control | N1: Defectos declarados (ratio) | O1: Registros totales (todo estatus) | P1: D01 Notificación o emplazamiento defectuoso | Q1: D02 Vulneración del derecho de defensa | R1: D03 Litisconsorte necesario omitido | S1: D04 Declaración indebida de rebeldía | T1: D05 Omisión o irregularidad de audiencia | U1: D06 Deficiente fijación de puntos/hechos controvertidos | V1: D07 Prueba admitida y no actuada | W1: D08 Indebida admisión o exclusión de prueba | X1: D09 Prueba de oficio irregular | Y1: D10 Falta de contradictorio de la prueba | Z1: D11 Omisión de valoración de prueba decisiva | AA1: D12 Valoración probatoria defectuosa | AB1: D13 Motivación insuficiente | AC1: D14 Motivación aparente | AD1: D15 Falta o defecto interno de motivación | AE1: D16 Incongruencia procesal | AF1: D17 Falta de respuesta a agravios | AG1: D18 Violación de preclusión procesal | AH1: D19 Omisión de resolver incidencia previa | AI1: D20 Otro defecto insubsanable del procedimiento | AJ1: D21 Deficiencia de motivación externa (justificación de las premisas) | AK1: D22 Nulidad refleja, concatenada o por hecho sobreviniente | AL1: D23 Motivación defectuosa sin especificación del supuesto | AM1: Insubsanabilidad declarada | AN1: Nulidad sin vicio procesal identificado | AO1: Verificación pendiente de cita | AP1: Cambios aplicados | AQ1: Tipo de motivación (Llamoja) — principal | AR1: Tipo de motivación — secundario | AS1: ¿La Sala etiqueta el supuesto Llamoja? | AT1: Cita textual 1 | AU1: Cita 1 — qué sustenta | AV1: Cita textual 2 | AW1: Cita 2 — qué sustenta | AX1: Cita textual 3 | AY1: Cita 3 — qué sustenta | AZ1: Observaciones | BA1: Archivo / fuente documental | BB1: Fuentes del registro | BC1: N° de fuentes | BD1: DESC_PROCESO | BE1: TIPO_FALLO (NULA/REVOCADA/CONFIRMADA) | BF1: PROCESO_TIPO
A2: 1 | B2: 00001-2018 | C2: 00001-2018-0-0401-JR-CI-10 | D2: Matriz sumarísimos — anteriores a 2019 | E2: Otorgamiento de escritura pública | F2: 2SC | G2: SV 343-2019-2SC | H2: Res. 25 (tres-2SC) | I2: 09/07/2019 | J2: 2019 | K2: Javier Marín Andia | M2: NULA (reenvío) | N2: 2 | O2: 2 | AA2: DECLARADO — «se aprecia que el juez de la causa ha incurrido en error al considerar que el inmueble respecto del cual se pretende se otorgue una escritura pública es ganancial, fundamento que ha servido para declarar improcedente la demanda» | AD2: DECLARADO — «la resolución apelada contiene una motivación interna defectuosa o una falta de motivación interna del razonamiento conforme a lo señalado por el Tribunal Constitucional en el EXP. N° 00728-2008-PHC/TC» | AZ2: El A quo tuvo por ganancial el bien pese a que la partida de matrimonio de f. 33 (prueba de oficio admitida por él mismo) acreditaba que la venta fue anterior al matrimonio. | BB2: Matriz_defectos_procesales_1ra_SV | BC2: 1 | BD2: SUMARISIMO | BE2: NULA | BF2: SN
A3: 2 | B3: 00072-2023 | C3: 00072-2023-0-0401-JR-CI-06 | D3: Matriz sumarísimos — grupo 2024 | E3: Desalojo por ocupación precaria | F3: 2SC | G3: SV 429-2025-2SC | H3: Res. 43 (ocho-2SC) | I3: 10/09/2025 | J3: 2025 | K3: Patricia Valdivia Franco | M3: NULA DE OFICIO (reenvío) | N3: 4 | O3: 4 | Z3: DECLARADO — «solamente se analiza la inspección judicial y no medios probatorios directos que acrediten el lazo consanguíneo y/o afinidad que existiría entre las demandadas y Zhaodi Dara Bravo Salas, Josué Daniel Arenas Salas y Edmundo Ciro Barrantes» | AD3: DECLARADO — «la sentencia impugnada adolece de vicios de motivación en su fase interna y externa, al no deducirse de las premisas fácticas y de los medios probatorios aportados, la conclusión que los litisconsortes necesarios pasivos ostentan también legitimidad para poseer» | AE3: DECLARADO — «se omitió pronunciamiento en relación a la buena fe del tercero adquiriente y de la transferencia del predio a favor de Juan Manuel Salazar Herrera y Epifanía Rosenda Barrantes Quispe» | AJ3: DECLARADO — «la sentencia impugnada adolece de vicios de motivación en su fase interna y externa» (extremo externo: justificación de las premisas) | AM3: Sí | AP3: Baja D20→— · Alta —→D21 | AZ3: Nulidad declarada de oficio (art. 176 in fine CPC) pese a que el apelante pedía revocatoria. | BB3: Matriz_defectos_procesales_1ra_SV | BC3: 1 | BD3: SUMARISIMO | BE3: NULA | BF3: SN
A4: 3 | B4: 00115-2012 | C4: 00115-2012-0-0401-JR-CI-08 | D4: Matriz sumarísimos — anteriores a 2019 | E4: Desalojo por ocupación precaria | F4: 2SC | G4: SV 660-2018-2SC | H4: Res. 63 (siete-2SC) | I4: 21/12/2018 | J4: 2018 | K4: Omar del Carpio Medina | M4: NULA (reenvío) | N4: 1 | O4: 2 | P4: DECLARADO — «el Juzgado no ha notificado con la demanda y anexos en el predio a desalojar, inobservando dicha normatividad al expedir la sentencia» | Q4: DERIVADO — «ello a efecto de garantizar el conocimiento de la existencia del proceso a los ocupantes del predio»; «por haberse transgredido el principio al debido proceso consagrado por el artículo 139 inciso 3) de la Constitución Política del Estado» | AM4: Sí | AP4: Baja D20→— · Reclasificación de estatus D02→D02 (derivado) | AZ4: Art. 589 CPC: en desalojo la demanda debe notificarse además en el predio. La Sala precisa que el apersonamiento de un codemandado «no convalida ni subsana dicha omisión». | BB4: Matriz_defectos_procesales_1ra_SV | BC4: 1 | BD4: SUMARISIMO | BE4: NULA | BF4: SN
A5: 4 | B5: 00129-2022 | C5: 00129-2022-0-0401-JR-CI-01 | D5: Matriz sumarísimos — grupo 2024 | E5: Desalojo por ocupación precaria | F5: 2SC | G5: SV 563-2024-2SC | H5: Res. 47 (cinco-2SC) | I5: 10/12/2024 | J5: 2024 | K5: Shelah Galagarza Pérez | M5: REVOCADA → IMPROCEDENTE | N5: 0 | O5: 0 | AZ5: Sin vicio procesal declarado. Pronunciamiento inhibitorio por concurrencia de dos títulos de propiedad (ff. 21 y 58, IV Pleno Casatorio). | BB5: Matriz_defectos_procesales_1ra_SV | BC5: 1 | BD5: SUMARISIMO | BE5: REVOCADA | BF5: SR
A6: 5 | B6: 00132-2015 | C6: 00132-2015 | D6: Pre-2019 | F6: 2SC | G6: SV N° 667-2018-2SC | I6: 27/12/2018 | J6: 2018 | M6: Revocada | N6: 0 | O6: 0 | BB6: Comparativa_defectos_2018_vs_2024 + Defectos_procesales_SV_CSJA | BC6: 2 | BD6: CONOCIMIENTO | BE6: REVOCADA | BF6: CR
A7: 6 | B7: 00153-2022 | C7: 00153-2022-0-0401-SP-CI-03 | D7: Matriz sumarísimos — grupo 2024 | E7: Revisión judicial de procedimiento de ejecución coactiva | F7: 3SC | G7: SV 51-2025-3SC | H7: Res. 20 (dos) | I7: 31/01/2025 | J7: 2025 | K7: Javier Talavera Ugarte | M7: REVOCADA → INFUNDADA | N7: 0 | O7: 0 | AZ7: Sin vicio procesal declarado en el proceso judicial. La revocatoria se funda en error en la aplicación del régimen de notificación electrónica (art. 20.4 TUO LPAG y 6ª DCF del D. Leg. 1511). | BB7: Matriz_defectos_procesales_1ra_SV | BC7: 1 | BD7: SUMARISIMO | BE7: REVOCADA | BF7: SR
A8: 7 | B8: 00192-2021 | C8: 00192-2021 | D8: 2024 | G8: SV N° 285-2026 | I8: 04/06/2026 | J8: 2026 | M8: Revocada | N8: 0 | O8: 0 | BB8: Comparativa_defectos_2018_vs_2024 + Defectos_procesales_SV_CSJA | BC8: 2 | BD8: CONOCIMIENTO | BE8: REVOCADA | BF8: CR
A9: 8 | B9: 00234-2018 | C9: 00234-2018-0-0401-JR-JC-03 | D9: Matriz sumarísimos — anteriores a 2019 | E9: Desalojo por ocupación precaria | F9: 3SC | G9: SV 638-2019-3SC | H9: Res. 25 (seis) | I9: 23/08/2019 | J9: 2019 | K9: Zoilo Chávez Mamani | M9: REVOCADA → INFUNDADA | N9: 0 | O9: 1 | AH9: ALEGADO — «Debe declararse la nulidad de la sentencia puesto que ha sido emitida sin que las resoluciones tres y catorce hayan quedado consentidas» | AP9: Migración D20→D19 | AZ9: La Sala desestima la nulidad alegada (art. 190 in fine CPC) y revoca por el fondo: falta de comunicación indubitable de fenecimiento del comodato (IV Pleno). | BB9: Matriz_defectos_procesales_1ra_SV | BC9: 1 | BD9: SUMARISIMO | BE9: REVOCADA | BF9: SR
A10: 9 | B10: 00320-2023 | C10: 00320-2023 | D10: 2024 | F10: 2SC | G10: SV N° 398-2025-2SC | I10: 26/08/2025 | J10: 2025 | M10: Nula | N10: 1 | O10: 1 | AB10: DECLARADO — “…contractual. En ese sentido, la sentencia materia de alzada adolece de motivación insuficiente “[…] referida básicamente al mínimo de motivación exigible atendiendo a las razones de hecho o de derecho indispensables para asumir que la decisión está debidamente motivada. Si bien, como ha establecido este Tribunal, no se trata de dar…” | BB10: Comparativa_defectos_2018_vs_2024 + Defectos_procesales_SV_CSJA | BC10: 2 | BD10: CONOCIMIENTO | BE10: NULA | BF10: CN
A11: 10 | B11: 00340-2002 | C11: 00340-2002 | D11: Pre-2019 | F11: 2SC | G11: SV N° 0008-2018-2SC | I11: 08/01/2018 | J11: 2018 | M11: Nula | N11: 2 | O11: 2 | Q11: DECLARADO — “…de acto jurídico se encuentra incursa además en la causal prevista por el inciso 8) del artículo 219 del Código Civil", vulnera el derecho de defensa de las partes, porque la contestación de la demanda, no se alegó la causal invocada de oficio por el señor juez; no habiéndose ofrecido, ni actuado pruebas sobre la causal formulada por el juez. c) En el décimo pr…” | AE11: DECLARADO — “…Se ha sentenciado sobre una causal no determinada como punto controvertido materia de Probanza o thema decidendum, acarreando un estado de indefensión a las partes del proceso, pues el hecho que el A quo, comunique a las partes mediante resolución Nro. 2…” | AP11: Migración D06→D16 · Baja D15→— · Sustitución de cita D16→D16 | BB11: Comparativa_defectos_2018_vs_2024 + Defectos_procesales_SV_CSJA | BC11: 2 | BD11: CONOCIMIENTO | BE11: NULA | BF11: CN
A12: 11 | B12: 00367-2024 | C12: 00367-2024-0-0401-JR-CI-10 | D12: Matriz sumarísimos — grupo 2024 | E12: Desalojo por ocupación precaria | F12: 1SC | G12: SV 338-2024-1SC | H12: Res. 12 (tres-1SC) | I12: 22/07/2024 | J12: 2024 | K12: Zoraida Julia Salas Flores | M12: REVOCADA → INFUNDADA | N12: 0 | O12: 0 | AZ12: Sin vicio procesal declarado respecto de la sentencia apelada. La Sala observa un error de juzgamiento en un proceso anterior (Exp. 1999-0488) ajeno a esta causa. | BB12: Matriz_defectos_procesales_1ra_SV | BC12: 1 | BD12: SUMARISIMO | BE12: REVOCADA | BF12: SR
A13: 12 | B13: 00414-2023 | C13: 00414-2023-0-0401-JR-CI-02 | D13: Llamoja — SV de control (2021-2023) | E13: Enriquecimiento sin causa / indemnización | F13: 3SC | G13: 178-2025-3SC | H13: 18 | I13: dos mil veinticinco, Mayo veintiuno | J13: 2025 | L13: Burga Cervantes | M13: NULA | N13: 2 | O13: 2 | AB13: DECLARADO — (evidencia en las columnas «Cita textual 1–3» de esta misma fila) | AE13: DECLARADO — (evidencia en las columnas «Cita textual 1–3» de esta misma fila) | AQ13: d) Motivación insuficiente | AR13: e) Motivación sustancialmente incongruente | AS13: No | AT13: «El juez no ha motivado su resolución, por lo que esta adolece de debida motivación, por no haberse pronunciado sobre todos los hechos controvertidos y justificar objetivamente las razones de su decisión.» | AU13: d)/e): no se pronuncia sobre todos los hechos controvertidos | AV13: «En consecuencia, la sentencia apelada no se encuentra conforme a derecho y debe ser declarada nula, para que el juzgado A quo emita pronunciamiento de fondo sobre la pretensión incoada por la parte demandante.» | AW13: Efecto: nulidad y pronunciamiento de fondo | AZ13: 'No haberse pronunciado sobre todos los hechos controvertidos y justificar objetivamente las razones'. Improcedencia declarada en sentencia; ordena pronunciamiento de fondo. | BA13: 414 2023 SV.doc | BB13: Clasificacion_SV_ABR24_Llamoja_defectos | BC13: 1 | BD13: ABREVIADO | BE13: NULA | BF13: AN
A14: 13 | B14: 00428-2017 | C14: 00428-2017-0-0401-JP-CI-02 | D14: Matriz sumarísimos — anteriores a 2019 | E14: Desalojo por ocupación precaria | F14: 2SC | G14: SV 033-2020-2SC | H14: Res. 23 (cinco-2SC) | I14: 17/01/2020 | J14: 2020 | K14: Carlos Polanco Gutiérrez | M14: REVOCADA → FUNDADA | N14: 0 | O14: 2 | AB14: ADVERTIDO — «el juez tampoco ha cumplido con exponer razones o motivos propios por los cuales considera que en el caso en concreto se debe considerar el vínculo familiar de conviviente como título para poseer» | AJ14: ADVERTIDO — «lo que evidencia que la sentencia tiene una motivación defectuosa, lo cual afecta la validez la recurrida ya que se ha vulnerado el derecho del demandante a una resolución debidamente motivada» | AP14: Migración D15→D21 · Reclasificación de estatus —→ADV | AZ14: Uso de casaciones sobre supuestos fácticos distintos («su aplicación en autos es equivocada ya que no se tratan de supuestos similares»). Pese al vicio, la Sala revoca y falla el fondo (rebeldía de la demandada). | BB14: Matriz_defectos_procesales_1ra_SV | BC14: 1 | BD14: SUMARISIMO | BE14: REVOCADA | BF14: SR
A15: 14 | B15: 00598-2022 | C15: 00598-2022 | D15: 2024 | F15: 3SC | G15: SV N° 256-2025-3SC | I15: 20/06/2025 | J15: 2025 | M15: Nula | N15: 2 | O15: 2 | AA15: DECLARADO — “…denotarían la supuesta existencia de irregularidades en la partida de nacimiento de la demandante, de carácter formal, no habiendo valorado el contexto en el que se expide la partida de nacimiento y otras que han sido desarrolladas en la presente resolución; por lo que corresponde declarar nula la sentencia venida en grado, disponiendo que el Juez de origen emita un nuevo p…” | AB15: DECLARADO — “…vierte que el Juez de primera instancia no ha realizado un análisis suficiente de lo actuado en autos, habiéndose centrado en las cuestiones que denotarían la supuesta existencia de irregularidades en la partida de nacimiento de la demandante, de carácter formal, no habiendo valorado el contexto en e…” | BB15: Comparativa_defectos_2018_vs_2024 + Defectos_procesales_SV_CSJA | BC15: 2 | BD15: CONOCIMIENTO | BE15: NULA | BF15: CN
A16: 15 | B16: 00646-2024 | C16: 00646-2024-0-0401-JR-CI-01 | D16: Matriz sumarísimos — grupo 2024 | E16: Desalojo por ocupación precaria | F16: 2SC | G16: SV 240-2025-2SC | H16: Res. 21 (tres-2SC) | I16: 23/05/2025 | J16: 2025 | K16: Shelah Galagarza Pérez | M16: NULA (reenvío) | N16: 3 | O16: 3 | AA16: DECLARADO — «No ha tomado en cuenta que, a la parte demandada le corresponde desvirtuar la condición de precario que se le imputa, todo ello en virtud del principio de reversión de la carga de la prueba, contemplada por el artículo 196 del Código Procesal Civil» | AE16: DECLARADO — «si bien el A quo se ha pronunciado sobre la codemandada Ana María Meneses Portugal; sin embargo, ha omitido pronunciarse sobre la condición de poseedores precarios que se imputa a los codemandados Walter Cisneros Meneses, Dalia Cisneros Meneses» | AL16: DECLARADO — «se tiene que se ha vulnerado el inciso 5º del artículo 139 de nuestra constitución» | AP16: Baja D11→— · Migración D13→D23 | AZ16: Incongruencia omisiva respecto de dos codemandados declarados rebeldes e inversión indebida de la carga de la prueba. | BB16: Matriz_defectos_procesales_1ra_SV | BC16: 1 | BD16: SUMARISIMO | BE16: NULA | BF16: SN
A17: 16 | B17: 00661-2023 | C17: 00661-2023-0-0401-JP-CI-06 | D17: Matriz sumarísimos — grupo 2024 | E17: Obligación de dar suma de dinero | F17: 2SC | G17: SV 302-2025-2SC | H17: Res. 18 (cuatro-2SC) | I17: 27/06/2025 | J17: 2025 | K17: Edgard Pineda Gamarra | M17: NULA (reenvío) | N17: 2 | O17: 2 | AA17: DECLARADO — «se evidencia que el juzgador no ha efectuado una debida valoración de los medios probatorios y actuados obrantes en el caso de autos» | AB17: DECLARADO — «incurriéndose en vicio procesal por motivación insuficiente para la dilucidación de los hechos materia de litis» | AP17: Baja D11→— | AZ17: La rebeldía (art. 461 CPC) no exime del análisis; la Sala recuerda la facultad de prueba de oficio (art. 194 CPC). | BB17: Matriz_defectos_procesales_1ra_SV | BC17: 1 | BD17: SUMARISIMO | BE17: NULA | BF17: SN
A18: 17 | B18: 00742-2022 | C18: 00742-2022 | D18: 2024 | G18: SV N° 196-2025 | I18: 16/05/2025 | J18: 2025 | M18: Otro | N18: 4 | O18: 4 | Q18: DECLARADO — “…ste proceder habría resultado legítimo en la medida de que, el juez de primera instancia hubiese promovido un debido contradictorio respecto de esta causal de nulidad de acto jurídico no invocada. Una forma de verificar que no se promovió el contradictorio respecto de esta causal de nulidad, es analizar los pu…” | S18: DECLARADO — “…udible no resaltar que en la página quince de la sentencia, el juez ha incurrido en un gravísimo error al aceptar como ciertos los argumentos expuestos en la contestación del demandado Andrés Saya Alarcón, que en la presente causa ostenta la posición de rebelde y la cual fue expresamente declarada improcedente en la resolución N.° 7 del mismo despacho. Este h…” | Z18: DECLARADO — “…La falta de valoración de pruebas clave que demuestran la titularidad de William Canazas Carta genera un claro desbalance en el proceso, al ignorar evidencias que podrían haber conducido a un resultado judicial diferente. p) La jurisprudencia establece que el…” | AE18: DECLARADO — “…urídico no invocada. Una forma de verificar que no se promovió el contradictorio respecto de esta causal de nulidad, es analizar los puntos controvertidos (fojas cuatrocientos setenta y seis), en donde se advierte que ninguno de estos plantea la controversia de la causal de imposibilidad jurídica por el objeto. Es evidente que haber omitido establecer esta causal (imposib…” | AP18: Migración D10→D02 · Migración D06→D16 · Sustitución de cita D16→D16 | BB18: Comparativa_defectos_2018_vs_2024 + Defectos_procesales_SV_CSJA | BC18: 2 | BD18: CONOCIMIENTO | BE18: OTRO | BF18: CO
A19: 18 | B19: 00748-2013 | C19: 00748-2013 | D19: Pre-2019 | F19: 2SC | G19: SV N° 674-2018-2SC | I19: 28/12/2018 | J19: 2018 | M19: Nula | N19: 1 | O19: 1 | AD19: DECLARADO — “…azonamiento conforme al Tribunal Constitucional. En conclusión, en mérito a lo expuesto precedentemente se concluye que la sentencia recurrida no se encuentra debidamente motivada contraviniendo de esta manera no sólo lo establecido en el inciso 3) del artículo 122 del Código Procesal Civil, sino también lo dispuesto en el inciso 5) del artículo 139 de nuestra Constitución Política, por lo que co…” | AO19: Cita truncada al inicio: verificar en el original si el Colegiado califica el vicio como falta de motivación interna o emplea una fórmula genérica. | BB19: Comparativa_defectos_2018_vs_2024 + Defectos_procesales_SV_CSJA | BC19: 2 | BD19: CONOCIMIENTO | BE19: NULA | BF19: CN
A20: 19 | B20: 00760-2021 | C20: 00760-2021-0-0401-JP-CI-07 | D20: Llamoja — SV de control (2021-2023) | E20: Obligación de dar suma de dinero | F20: 3SC | G20: 34-2025-3SC | H20: 31 | I20: dos mil veinticinco, Enero veintinueve | J20: 2025 | L20: Marroquín Mogrovejo | M20: NULA | N20: 2 | O20: 2 | W20: DECLARADO — (evidencia en las columnas «Cita textual 1–3» de esta misma fila) | Y20: DECLARADO — (evidencia en las columnas «Cita textual 1–3» de esta misma fila) | AQ20: — Sin vicio de motivación como causal | AS20: No | AT20: «Así las cosas, tenemos que la decisión se ha emitido sin que el juez de la causa haya garantizado el derecho de las partes de propiciar y conducir el debate de manera previa a su decisión, vulnerando de ese modo su derecho al contradictorio, al sustentar la decisión en la valoración sorpresiva de pruebas no admitidas en el proceso y sobre las que ambas partes, no se permitió que ejerzan el derecho que corresponda en forma previa a su valoración y posterior decisión; por tanto, se ha incurrido en nulidad que debe ser declarada por esta sala al haber resuelto sin tener en cuenta el mérito de lo actuado conforme exige el inciso 3 del artículo 122° del Código Procesal Civil.» | AU20: Falta de contradictorio: valoración sorpresiva de prueba no admitida | AV20: «Por otro lado, si los documentos mencionados tiene relevancia e incidencia determinante en la litis, en todo caso, el juez de la causa debió, en forma previa a emitir sentencia, ejercer la facultad prevista en el artículo 194° del Código Procesal Civil “…que confiere al juez un poder probatorio con carácter de facultad excepcional … esta disposición legal habilita al juez a realizar prueba de oficio, cuando el caso así lo amerite, respetando los límites impuestos por el legislador” como lo establece la casación número 1242-2017 Lima Este; lo que no hizo y que debe evaluar el juez de primera instancia.» | AW20: Prueba de oficio no ejercida (art. 194 CPC; Cas. 1242-2017) | AZ20: Valoración sorpresiva de pruebas no admitidas, sin contradictorio (art. 122.3 CPC). El agravio habla de 'indebida motivación', pero la Sala anula por vicio probatorio-procesal. | BA20: 760 2021 SV 2025.doc | BB20: Clasificacion_SV_ABR24_Llamoja_defectos | BC20: 1 | BD20: ABREVIADO | BE20: NULA | BF20: AN
A21: 20 | B21: 00774-2021 | C21: 00774-2021-0-0401-JR-CI-05 | D21: Llamoja — SV de control (2021-2023) | E21: División y partición | F21: 2SC | G21: 161-2025-2SC | H21: 28 | I21: dos mil veinticinco, Abril catorce | J21: 2025 | L21: Yucra Quispe | M21: NULA | N21: 2 | O21: 2 | AE21: DECLARADO — (evidencia en las columnas «Cita textual 1–3» de esta misma fila) | AJ21: DECLARADO — (evidencia en las columnas «Cita textual 1–3» de esta misma fila) | AP21: Migración D20→D21 | AQ21: c) Deficiencia de motivación externa | AS21: No | AT21: «Conforme a lo señalado, al haberse emitido la sentencia, sin tener en cuenta lo señalado en el punto anterior, se ha vulnerado el derecho a la tutela jurisdiccional prevista en el inciso 3 del artículo 139 de nuestra constitución, por lo que al amparo de lo establecido en el artículo 176 , concordante con el 171 del Código Procesal Civil debe anularse la apelada.» | AU21: c) Premisa no confrontada con los hechos de la demanda (139.3) | AV21: «De la revisión de los actuados, se tiene que, el juzgador al emitir la apelada: a) No ha tomado en cuenta que, tratándose de la pretensión de división y partición, los hechos que se invoquen deben estar referidos a: 1) La existencia de un estado de copropiedad sobre un bien; 2) Que el bien no haya sido objeto de división y partición; 3) Que los copropietarios sean titulares de derechos sobre el bien; b) No ha tomado en cuenta que, la causal de improcedencia de la demanda de falta de conexión lógica entre los hechos y el petitorio prevista en el inciso 4° del artículo 427 del Código procesal Civil, se da cuando se advierte la evidente incongruencia entre lo que se solicita(pide) en el petitorio de la pretensión demandada y los fundamentos de hecho que sustentan dicha pretensión, es decir que los hechos que se invoca no están referidos a los supuestos de procedencia objeto del proceso; c) No ha tomado en cuenta que, cuando se formula una pretensión en el escrito de demanda, los hechos que se invoquen como sustento del petitorio, deben estar referidos necesariamente a los supuesto de procedencia de la institución jurídica material que se invoca en el petitorio de la demanda; d) No ha tomado en cuenta que, en el escrito de demanda de fojas dieciséis al veinte, subsanada a fojas cuarenta y cuatro al cuarenta y seis, se advierte que Pedro Isaias Pertalta Vilca, ha interpuesto la pretensión de división y participación del bien inmueble ubicado en el Pueblo Joven La Tomilla Manzana N, Lote 25, Zona A del distrito de Cayma, provincia y departamento de Arequipa, debidamente inscrito en la Partida registral del Predio número P06003392 del registro de Predios de los registros Públicos de Arequipa; en cuyos fundamentos facticos, ha invocado la existencia de un estado de copropiedad del bien objeto de litis, entre el demandante y los demandados Genaro Mercedes Peralta Vilca, Raymunda Emperatriz Peralta Vilca y Jesús Avelino Peralta Vilca y ha señalado los porcentajes que corresponderían a cada uno de los copropietarios; los que están referidos a los supuestos de procedencia de la pretensión de división y partición, ya que, los hechos invocado en la demanda están referidos a la existencia de un estado de copropiedad sobre el bien objeto de litis, que el bien no ha sido objeto de división y partición, y que los copropietarios demandante y demandados son titulares de derechos sobre el bien inmueble ubicado en el Pueblo Joven La Tomilla Manzana N, Lote 25, Zona A del distrito de Cayma, provincia y departamento de Arequipa, debidamente inscrito en la Partida registral del Predio número P06003392.» | AW21: Concepto de incongruencia aplicado al art. 427.4 CPC | AZ21: Improcedencia (art. 427.4) sin confrontar los hechos de la demanda que sí describen copropiedad. La Sala invoca 139.3 (tutela) y no etiqueta vicio de motivación. c) tentativo. | BA21: 774 2021 SV 2025.doc | BB21: Clasificacion_SV_ABR24_Llamoja_defectos | BC21: 1 | BD21: ABREVIADO | BE21: NULA | BF21: AN
A22: 21 | B22: 00788-2013 | C22: 00788-2013 | D22: Pre-2019 | F22: 2SC | G22: SV N° 191-2021-2SC | I22: 01/03/2021 | J22: 2021 | M22: Nula | N22: 1 | O22: 1 | AE22: DECLARADO — “…es decir, emitió un pronunciamiento distinto a lo alegado por la parte demandante y a las fijadas en los puntos controvertidos, lo que evidencia que en el caso subjúdice el A quo ha emitido una sentencia extra petita, amparándose para ello en el principio del iura novit curia. Empero, si bien el juzgador ha aplicado el principio del i…” | AP22: Baja D06→— | BB22: Comparativa_defectos_2018_vs_2024 + Defectos_procesales_SV_CSJA | BC22: 2 | BD22: CONOCIMIENTO | BE22: NULA | BF22: CN
A23: 22 | B23: 00848-2011 | C23: 00848-2011-0-0411-JR-CI-08 | D23: Matriz sumarísimos — anteriores a 2019 | E23: Otorgamiento de escritura pública | F23: 3SC | G23: SV 309-2019-3SC | H23: Res. 58 (cuatro) | I23: 27/05/2019 | J23: 2019 | K23: Ronald Valencia de Romaña | M23: REVOCADA → FUNDADA EN PARTE | N23: 0 | O23: 1 | AA23: ADVERTIDO — «el Juez a quo no ha realizado una valoración conjunta, razonada y adecuada de los medos probatorios aportados al proceso; al documento de compraventa del siete de octubre de mil novecientos ochenta y dos… no se le ha asignado el valor probatorio sobre la real intención de las partes» | AP23: Migración D11→D12 | AZ23: La Sala invoca expresamente la Circular sobre reenvío (RA N° 002-2014-CE-PJ) y opta por corregir en instancia en lugar de anular. | BB23: Matriz_defectos_procesales_1ra_SV | BC23: 1 | BD23: SUMARISIMO | BE23: REVOCADA | BF23: SR
A24: 23 | B24: 00856-2017 | C24: 00856-2017 | D24: Pre-2019 | F24: 1SC | G24: SV N° 525-2019-1SC | I24: 01/08/2019 | J24: 2019 | M24: Nula e insubsistente | N24: 1 | O24: 1 | AE24: DECLARADO — “…se ha incurrido en causal de nulidad por falta de motivación de una pretensión accesoria, y corresponderá al juez emitir nuevo pronunciamiento tomando en cuenta la doctrina Jurisprudencial vinculante emitida en el IV Pleno Casatorio Civil, Casación N° 2195-2011-UCAYALI, en el entendido d…” | AP24: Migración D15→D16 | BB24: Comparativa_defectos_2018_vs_2024 + Defectos_procesales_SV_CSJA | BC24: 2 | BD24: CONOCIMIENTO | BE24: NULA | BF24: CN
A25: 24 | B25: 00879-2022 | C25: 00879-2022-0-0401-JR-CI-02 | D25: Llamoja — SV de control (2021-2023) | E25: Indemnización (Contraloría) | F25: 1SC | H25: 28 | I25: dos mil veinticinco, julio cuatro | J25: 2025 | L25: Cervantes López | M25: NULA | N25: 2 | O25: 2 | AD25: DECLARADO — (evidencia en las columnas «Cita textual 1–3» de esta misma fila) | AE25: DECLARADO — (evidencia en las columnas «Cita textual 1–3» de esta misma fila) | AQ25: e) Motivación sustancialmente incongruente | AR25: b) Falta de motivación interna | AS25: Sí | AT25: «En consecuencia, es evidente el error de incongruencia incurrido por el juez A quo, al modificar o alterar el objeto de debate del proceso (fijado como primer hecho controvertido en la audiencia preliminar digitalizada a fojas cinco mil doscientos ochenta y tres); esto es, sobre el factor de atribución imputado a la parte demandada (culpa inexcusable) y la valoración jurídica efectuada en la decisión (existencia de dolo), lo que afecta el debido proceso en su vertiente al derecho a una debida motivación de las resoluciones judiciales.» | AU25: e) Incongruencia sustancial / Incongruencia procesal | AV25: «Sin perjuicio de lo señalado, del análisis de la recurrida se puede advertir también, falta de motivación interna del razonamiento empleado.» | AW25: b) Falta de motivación interna | AX25: «En consecuencia, estando a lo expuesto se concluye que la recurrida incurre en causal de nulidad prevista y sancionada en el artículo 171 concordante con el artículo 122 del Código Procesal Civil, debiendo el juez A quo emitir nueva resolución teniendo en cuenta lo señalado en la presente.» | AY25: Efecto: nulidad (arts. 171 y 122 CPC) | AZ25: La Sala cita expresamente los supuestos b) y e) de la STC 00728-2008-PHC/TC; alteró el objeto de debate (culpa inexcusable → dolo). | BA25: 879 2022 SV 2025.doc | BB25: Clasificacion_SV_ABR24_Llamoja_defectos | BC25: 1 | BD25: ABREVIADO | BE25: NULA | BF25: AN
A26: 25 | B26: 00898-2013 | C26: 00898-2013 | D26: Pre-2019 | F26: 3SC | G26: SV N° 550-2018-3SC | I26: 26/10/2018 | J26: 2018 | M26: Revocada | N26: 0 | O26: 1 | AE26: ADVERTIDO — “…obre algún punto principal o accesorio. En este caso, en la parte resolutiva de la ampulosa sentencia materia de grado, se ha omitido declarar la nulidad de los actos jurídicos contenidos en las escrituras cuya nulidad se ha demandado como pretensiones principales, no obstante haberse analizado dichos aspectos en la parte considerativa, por lo que, debe integrarse la sentencia recurrida en ese sentido.…” | AP26: Reclasificación de estatus —→ADV | BB26: Comparativa_defectos_2018_vs_2024 + Defectos_procesales_SV_CSJA | BC26: 2 | BD26: CONOCIMIENTO | BE26: REVOCADA | BF26: CR
A27: 26 | B27: 00933-2022 | C27: 00933-2022-0-0401-JR-CI-07 | D27: Llamoja — SV de control (2021-2023) | E27: Obligación de dar suma de dinero | F27: 3SC | G27: 72-2024-3SC | H27: 24 | I27: dos mil veinticuatro, Marzo ocho | J27: 2024 | L27: Burga Cervantes | M27: NULA | N27: 2 | O27: 2 | AC27: DECLARADO — (evidencia en las columnas «Cita textual 1–3» de esta misma fila) | AE27: DECLARADO — (evidencia en las columnas «Cita textual 1–3» de esta misma fila) | AP27: Migración D17→D14 | AQ27: a) Inexistencia / motivación aparente | AR27: e) Motivación sustancialmente incongruente | AS27: Sí | AT27: «Siendo así, se advierte que la sentencia objeto de apelación ha incurrido en el vicio consistente en ausencia de motivación, puesto que se ha omitido emitir pronunciamiento sobre el hecho impeditivo expuesto como defensa de fondo por el recurrente Ronald Federico Companoca Coaquira.» | AU27: a) Ausencia de motivación (etiqueta expresa) | AV27: «Ahora, de la revisión de la sentencia que viene en grado de apelación, precisamente del considerando tercero, se advierte que el Juez a quo ha omitido emitir pronunciamiento sobre el hecho impeditivo expuesto como defensa de fondo por el recurrente Ronald Federico Companoca Coaquira.» | AW27: Incongruencia omisiva: omite el hecho impeditivo | AZ27: Etiqueta expresa 'ausencia de motivación' por omitir el hecho impeditivo (defensa de fondo). Materialmente es incongruencia omisiva. SV 72-2024-3SC (menor año; existe SV 471-2025-3SC que revoca). | BA27: 933 2022 SV 2023.doc | BB27: Clasificacion_SV_ABR24_Llamoja_defectos | BC27: 1 | BD27: ABREVIADO | BE27: NULA | BF27: AN
A28: 27 | B28: 00965-2015 | C28: 00965-2015 | D28: Pre-2019 | F28: 3SC | G28: SV N° 498-2019-3SC | I28: 03/07/2019 | J28: 2019 | M28: Nula | N28: 2 | O28: 2 | U28: DECLARADO — “…e se decide u ordena, respecto de todos los puntos controvertidos, que al haberse emitido sin los requisitos señalados, se ha incurrido en causal de nulidad y que este colegiado debe sancionar en aplicación del artículo 176 del acotado Código, reponiéndose el proceso al estado de fijarse los puntos controvertidos de acuerdo a la pretensión demandada y la contestación de la demandada, dejando subsistente la in…” | AL28: DECLARADO — “…requisitos que deben contener las Resoluciones tales como los fundamentos de hecho que sustentan la decisión, y los respectivos de derecho con la cita de la norma o normas aplicables en cada punto, según el mérito de lo actuado. La expresión clara y precisa de lo que se decide u ordena, respecto de to…” | AP28: Migración D15→D23 | BB28: Comparativa_defectos_2018_vs_2024 + Defectos_procesales_SV_CSJA | BC28: 2 | BD28: CONOCIMIENTO | BE28: NULA | BF28: CN
A29: 28 | B29: 00979-2024 | C29: 00979-2024-0-0401-JR-CI-06 | D29: Matriz sumarísimos — grupo 2024 | E29: Ineficacia de acto jurídico (excepciones) | F29: 1SC | G29: Auto de Vista 960-2025-1SC | H29: Res. 26 (seis-1SC) | I29: 17/09/2025 | J29: 2025 | K29: Patricia Ruby Valdivia Franco | M29: CONFIRMADA | N29: 0 | O29: 0 | AZ29: OBSERVACIÓN DE CORPUS: es un AUTO DE VISTA sobre excepciones, no una sentencia de vista sobre el fondo. Sin vicio procesal declarado. | BB29: Matriz_defectos_procesales_1ra_SV | BC29: 1 | BD29: SUMARISIMO | BE29: CONFIRMADA | BF29: SF
A30: 29 | B30: 00992-2016 | C30: 00992-2016 | D30: Pre-2019 | F30: 3SC | G30: SV N° 76-2019-3SC | I30: 08/03/2019 | J30: 2019 | M30: Otro | N30: 2 | O30: 2 | AE30: DECLARADO — “…o 04003327. Que, la sentencia recurrida ha omitido pronunciarse sobre el fondo del asunto, señalando como presupuesto la aclaración sobre el heredero poseedor, sin analizar las declaraciones contenidas en la demanda, ya que los demandantes no tomaron conocimiento previo de estos hechos por tener domicilio en…” | AL30: DECLARADO — “…la sentencia apelada incurre en causal de nulidad prevista por el artículo 122 párrafo penúltimo concordante con el artículo 171 del Código Procesal Civil. Se deja constancia que la Sala Superior, se encuentra impedida de emitir pronunciamiento de fondo, para garantizar el dere…” | AP30: Migración D17→D16 · Migración D15→D23 | BB30: Comparativa_defectos_2018_vs_2024 + Defectos_procesales_SV_CSJA | BC30: 2 | BD30: CONOCIMIENTO | BE30: OTRO | BF30: CO
A31: 30 | B31: 01033-2023 | C31: 01033-2023-0-0401-JR-CI-04 | D31: Llamoja — SV de control (2021-2023) | E31: Indemnización (ONP) | F31: 2SC | G31: 470-2025-2SC | H31: 24 | I31: dos mil veinticinco, Setiembre treinta | J31: 2025 | L31: de la Cuba Chirinos | M31: NULA DE OFICIO | N31: 1 | O31: 1 | AE31: DECLARADO — (evidencia en las columnas «Cita textual 1–3» de esta misma fila) | AM31: Sí | AP31: Baja D13→— | AQ31: e) Motivación sustancialmente incongruente | AS31: No | AT31: «En ese sentido, existe manifiesta incongruencia entre lo que se pretendió en la demanda – responsabilidad civil contractual – y, lo que se ha resuelto en la sentencia, confundiendo ambos tipos de responsabilidad civil en su fundamento jurídico, estableciendo que el hecho objeto de probanza es la responsabilidad contractual; y, aplicando indistintamente las reglas jurídicas de ambas.» | AU31: e) Incongruencia sustancial (contractual vs. extracontractual) | AV31: «Aun cuando la nulidad procesal es de último recurso, en el caso concreto, no puede esta instancia superior superar tales vicios de motivación, pues se trata de defectos graves insubsanables.» | AW31: Efecto: nulidad de oficio, vicios insubsanables | AX31: «En consecuencia, debe declararse la nulidad de la sentencia apelada, debiendo el juez de primera instancia cumplir con determinar el tipo de responsabilidad civil en la cual nos encontramos; analizando la aplicación de principios para sustanciar de modo correcto la pretensión del actor en los hechos y fundamento jurídico invocado.» | AY31: Alcance del reenvío: determinar el tipo de responsabilidad | AZ31: 'Manifiesta incongruencia' entre lo pretendido (resp. contractual) y lo resuelto; confusión de regímenes de responsabilidad. | BA31: 1033 2023 SV.doc | BB31: Clasificacion_SV_ABR24_Llamoja_defectos | BC31: 1 | BD31: ABREVIADO | BE31: NULA | BF31: AN
A32: 31 | B32: 01101-2022 | C32: 01101-2022 | D32: 2024 | F32: 2SC | G32: SV N° 226-2025-2SC | I32: 16/05/2025 | J32: 2025 | M32: Nula | N32: 1 | O32: 1 | AL32: DECLARADO — “…lo no es posible particularmente en este caso, debido a que el error en la motivación de la recurrida, contraviene de esta manera no sólo lo establecido en el numeral 3) del artículo 122 del T.U.O. del Código Procesal Civil, sino también lo dispuesto en el numeral 5) del artículo 139 de nuestra Constitución Política, po…” | AP32: Migración D15→D23 | BB32: Comparativa_defectos_2018_vs_2024 + Defectos_procesales_SV_CSJA | BC32: 2 | BD32: CONOCIMIENTO | BE32: NULA | BF32: CN
A33: 32 | B33: 01286-2022 | C33: 01286-2022 | D33: 2024 | F33: 2SC | G33: SV N° 341-2025-2SC | I33: 18/07/2025 | J33: 2025 | M33: Nula e insubsistente | N33: 2 | O33: 3 | P33: DECLARADO — “…ntencia fue expedida incumpliendo el inciso 3) del artículo 139º de la Constitución Política del Estado, en concordancia con el artículo I del título preliminar del código procesal civil y el artículo 165º del código procesal civil, ya que todas las notificaciones se han efectuado en un domicilio que no es el suyo. 4.4. Al respecto,…” | Q33: DERIVADO — “…esales posteriores, incluida la sentencia. En consecuencia, se vulneró su derecho de defensa y contradicción, configurándose así una infracción al debido proceso. Este vicio procesal resulta ser insubsanable, al haber impedido l…” | S33: DECLARADO — “…tubre de dos mil veintidós [ver de fojas 337 a 339 del eje] se declara rebelde al recurrente Rossvel Gregorio Mamani Chire, además se indica, que debe notificársele con arreglo a lo dispuesto por el artículo 459º del código procesal civil. Asimismo, la mencionada resolución fue notificada al…” | AM33: Sí | AO33: D04: la cita registrada es narrativa (refiere la declaración de rebeldía y el art. 459 CPC) y no contiene juicio sobre su invalidez. Sustituir por el pasaje que anula los actos desde la Res. N° 04. | AP33: Baja D08→— · Baja D20→— · Reclasificación de estatus D02→D02 (derivado) | BB33: Comparativa_defectos_2018_vs_2024 + Defectos_procesales_SV_CSJA | BC33: 2 | BD33: CONOCIMIENTO | BE33: NULA | BF33: CN
A34: 33 | B34: 01328-2023 | C34: 01328-2023 | D34: 2024 | F34: 2SC | G34: SV N° 155-2025-2SC | I34: 08/04/2025 | J34: 2025 | M34: Revocada | N34: 0 | O34: 0 | BB34: Comparativa_defectos_2018_vs_2024 + Defectos_procesales_SV_CSJA | BC34: 2 | BD34: CONOCIMIENTO | BE34: REVOCADA | BF34: CR
A35: 34 | B35: 01376-2023 | C35: 01376-2023 | D35: 2024 | F35: 2SC | G35: SV N° 033-2026-2SC | I35: 23/01/2026 | J35: 2026 | M35: Revocada | N35: 2 | O35: 2 | AA35: DECLARADO — “…rente que la jueza de primera instancia incurre en omisión en cuanto a la valoración conjunta y razonada de los medios probatorios admitidos de la parte demandante y en consecuencia se ha constituido un vicio in procedendo debido que todos los medios probatorios admitidos por la jueza de primera instancia deben ser valorados en forma conjunta o en…” | AH35: DECLARADO — “…ción N° 07 de fecha tres de noviembre de dos mil veintitrés [ver fojas 232 y 233 del EJE], en donde se declaró improcedente tanto la contestación de la demanda como la reconvención por extemporánea en relación al condemandado Alfredo Joaquín Flores Apaza y disponiendo que el juzgado de primera instancia proceda a calificar la contestación de la demanda y…” | AO35: La cita registrada en D20 es literalmente idéntica a la CITA1 del expediente 04965-2023. Verificar en el original antes de conservar el registro. | AP35: Migración D11→D12 · Migración D08→D19 · Baja D20→— | BB35: Comparativa_defectos_2018_vs_2024 + Defectos_procesales_SV_CSJA | BC35: 2 | BD35: CONOCIMIENTO | BE35: REVOCADA | BF35: CR
A36: 35 | B36: 01417-2017 | C36: 01417-2017 | D36: Pre-2019 | F36: 2SC | G36: SV N° 004-2020-2SC | I36: 03/01/2020 | J36: 2020 | M36: Nula | N36: 1 | O36: 1 | AL36: DECLARADO — “…en mérito a lo expuesto precedentemente se concluye que la sentencia recurrida no se encuentra debidamente motivada, contraviniendo de esta manera lo establecido en el segundo párrafo del artículo 122 del Código Procesal Civil, por lo que, corresponde declarar la nulidad de la apelada, de conformidad con el artículo 171 del Código Procesal acotado. PARTE RESOLUTIVA: Fundamentos…” | AP36: Migración D15→D23 | BB36: Comparativa_defectos_2018_vs_2024 + Defectos_procesales_SV_CSJA | BC36: 2 | BD36: CONOCIMIENTO | BE36: NULA | BF36: CN
A37: 36 | B37: 01535-2022 | C37: 01535-2022 | D37: 2024 | F37: 2SC | G37: SV N° 572-2024-2SC | I37: 11/12/2024 | J37: 2024 | M37: Nula | N37: 2 | O37: 2 | Z37: DECLARADO — “…n apelada no se ha dado una respuesta debidamente razonada al justiciable, pues se ha omitido valorar los argumentos expuestos por la parte apelante, así como los medios probatorios adjuntos al escrito de solicitud de medida cautelar, existiendo una motivación aparente, la cual es entendida por el Tribunal Constitucional como…” | AC37: DECLARADO — “…a que a través de la resolución apelada no se ha dado una respuesta debidamente razonada al justiciable, pues se ha omitido valorar los argumentos expuestos por la parte apelante, así como los medios probatorios adjuntos al escrito de solicitud de medida cautelar…” | AP37: Migración D15→D14 | BB37: Comparativa_defectos_2018_vs_2024 + Defectos_procesales_SV_CSJA | BC37: 2 | BD37: CONOCIMIENTO | BE37: NULA | BF37: CN
A38: 37 | B38: 01549-2017 | C38: 01549-2017-0-0401-JR-CI-04 | D38: Matriz sumarísimos — anteriores a 2019 | E38: Otorgamiento de escritura pública | F38: 2SC | G38: SV 173-2019-2SC | H38: Res. 18 (tres-2SC) | I38: 10/05/2019 | J38: 2019 | K38: Justo Quispe Apaza | M38: REVOCADA → IMPROCEDENTE | N38: 0 | O38: 0 | AZ38: Sin vicio procesal declarado. La revocatoria se funda en error de derecho sustantivo (condición suspensiva no acreditada; IX Pleno Casatorio). | BB38: Matriz_defectos_procesales_1ra_SV | BC38: 1 | BD38: SUMARISIMO | BE38: REVOCADA | BF38: SR
A39: 38 | B39: 01647-2019 | C39: 01647-2019 | D39: 2024 | F39: 2SC | G39: SV N° 082-2026-2SC | I39: 18/03/2026 | J39: 2026 | M39: Nula | N39: 2 | O39: 2 | AA39: DECLARADO — “…uye, que al haberse expedido la sentencia materia de grado, sin que se haya realizado un análisis conjunto y razonado de los medios probatorios admitidos y actuados en el proceso como lo dispone el artículo 197 del Código Procesal Civil, se ha vulnerado el principio al debido proceso y el de motivación establecido en los incisos 3° y 5° del artículo 139 de nues…” | AC39: DECLARADO — “…al debido proceso y el de motivación establecido en los incisos 3° y 5° del artículo 139 de nuestra constitución; pues nos encontramos ante una motivación aparente; por lo que, en aplicación de lo dispuesto por el artículo 176, concordante con el 171 del Código Procesal Civil debe d…” | AP39: Migración D11→D12 | BB39: Comparativa_defectos_2018_vs_2024 + Defectos_procesales_SV_CSJA | BC39: 2 | BD39: CONOCIMIENTO | BE39: NULA | BF39: CN
A40: 39 | B40: 01650-2023 | C40: 01650-2023 | D40: 2024 | G40: SV N° 267-2025 | I40: 30/06/2025 | J40: 2025 | M40: Revocada | N40: 0 | O40: 0 | BB40: Comparativa_defectos_2018_vs_2024 + Defectos_procesales_SV_CSJA | BC40: 2 | BD40: CONOCIMIENTO | BE40: REVOCADA | BF40: CR
A41: 40 | B41: 01681-2023 | C41: 01681-2023-0-0401-JR-CI-01 | D41: Llamoja — SV de control (2021-2023) | E41: División y partición | F41: 3SC | G41: 219-2025-3SC | H41: 39 | I41: dos mil veinticinco, Junio seis | J41: 2025 | L41: Marroquín Mogrovejo | M41: NULA (reposición hasta puntos controvertidos) | N41: 2 | O41: 2 | U41: DECLARADO — (evidencia en las columnas «Cita textual 1–3» de esta misma fila) | AD41: DECLARADO — (evidencia en las columnas «Cita textual 1–3» de esta misma fila) | AQ41: b) Falta de motivación interna | AR41: a) Inexistencia / motivación aparente | AS41: No | AT41: «Por otro lado, si bien se demandó la partición de sólo de una parte de derechos sobre el inmueble inscrito en la partida N° 01125760, la recurrida ha resuelto, sin ninguna motivación, que la división y partición se realice sobre el íntegro del inmueble asignando el porcentaje del 33.33% a cada una de las partes del proceso, conclusión contradictoria con lo señalado en el numeral 4.7.» | AU41: b) Defecto interno: fallo sin motivación y contradictorio | AV41: «Las omisiones, e incoherencias anotadas en los fundamentos anteriores, constituyen causal de nulidad prevista en el artículo 122 concordante con el artículo 171 del Código Procesal Civil, por lo que debe declararse nula la apelada.» | AW41: b) Omisiones e incoherencias como causal (arts. 122 y 171 CPC) | AX41: «Se deja constancia, que la Sala Superior se encuentra impedida de emitir pronunciamiento de fondo, para garantizar el principio de doble instancia a que se refiere el inciso 6 del artículo 139 de la Constitución Política del Perú.» | AY41: Efecto: reenvío por instancia plural | AZ41: Incoherencia entre fundamentos y fallo (partición sobre el íntegro vs. parte); extremo resuelto 'sin ninguna motivación'. Ordena prueba de oficio y nuevo punto controvertido. | BA41: 1681 2023 SV.doc | BB41: Clasificacion_SV_ABR24_Llamoja_defectos | BC41: 1 | BD41: ABREVIADO | BE41: NULA | BF41: AN
A42: 41 | B42: 01723-2022 | C42: 01723-2022-0-0401-JR-CI-06 | D42: Llamoja — SV de control (2021-2023) | E42: División y partición | F42: 2SC | G42: 063-2025-2SC | H42: 23 | I42: dos mil veinticinco, Enero veintiuno | J42: 2025 | L42: Cervantes López | M42: REVOCA → IMPROCEDENTE | N42: 0 | O42: 0 | AQ42: — Sin vicio de motivación como causal | AS42: No | AT42: «Por estos fundamentos, SE RESUELVE: REVOCAR la Sentencia N° 5-2024-6JEC (Resolución N° 16) de fecha 15 de enero de 2024 digitalizada a fojas doscientos quince, que resolvió declarar fundada la demanda interpuesta por Dennis Pablo Salas Mollinedo en contra de Miryam Giannina Aguilar Pacheco sobre División y Partición de bien, con lo demás que contiene.» | AU42: Error de juicio: revoca y reforma (improcedente) | AV42: «REFORMANDOLA, se declara IMPROCEDENTE la citada demanda interpuesta por Dennis Pablo Salas Mollinedo en contra de Miryam Giannina Aguilar Pacheco sobre división y partición, por las razones expuestas; se deja a salvo el derecho de la parte demandante para que haga valer con arreglo a ley.» | AW42: Fallo reformado | AZ42: Error de juicio; sin anulación. | BA42: 1723 2022 SV 202.doc | BB42: Clasificacion_SV_ABR24_Llamoja_defectos | BC42: 1 | BD42: ABREVIADO | BE42: REVOCADA | BF42: AR
A43: 42 | B43: 01734-2017 | C43: 01734-2017 | D43: Pre-2019 | F43: 2SC | G43: SV N° 017-2019-2SC | I43: 18/01/2019 | J43: 2019 | M43: Nula | N43: 1 | O43: 1 | AD43: DECLARADO — “…dose establecido que el fundamento expuesto en la recurrida adolece de una falta de motivación interna, se concluye que la recurrida adolece de nulidad insubsanable, por haber infringido no sólo el inciso 5) del artículo 139 de nuestra Constitución Política, sino también el inciso 3) del artículo 122…” | AM43: Sí | AP43: Baja D20→— | BB43: Comparativa_defectos_2018_vs_2024 + Defectos_procesales_SV_CSJA | BC43: 2 | BD43: CONOCIMIENTO | BE43: NULA | BF43: CN
A44: 43 | B44: 01835-2024 | C44: 01835-2024 | D44: 2024 | F44: 1SC | G44: SV N° 295-2025-1SC | I44: 16/07/2025 | J44: 2025 | M44: Revocada | N44: 0 | O44: 0 | BB44: Comparativa_defectos_2018_vs_2024 + Defectos_procesales_SV_CSJA | BC44: 2 | BE44: REVOCADA
A45: 44 | B45: 01869-2023 | C45: 01869-2023-0-0401-JR-CI-01 | D45: Llamoja — SV de control (2021-2023) | E45: Indemnización (Contraloría) | F45: 2SC | G45: 032-2026-2SC | H45: 35 | I45: dos mil veintiséis, Enero veintitrés | J45: 2026 | L45: de la Cuba Chirinos | M45: NULA | N45: 3 | O45: 3 | AA45: DECLARADO — (evidencia en las columnas «Cita textual 1–3» de esta misma fila) | AB45: DECLARADO — (evidencia en las columnas «Cita textual 1–3» de esta misma fila) | AJ45: DECLARADO — «el juzgado de primera instancia sustenta su conclusión en un medio probatorio que no acredita el hecho que se pretende demostrar» (premisa fáctica no justificada) | AP45: Alta —→D21 | AQ45: d) Motivación insuficiente | AR45: c) Deficiencia de motivación externa | AS45: Sí | AT45: «En ese sentido, esta sala superior concluye que el juzgado de primera instancia incurre en una deficiencia de motivación al considerar que la carta N° 070-2019-OOPP/MDM constituye sustento del pedido de ampliación de plazo N° 01 por parte del contratista, pues dicho documento no fue emitido ni suscrito por el representante legal del Consorcio COLTAN, sino por el codemandado Lucio Vilca Ticona, servidor de la entidad demandada, y se encuentra dirigido, además, al representante legal común del consorcio.» | AU45: d) Deficiencia de motivación (etiqueta expresa) | AV45: «Asimismo, de su contenido no es posible también inferir la existencia de una solicitud expresa de ampliación de plazo formulada por el contratista, exigencia prevista en el artículo 170º del reglamento de ley de las contrataciones del Estado; por lo que, el juzgado de primera instancia sustenta su conclusión en un medio probatorio que no acredita el hecho que se pretende demostrar, afectándose el deber de motivación suficiente de las resoluciones judiciales, verificándose así una incongruencia probatoria que afecta la motivación de la sentencia apelada de manera insubsanable.» | AW45: c)/d): premisa probatoria falsa; 'incongruencia probatoria' insubsanable | AX45: «La falta de motivación o una motivación deficiente en las resoluciones judiciales constituye un vicio que puede ser objeto de control en sede impugnatoria, especialmente cuando tal deficiencia compromete gravemente la validez del acto procesal.» | AY45: Marco: la deficiencia como vicio controlable en sede impugnatoria | AZ45: Etiqueta 'deficiencia de motivación' / 'motivación suficiente'; premisa fáctica falsa (carta atribuida a quien no la emitió) = también c). SV fechada 2026. | BA45: 1869 2023 SV.doc | BB45: Clasificacion_SV_ABR24_Llamoja_defectos | BC45: 1 | BD45: ABREVIADO | BE45: NULA | BF45: AN
A46: 45 | B46: 01879-2022 | C46: 01879-2022 | D46: 2024 | F46: 2SC | G46: SV N° 527-2025-2SC | I46: 28/10/2025 | J46: 2025 | M46: Nula | N46: 1 | O46: 1 | AL46: DECLARADO — “…esta instancia superior no puede subsanar los referidos vicios de motivación, al tratarse de defectos graves e insubsanables. 4.24. Por tanto, al renovarse el pronunciamiento judicial, corresponde al juzgado de primera instancia dispone…” | AM46: Sí | AP46: Migración D15→D23 · Baja D20→— | BB46: Comparativa_defectos_2018_vs_2024 + Defectos_procesales_SV_CSJA | BC46: 2 | BD46: CONOCIMIENTO | BE46: NULA | BF46: CN
A47: 46 | B47: 01888-2011 | C47: 01888-2011 | D47: Pre-2019 | F47: 2SC | G47: SV N° 022-2020-2SC | I47: 10/01/2020 | J47: 2020 | M47: Nula | N47: 1 | O47: 1 | AH47: DECLARADO — “…cisiete, de fojas seiscientos sesenta y siete, que resolvía declarar improcedente por extemporánea la tacha de documento formulada por la demandada Sandra Luz Parada Aramayo, por los considerandos del Auto de Vista que antecede, por medio del cual se dispone que el Juzgado emitir nuevo pronunciamiento respecto de la tacha deducida por la…” | AM47: Sí | AP47: Migración D08→D19 · Baja D15→— · Baja D20→— | BB47: Comparativa_defectos_2018_vs_2024 + Defectos_procesales_SV_CSJA | BC47: 2 | BD47: CONOCIMIENTO | BE47: NULA | BF47: CN
A48: 47 | B48: 01946-2016 | C48: 01946-2016 | D48: Pre-2019 | F48: 3SC | G48: SV N° 616-2019-3SC | I48: 13/08/2019 | J48: 2019 | M48: Revocada | N48: 0 | O48: 0 | BB48: Comparativa_defectos_2018_vs_2024 + Defectos_procesales_SV_CSJA | BC48: 2 | BD48: CONOCIMIENTO | BE48: REVOCADA | BF48: CR
A49: 48 | B49: 02167-2023 | C49: 02167-2023-0-0401-JR-CI-06 | D49: Matriz sumarísimos — grupo 2024 | E49: Desalojo por ocupación precaria | F49: 2SC | G49: SV 608-2025-2SC (por mayoría) | H49: Res. 27 (seis-2SC) | I49: 22/12/2025 | J49: 2025 | K49: Patricia Valdivia Franco | M49: REVOCADA → IMPROCEDENTE (por mayoría) | N49: 0 | O49: 3 | U49: VOTO MINORÍA — «el problema de la falta de identificación plena y ocupación, se origina en que se establecieron de manera errónea los puntos controvertidos en este expediente… cuando lo que correspondía era establecer si existe alguna superposición entre el predio sublitis y respecto al cual el demandado señala ser titular» | X49: VOTO MINORÍA — «corresponde que de oficio se solicite una prueba pericial para determinar tanto la ubicación como los linderos y/o inspección judicial; facultad que tiene el juez con arreglo al Art. 194 del Código Procesal Civil y al X Pleno Casatorio Civil» | AL49: VOTO MINORÍA — «la resolución que viene en apelación se halla incursa en la causal de nulidad prevista en los incisos 3 y 4 del Art. 122» | AP49: Migración D20→D23 · Reclasificación de estatus —→MIN | AZ49: La mayoría revoca sin declarar vicio. El voto en minoría (Polanco Gutiérrez) propone nulidad por defectuosa fijación de puntos controvertidos y falta de prueba de oficio; además observa que debió declararse infundada (regla 6 del IV Pleno) y no improcedente. | BB49: Matriz_defectos_procesales_1ra_SV | BC49: 1 | BD49: SUMARISIMO | BE49: REVOCADA | BF49: SR
A50: 49 | B50: 02275-2023 | C50: 02275-2023-0-0401-JR-CI-02 | D50: Llamoja — SV de control (2021-2023) | E50: Ineficacia de acto jurídico | F50: 3SC | G50: 412-2025-3SC | H50: 22 | I50: dos mil veinticinco, Octubre quince | J50: 2025 | L50: Marroquín Mogrovejo | M50: NULA + nulo lo actuado desde la notificación | N50: 2 | O50: 2 | P50: DECLARADO — (evidencia en las columnas «Cita textual 1–3» de esta misma fila) | S50: DECLARADO — (evidencia en las columnas «Cita textual 1–3» de esta misma fila) | AQ50: — Sin vicio de motivación como causal | AS50: No | AT50: «4.4 La deficiencia descrita ha generado que no se realice un adecuado emplazamiento o notificación al apelante, generando que se festine el trámite del proceso, cursándose las notificaciones de la demanda y demás actos procesales a una persona distinta a la que fue demandada, lo que ha generado indefensión de dicha parte, por cuanto evidentemente se ha vulnerado su derecho de defensa, derecho previsto y consagrado en el inciso 14) del artículo 139° de la Constitución Política del Perú; en consecuencia, se vulneró el derecho al debido proceso y tutela jurisdiccional, toda vez que, al no ser debidamente notificados, no pudo ejercer su derecho de defensa en la forma que consideren pertinente.» | AU50: Notificación/emplazamiento defectuoso + indefensión (139.14) | AV50: «4.5 Aunado a lo señalado y a causa de la deficiencia incurrida por el órgano jurisdiccional en la plena identificación de la persona demandada, el error mencionado se reiteró al emitir la Resolución número cinco de la página setenta, en la que se declaró “(…) REBELDE a los demandados José ROBERTO BROUNCLE CÉSPEDES (…)” persona que es distinta a quien se demandó y en contra de quien se admitió la demanda.» | AW50: Declaración indebida de rebeldía contra persona distinta | AZ50: Notificaciones dirigidas a persona con apellido distinto (Brouncle/Bouroncle); rebeldía declarada contra persona distinta; vulneración del derecho de defensa (139.14). | BA50: 2275 2023 SV.doc | BB50: Clasificacion_SV_ABR24_Llamoja_defectos | BC50: 1 | BD50: ABREVIADO | BE50: NULA | BF50: AN
A51: 50 | B51: 02371-2021 | C51: 02371-2021 | D51: 2024 | G51: SV N° 443-2025 | I51: 25/09/2025 | J51: 2025 | M51: Revocada | N51: 0 | O51: 0 | BB51: Comparativa_defectos_2018_vs_2024 + Defectos_procesales_SV_CSJA | BC51: 2 | BD51: CONOCIMIENTO | BE51: REVOCADA | BF51: CR
A52: 51 | B52: 02483-2021 | C52: 02483-2021-0-0401-JR-CI-01 | D52: Llamoja — SV de control (2021-2023) | E52: Petición de herencia | F52: 2SC | G52: 139-2023 | H52: 23 | I52: dos mil veintitrés, Marzo treinta y uno | J52: 2023 | L52: Paredes Bedregal | M52: NULA | N52: 1 | O52: 1 | R52: DECLARADO — (evidencia en las columnas «Cita textual 1–3» de esta misma fila) | AP52: Baja D09→— | AQ52: — Sin vicio de motivación como causal | AS52: No | AT52: «De esta manera, se evidencia, que además de las partes incluidas en este proceso, existiría otro heredero de la causante Laura Cristina Lizárraga y Salas, declarado mediante el acta protocolizada del once de febrero de dos mil quince, que sería Miguel Ernesto Chávez Lizárraga, quien debe ser emplazado, con la finalidad que haga valer su derecho si así lo considera, debiendo ser incorporado como litisconsorte necesario activo, conforme a lo dispuesto en los artículos 92, 93, 95 y 98 del T.U.O.» | AU52: Litisconsorte necesario omitido (arts. 93, 95 y 98 CPC) | AV52: «se debe declarar la nulidad de la resolución impugnada según lo dispuesto en el artículo 171 y 176 in fine del T.U.O. del Código Procesal Civil, a fin que la A quo disponga la incorporación al proceso de Miguel Ernesto Chávez Lizarraga y emita nuevo pronunciamiento de acuerdo a ley.» | AW52: Efecto: nulidad (arts. 171 y 176) e incorporación del heredero | AZ52: Heredero no emplazado (arts. 93, 95 CPC); ordena incorporarlo y sugiere prueba de oficio (art. 194). SV 139-2023 (menor año; existe SV 460-2025-2SC). | BA52: 2483 2021 sv 2023.doc | BB52: Clasificacion_SV_ABR24_Llamoja_defectos | BC52: 1 | BD52: ABREVIADO | BE52: NULA | BF52: AN
A53: 52 | B53: 02505-2009 | C53: 02505-2009 | D53: Pre-2019 | F53: 3SC | G53: SV N° 02-2019-3SC | I53: 03/01/2019 | J53: 2019 | M53: Nula | N53: 2 | O53: 2 | Q53: DECLARADO — “…go, si se quiere dar cumplimiento al mandato y pronunciarse sobre dicha causal, debe permitírsele que ejerza su derecho de defensa sobre dicho extremo por lo que debió efectuarse el emplazamiento correspondiente, lo que no ha ocurrido en el caso de autos colocándosele en estado de indefensión respecto de dich…” | AE53: DECLARADO — “…se ha incurrido en nulidad al no haberse resuelto conforme al mérito de lo actuado como lo exige el artículo 122° inciso 3° del Código Procesal Civil, la que debe ser declarada por éste colegiado. Fundamentos por los cuales: DECLARARON NULA la Sentencia número c…” | AO53: D16: la cita es la fórmula genérica del art. 122.3 CPC. Sustituir por el pasaje que describe la incorporación de oficio de la causal del art. V TP del Código Civil. | AP53: Baja D09→— · Baja D10→— | BB53: Comparativa_defectos_2018_vs_2024 + Defectos_procesales_SV_CSJA | BC53: 2 | BD53: CONOCIMIENTO | BE53: NULA | BF53: CN
A54: 53 | B54: 02532-2017 | C54: 02532-2017-0-0401-JR-CI-08 | D54: Matriz sumarísimos — anteriores a 2019 | E54: Otorgamiento de escritura pública (CONSULTA) | F54: 1SC | G54: SV 519-2018-1SC | H54: Res. 12 (dos-1SC) | I54: 23/10/2018 | J54: 2018 | K54: Ronald Valencia de Romaña | M54: DESAPROBADA (reenvío) | N54: 2 | O54: 3 | P54: DECLARADO — «no solo no se ha mencionado a los herederos como demandados sino que tampoco se ha indicado que se ignora el domicilio de éstos bajo juramento»; «se debió disponer se notifique a los herederos en el domicilio que se consigna en el RENIEC» | Q54: DERIVADO — «al no haberse procedido así, se ha afectado el debido proceso, por lo que debe desaprobarse la sentencia emitida» | R54: DECLARADO — «se afecta el debido proceso al admitir la demanda en contra de la "sucesión de Hipólito Efraín Sánchez Rivera", cuando ya se sabe quien son los herederos declarados de dicha sucesión, por lo que la demanda debió ser admitida en contra de dichos herederos» | AP54: Reclasificación de estatus D02→D02 (derivado) | AZ54: Revisión en consulta (art. 408.2 CPC) por haber intervenido curador procesal. Emplazamiento genérico a la «sucesión» pese a existir sucesión intestada inscrita con herederos identificados. | BB54: Matriz_defectos_procesales_1ra_SV | BC54: 1 | BD54: SUMARISIMO | BE54: NULA | BF54: SN
A55: 54 | B55: 02635-2019 | C55: 02635-2019 | D55: 2024 | G55: SV N° 531-2023 | I55: 06/11/2023 | J55: 2023 | M55: Nula | N55: 2 | O55: 2 | Z55: DECLARADO — “…dante. En la sentencia materia de grado no se han valorado los medios probatorios ofrecidos en la contestación de demanda, no se ha merituado el valor probatorio del acta de asamblea de fecha dieciséis de octubre del dos mil diecinueve y el acta de fecha dieciocho de noviembre del dos mil veinte, así como las actas, escrituras publicas y testigos cuyo valor p…” | AC55: DECLARADO — “…ha copiado y pegado literalmente todo el texto y no ha realizado fundamentación alguna respecto a la causal de ser contrario al orden público y las buenas costumbres y ha copiado los considerandos desarrollados en la sentencia número 21-2023 del veintisiete de marzo del dos mil veintitrés del expediente 5…” | AM55: Sí | AP55: Migración D15→D14 · Baja D20→— | BB55: Comparativa_defectos_2018_vs_2024 + Defectos_procesales_SV_CSJA | BC55: 2 | BD55: CONOCIMIENTO | BE55: NULA | BF55: CN
A56: 55 | B56: 02641-2010 | C56: 02641-2010 | D56: Pre-2019 | F56: 1SC | G56: SV N° 479-2018-1SC | I56: 25/09/2018 | J56: 2018 | M56: Nula | N56: 1 | O56: 1 | V56: DECLARADO — “…stente en el audio contenido en el CD, acta de verificación de grabación y el documento de transcripción del mismo, que debía actuarse en la audiencia de pruebas programada, conforme lo dispuesto en el artículo 234 del Código Procesal Civil; esto es, se disponga por el Juez de la causa, la reproducción del contenido del audio del…” | AP56: Baja D05→— | BB56: Comparativa_defectos_2018_vs_2024 + Defectos_procesales_SV_CSJA | BC56: 2 | BD56: CONOCIMIENTO | BE56: NULA | BF56: CN
A57: 56 | B57: 02706-2015 | C57: 02706-2015 | D57: Pre-2019 | F57: 2SC | G57: SV N° 070-2019-2SC | I57: 21/03/2019 | J57: 2019 | M57: Nula | N57: 1 | O57: 1 | R57: DECLARADO — “…el Notario debió ser integrado al proceso como parte demandada, lo cual no fue advertido por el jugador, de modo que a fin de garantizar que la presente causa se tramite sin vulnerar el debido proceso y garantizando el derecho de defensa del Notario citado, es que debe incluírsele en la relación jurídica procesal, conforme a las facultares establecidas en el a…” | AP57: Baja D02→— | BB57: Comparativa_defectos_2018_vs_2024 + Defectos_procesales_SV_CSJA | BC57: 2 | BD57: CONOCIMIENTO | BE57: NULA | BF57: CN
A58: 57 | B58: 02706-2016 | C58: 02706-2016-0-0401-JR-CI-04 | D58: Matriz sumarísimos — anteriores a 2019 | E58: Desalojo por ocupación precaria | F58: 2SC | G58: SV 2SC (en discordia) | H58: Res. 35 (ocho-2SC) | I58: 19/02/2021 | J58: 2021 | K58: Justo Quispe Apaza | M58: REVOCADA → IMPROCEDENTE (por mayoría) | N58: 0 | O58: 2 | U58: VOTO MINORÍA — «no fue alegado por la parte demandada en la contestación a la demanda, y menos ha sido fijado como punto controvertido en la audiencia del tres de julio del dos mil diecisiete (foja 179)» | W58: VOTO MINORÍA — «el juzgado indebidamente ha admitido mediante auto 23 del 28 de setiembre del dos mil dieciocho (foja 326) el contrato privado del 14 de enero de mil novecientos noventa y siete… la introducción de dicho documento al acervo probatorio es indebido» | AZ58: Los vicios los señala el voto en discordia (Barrera Benavides), que además objeta que la ponencia funde la improcedencia en una usucapión no alegada (art. VII TP CPC). | BB58: Matriz_defectos_procesales_1ra_SV | BC58: 1 | BD58: SUMARISIMO | BE58: REVOCADA | BF58: SR
A59: 58 | B59: 02712-2023 | C59: 02712-2023-0-0401-JR-CI-10 | D59: Llamoja — SV de control (2021-2023) | E59: División y partición / rentas | F59: 2SC | G59: 065-2025-2SC | H59: 23 | I59: dos mil veinticinco, Enero veintiuno | J59: 2025 | L59: Cervantes López | M59: REVOCA → FUNDADA (extremo) | N59: 0 | O59: 0 | AQ59: — Sin vicio de motivación como causal | AS59: No | AT59: «Por estos fundamentos, SE RESUELVE: REVOCAR la Sentencia N° 016-2024 de fecha 13 de marzo de 2024, digitalizada a fojas ciento sesenta y cuatro, en el extremo que declara infundada la demanda interpuesta respecto de la pretensión de obligación de dar suma de dinero, por las razones expuestas.» | AU59: Error de juicio: revoca extremo | AV59: «REFORMANDOLA, se declara FUNDADA la pretensión de obligación de dar suma de dinero por rentas impagas interpuesta por María Patricia Núñez Moscoso en contra de Luis Enrique Núñez Moscoso.» | AW59: Fallo reformado (fundada obligación de dar) | AZ59: Error de juicio; sin anulación. | BA59: 2712 2023 SV 2025.doc | BB59: Clasificacion_SV_ABR24_Llamoja_defectos | BC59: 1 | BD59: ABREVIADO | BE59: REVOCADA | BF59: AR
A60: 59 | B60: 02718-2015 | C60: 02718-2015-0-0401-JR-CI-09 | D60: Matriz sumarísimos — anteriores a 2019 | E60: Desalojo por ocupación precaria | F60: 1SC | G60: SV 620-2018-1SC | H60: Res. 36 (once-1SC) | I60: 28/12/2018 | J60: 2018 | K60: José Meza Miranda | M60: NULA (reenvío) | N60: 3 | O60: 3 | V60: DECLARADO — «no siendo razonable que habiéndose admitido como medio probatorio de oficio una inspección a efecto de determinar e individualizar los ambientes materia de proceso, conforme a la Resolución N° 07 a folios noventa y cinco, ésta en términos prácticos no se haya realizado… porque la litisconsorte necesaria pasiva simplemente no quiso mostrar el inmueble, siendo el A quo quien debe ejercer las medidas coercitivas pertinentes» | AE60: DECLARADO — «dicha motivación en términos del Tribunal Constitucional resulta sustancialmente incongruente, pues tanto la parte demandante como la parte demandada en sus actos postulatorios han señalado y reconocido que la propiedad primigenia del inmueble materia de Litis perteneció a Alejandro Donato Sosa Postigo y Josefina Antonieta Muñoz Pacheco; por lo que, el análisis efectuado en tal sentido constituye una desviación que supone alterar el debate procesal» | AL60: DECLARADO — «la Sentencia venida en grado ha incurrido en causal de nulidad por una indebida motivación no subsanable en esta instancia» | AM60: Sí | AP60: Baja D02→— · Migración D15→D23 · Baja D20→— | AZ60: Se descarta la SV 542-2017 (anterior a 2018) por el criterio de corte temporal. La inspección judicial admitida de oficio (Res. N° 7) quedó frustrada por negativa de la litisconsorte y el A quo no usó medidas coercitivas. | BB60: Matriz_defectos_procesales_1ra_SV | BC60: 1 | BD60: SUMARISIMO | BE60: NULA | BF60: SN
A61: 60 | B61: 02723-2023 | C61: 02723-2023-0-0401-JR-CI-02 | D61: Llamoja — SV de control (2021-2023) | E61: Ineficacia de título valor | F61: 2SC | G61: 525-2025-2SC | H61: 21 | I61: dos mil veinticinco, Octubre veintiocho | J61: 2025 | L61: de la Cuba Chirinos | M61: REVOCA → FUNDADA | N61: 0 | O61: 0 | AQ61: — Sin vicio de motivación como causal | AS61: No | AT61: «Estando a todo lo analizado, dentro de los parámetros de ley y la jurisprudencia citada, son de recibo los argumentos impugnativos, debiendo revocarse la sentencia recurrida.» | AU61: Error de juicio: se amparan los agravios | AV61: «En cuanto a los efectos de la resolución del contrato, ha quedado acreditado que la relación contractual entre Matías Jochamowitz Mendoza y Corban Negocios S.A.C.» | AW61: Fundamento: resolución contractual acreditada | AZ61: Error de juicio; sin anulación. | BA61: 2723 2023 SV 22024.doc | BB61: Clasificacion_SV_ABR24_Llamoja_defectos | BC61: 1 | BD61: ABREVIADO | BE61: REVOCADA | BF61: AR
A62: 61 | B62: 02792-2023 | C62: 02792-2023-0-0401-JR-CI-03 | D62: Llamoja — SV de control (2021-2023) | E62: Nulidad de acto jurídico (simulación) | F62: 1SC | H62: 27 | I62: dos mil veinticinco, junio veinticuatro | J62: 2025 | L62: Polanco Gutiérrez | M62: REVOCA extremo → (nulidad desestimada) | N62: 0 | O62: 2 | AC62: ADVERTIDO — la Sala califica de aparente la motivación del considerando 7.2 | AD62: ADVERTIDO — la Sala califica de «no lógica» la conclusión del A quo | AP62: Alta —→D14 y D15 | AQ62: — Sin vicio de motivación como causal | AR62: a) Inexistencia / motivación aparente | AS62: No | AT62: «Ninguno de los contratos fue impugnado en su validez, por lo que prevalece lo señalado en el artículo 2013 del Código Civil y aun cuando es un indicio de la conducta de las partes, es aparente la motivación del juez en 7.2.» | AU62: a) Motivación aparente advertida (sin efecto anulatorio) | AV62: «cuando afirmar que: “… el hecho que no haya sido declaradas nulas no necesariamente significa que sean reales; entonces , bajo dicho presupuesto reposa la confianza de devolución que sustenta el acuerdo sobre el que habrían actuado las partes, independiente a la voluntad de la parte demandada de apropiarse el inmueble … se hacía aparentar a los demandados que eran los propietarios sin haber pagado el precio y/o perjudicar a los derechos de los demás hijos de los demandantes; concurriendo el propósito de engaño y perjuicio a terceros.” ¿Cómo debe, entonces, ser valorada la conducta de las partes? como una de confianza, por lo que justifica la inexistencia de cualquier contradocumento al respecto, pero no puede concluirse que como firmaron dos contratos simulados (afirmación que no está acreditada), el tercero también es simulado, pues dicha conclusión es una conclusión no lógica.» | AW62: b) Conclusión 'no lógica' (defecto interno), corregida por revocatoria | AX62: «Finalmente, se le recomienda al juez de la causa, que tenga en cuenta que el proceso por audiencias (oralidad), parte de la premisa de un proceso instrumento y flexible para una decisión correcta, siendo uno de sus límites importantes a las facultades del juez, la no vulneración del derecho de defensa y contradictorio al que tienen derecho las partes.» | AY62: Exhortación sobre oralidad y contradictorio | AZ62: Vicio advertido sin efecto anulatorio: la Sala califica de 'aparente' la motivación del 7.2 y de 'no lógica' la conclusión (a/b), pero corrige por revocatoria. Registrar como vicio detectado sin nulidad. | BA62: 2792 2023 SV 2025.doc | BB62: Clasificacion_SV_ABR24_Llamoja_defectos | BC62: 1 | BD62: ABREVIADO | BE62: REVOCADA | BF62: AR
A63: 62 | B63: 02814-2015 | C63: 02814-2015 | D63: Pre-2019 | F63: 3SC | G63: SV N° 716-2019-3SC | I63: 11/09/2019 | J63: 2019 | M63: Nula e insubsistente | N63: 1 | O63: 1 | AC63: DECLARADO — “…se viola el derecho a una decisión debidamente motivada cuando la motivación es inexistente o cuando la misma es solo aparente, en el sentido de que no da cuenta de las razones mínimas que sustentan la decisión o de que no responde a las alegaciones de las partes del proceso, o porque solo intenta dar un cumplimiento formal al mandato, amparándose en frases sin ni…” | AO63: La cita reproduce la definición abstracta del estándar del Tribunal Constitucional. Sustituir por el considerando en que la Sala subsume el caso. | BB63: Comparativa_defectos_2018_vs_2024 + Defectos_procesales_SV_CSJA | BC63: 2 | BD63: CONOCIMIENTO | BE63: NULA | BF63: CN
A64: 63 | B64: 02851-2023 | C64: 02851-2023-0-0401-JR-CI-07 | D64: Llamoja — SV de control (2021-2023) | E64: División y partición | F64: 1SC | H64: 39 | I64: dos mil veinticinco, junio seis | J64: 2025 | L64: Zamalloa Campero | M64: NULA | N64: 2 | O64: 2 | AH64: DECLARADO — (evidencia en las columnas «Cita textual 1–3» de esta misma fila) | AK64: DECLARADO — «como al resolver las apelaciones diferidas se ha declarado nula la resolución dieciocho… también corresponde declarar nula la sentencia» | AP64: Baja D03→— · Alta —→D22 | AQ64: — Sin vicio de motivación como causal | AS64: No | AT64: «4.4.- Ahora, como al resolver las apelaciones diferidas se ha declarado nula la resolución dieciocho que incorporaba a Vidal José Canales Salas, José Millton Canales Rodríguez y Cinthya Lourdes Canales Rodríguez como litisconsortes facultativos activos (apelantes), también corresponde declarar nula la sentencia materia de grado, pues se encuentra pendiente de resolver el pedido de intervención litisconsorcial formulado por dichas personas y de acuerdo a lo que se decida sobre ese pedido es que recién se podría determinar si en la sentencia debe emitirse algún pronunciamiento sobre el derecho que alegan o si estarían facultados para impugnarla.» | AU64: Omisión de resolver incidencia previa (nulidad concatenada de la Res. 18) | AV64: «Siendo así, carece de objeto emitir pronunciamiento sobre la apelación interpuesta contra la sentencia.» | AW64: Efecto: carece de objeto resolver la apelación de fondo | AZ64: Nulidad concatenada: anulada la Res. 18 (incorporación de litisconsortes) queda pendiente el pedido de intervención; carece de objeto resolver la apelación de fondo. | BA64: 2851 2023 SV.doc | BB64: Clasificacion_SV_ABR24_Llamoja_defectos | BC64: 1 | BD64: ABREVIADO | BE64: NULA | BF64: AN
A65: 64 | B65: 02943-2016 | C65: 02943-2016 | D65: Pre-2019 | F65: 2SC | G65: SV N° 623-2018-2SC | I65: 04/12/2018 | J65: 2018 | M65: Nula | N65: 2 | O65: 2 | AE65: DECLARADO — “…itirá que el Juzgado se pronuncie sobre los puntos controvertidos fijados en la Resolución N° 14-2017, puesto que no pasa desapercibido que el A quo no se ha pronunciado sobre ningún punto controvertido. OCTAVO: Así expuesto, y también a fin de permitir el derec…” | AL65: DECLARADO — “…declarar la nulidad de la recurrida por contener una motivación defectuosa, y, por ende ordenar que el juez de la cause emita un nuevo pronunciamiento. PARTE RESOLUTIVA: Por los fundamentos previamente expuestos, S…” | AP65: Migración D06→D16 · Migración D15→D23 | BB65: Comparativa_defectos_2018_vs_2024 + Defectos_procesales_SV_CSJA | BC65: 2 | BD65: CONOCIMIENTO | BE65: NULA | BF65: CN
A66: 65 | B66: 02973-2022 | C66: 02973-2022-0-0401-JR-CI-07 | D66: Llamoja — SV de control (2021-2023) | E66: Nulidad de acto jurídico (testamento) | F66: 2SC | G66: 250-2025-2SC | H66: 48 | I66: dos mil veinticinco, Mayo veintisiete | J66: 2025 | L66: Paredes Bedregal | M66: NULA | N66: 1 | O66: 1 | AJ66: DECLARADO — (evidencia en las columnas «Cita textual 1–3» de esta misma fila) | AP66: Migración D13→D21 · Baja D20→— | AQ66: c) Deficiencia de motivación externa | AS66: Sí | AT66: «Por consiguiente, la resolución materia de alzada adolece de falta de motivación externa, referida a la justificación de las premisas, pues conforme a lo señalado por el Tribunal Constitucional en la STC N° 03943-2006-PA/TC “[…] se presenta cuando las premisas de las que parte el Juez no han sido confrontadas o analizadas respecto de su validez fáctica o jurídica […]”; y si bien “no todo ni cualquier error en el que eventualmente incurra una resolución judicial constituye automáticamente la vulneración del contenido constitucionalmente protegido del derecho a la motivación de las resoluciones judiciales, cierto es también que el deber de motivar constituye una garantía del justiciable frente a la arbitrariedad judicial y garantiza que las resoluciones no se encuentren justificadas en el mero capricho de los jueces, sino en datos objetivos que proporciona el ordenamiento jurídico o los que se derivan del caso”.» | AU66: c) Deficiencia de motivación externa (premisa normativa no justificada) | AV66: «Consecuentemente, en salvaguarda del derecho a la instancia plural de las partes y el derecho de defensa contenidos en los numerales 6) y 14) del artículo 139 de la Constitución, corresponde declarar la nulidad de la recurrida, en mérito al primer párrafo del artículo 171 y artículo 176 in fine del Código Adjetivo, a fin de que el A quo emita nuevo pronunciamiento de acuerdo a ley y conforme a los antecedentes del proceso.» | AW66: Efecto: nulidad e imposibilidad de pronunciamiento de fondo (instancia plural) | AZ66: Etiqueta expresa 'falta de motivación externa'. Premisa normativa no justificada: aplicó norma sin considerar teoría de hechos cumplidos (art. 219.2 CC derogado). El catálogo no tiene 'motivación externa'; se asigna la categoría más próxima. | BA66: 2973 2022 SV.doc | BB66: Clasificacion_SV_ABR24_Llamoja_defectos | BC66: 1 | BD66: ABREVIADO | BE66: NULA | BF66: AN
A67: 66 | B67: 03228-2013 | C67: 03228-2013 | D67: Pre-2019 | F67: 2SC | G67: SV N° 681-2018-2SC | I67: 28/12/2018 | J67: 2018 | M67: Nula | N67: 3 | O67: 3 | AA67: DECLARADO — “…mpoco ha emitido pronunciamiento respecto del último punto controvertido, peor aún si no se hallan expuestas las razones mínimas o fundamento jurídico que justifican tal decisión, se ha generado insuficiencia de valoración probatoria. Atendiendo a lo señalado, el Colegiado determina que la im…” | AC67: DECLARADO — “…endo a lo señalado, el Colegiado determina que la impugnada incurre en vicio de motivación aparente al no haber dado respuesta a las alegaciones de las partes ni valorado pruebas admitidas, por lo que de conformidad con el artículo 139° inciso 5 de la Constitución Política del E…” | AE67: DECLARADO — “…tampoco ha emitido pronunciamiento respecto del último punto controvertido, peor aún si no se hallan expuestas las razones mínimas o fundamento jurídico que justifican tal decisión, se ha generado insuficiencia de valoración probatori…” | AP67: Migración D06→D16 · Baja D11→— · Baja D17→— · Nota —→— | BB67: Comparativa_defectos_2018_vs_2024 + Defectos_procesales_SV_CSJA | BC67: 2 | BD67: CONOCIMIENTO | BE67: NULA | BF67: CN
A68: 67 | B68: 03393-2017 | C68: 03393-2017 | D68: Pre-2019 | F68: 2SC | G68: SV N° 506-2019-2SC | I68: 23/08/2019 | J68: 2019 | M68: Nula | N68: 1 | O68: 2 | P68: DECLARADO — “…lación: La parte apelante sostiene, que su representada no ha sido válidamente emplazada tal como aparece de las cedulas de notificación y se ha emitido sentencia sin haberle permitido ejercer su derecho de defensa. Indica que el error en la notificación ha sido induc…” | Q68: DERIVADO — “…PAR y al Procurador a cargo de los asuntos judiciales de la Municipalidad Provincial de Arequipa, en su aspecto formal, por impedírseles haber ejercido su derecho de defensa, que constituye una garantía mínima a que tiene derecho todo justiciable, protegido por el artículo 139° de la Constitución, se colige que se ha incurrido en causal de nulidad insubsanable; por tanto, debe ser declarado…” | AM68: Sí | AO68: D01: la cita transcribe el agravio del apelante. Sustituir por el considerando en que el Colegiado hace suya la constatación. | BB68: Comparativa_defectos_2018_vs_2024 + Defectos_procesales_SV_CSJA | BC68: 2 | BD68: CONOCIMIENTO | BE68: NULA | BF68: CN
A69: 68 | B69: 03566-2011 | C69: 03566-2011 | D69: Pre-2019 | F69: 3SC | G69: SV N° 560-2018-3SC | I69: 28/12/2018 | J69: 2018 | M69: Nula | N69: 1 | O69: 1 | AA69: DECLARADO — “…Que, no se ha valorado los medios probatorios ofrecidos en forma conjunta. Que, respecto de la Sentencia de Vista número 528-2017-3SC, esta ha concluido que el bien objeto de litis es el mismo…” | AP69: Migración D11→D12 | BB69: Comparativa_defectos_2018_vs_2024 + Defectos_procesales_SV_CSJA | BC69: 2 | BD69: CONOCIMIENTO | BE69: NULA | BF69: CN
A70: 69 | B70: 03672-2013 | C70: 03672-2013 | D70: Pre-2019 | F70: 2SC | G70: SV N° 010-2019-2SC | I70: 15/01/2019 | J70: 2019 | M70: Nula | N70: 0 | O70: 0 | AM70: Sí | AO70: La única cita registrada enuncia la nulidad insubsanable y la pluralidad de instancias, sin identificar el defecto. Reexaminar el documento para asignar causal. | AP70: Baja D20→— | BB70: Comparativa_defectos_2018_vs_2024 + Defectos_procesales_SV_CSJA | BC70: 2 | BD70: CONOCIMIENTO | BE70: NULA | BF70: CN
A71: 70 | B71: 03701-2023 | C71: 03701-2023 | D71: 2024 | F71: 3SC | G71: SV N° 301-2025-3SC | I71: 14/07/2025 | J71: 2025 | M71: Nula | N71: 2 | O71: 2 | AA71: DECLARADO — “…algunos de ellos pueden conducirnos a sustentar alguna discrepancia entre la voluntad real y la declarada; sin embargo, no están referidos y no conducen cuando menos vía inferencia o deducción, a demostrar la existencia del acuerdo o concierto simulatorio entre Francisco Manuel Huberto Llerena Butrón transfiere vía compraventa, a favor de Hermelinda Mariño Quintanilla y Pablo H…” | AL71: DECLARADO — “…se ha resuelto sin tener en cuenta el mérito de lo actuado como exige el inciso 3 del artículo 122° del Código Procesal Civil, incurriéndose en nulidad que debe ser declarada por esta instancia superior. Fundamentos por los cuales: DECLAR…” | AP71: Migración D14→D23 | BB71: Comparativa_defectos_2018_vs_2024 + Defectos_procesales_SV_CSJA | BC71: 2 | BD71: CONOCIMIENTO | BE71: NULA | BF71: CN
A72: 71 | B72: 03731-2015 | C72: 03731-2015-0-0401-JR-CI-06 | D72: Matriz sumarísimos — anteriores a 2019 | E72: Desalojo por precario | F72: 1SC | G72: SV 581-2018-1SC | H72: Res. 28 (tres-1SC) | I72: 03/12/2018 | J72: 2018 | K72: Patricia Valdivia Franco | M72: NULA (reenvío) | N72: 1 | O72: 1 | AK72: DECLARADO — «si bien la sentencia emitida por el Juzgado de origen se encuentra arreglada a derecho, es esta nueva situación que nos obliga a declarar la nulidad y que el juez expida nueva resolución» | AP72: Migración D20→D22 · Baja D19→— | AZ72: Nulidad por hecho sobreviniente: nulidad del título de propiedad de la demandante declarada en el Exp. 2183-2014, pendiente de casación. Debe evaluarse la suspensión (art. 320 CPC). | BB72: Matriz_defectos_procesales_1ra_SV | BC72: 1 | BD72: SUMARISIMO | BE72: NULA | BF72: SN
A73: 72 | B73: 03754-2015 | C73: 03754-2015-0-0401-JR-CI-?? | D73: Matriz sumarísimos — anteriores a 2019 | E73: (no determinable) | G73: SIN DOCUMENTO PROPIO | M73: SIN DOCUMENTO | N73: 0 | O73: 0 | AM73: — | AP73: Baja D01–D20→— | AZ73: ALERTA DE CORPUS: el archivo '3754 2015 SV 2021.doc' del documento unificado contiene íntegramente el texto de la SV 660-2018-2SC del Exp. 00115-2012 (md5 idéntico). No hay SV propia de este expediente en el corpus; debe reemplazarse la fuente. | BB73: Matriz_defectos_procesales_1ra_SV | BC73: 1 | BD73: SUMARISIMO | BE73: OTRO | BF73: SO
A74: 73 | B74: 03770-2019 | C74: 03770-2019-0-0401-JR-CI-07 | D74: Llamoja — SV de control (2021-2023) | E74: Tercería de propiedad | F74: 1SC | H74: 64 | I74: dos mil veinticuatro, diciembre dieciséis | J74: 2024 | L74: Madariaga Condori | M74: NULA | N74: 2 | O74: 2 | V74: DECLARADO — (evidencia en las columnas «Cita textual 1–3» de esta misma fila) | AK74: DECLARADO — (evidencia en las columnas «Cita textual 1–3» de esta misma fila) | AP74: Migración D19→D22 | AQ74: — Sin vicio de motivación como causal | AS74: No | AT74: «4.1.- Atendiendo a que, al resolverse la apelación concedida sin efecto suspensivo y con la calidad de diferida, se ha declarado la nulidad de la resolución número cuarenta y uno, en la que se prescindió de la pericia ofrecida por el codemandado Félix Churata Churata, corresponde como consecuencia de ello declarar nula la sentencia N.° 24-2024-7JC de fecha treinta y uno de enero de dos mil veinticuatro, pues con la nulidad de la resolución número cuarenta y uno se tiene que está pendiente la realización de la pericia; siendo así, carece de objeto emitir pronunciamiento sobre la apelación interpuesta contra la sentencia.» | AU74: Nulidad concatenada: anulada la Res. 41 que prescindió de la pericia | AV74: «pues con la nulidad de la resolución número cuarenta y uno se tiene que está pendiente la realización de la pericia; siendo así, carece de objeto emitir pronunciamiento sobre la apelación interpuesta contra la sentencia.» | AW74: Prueba admitida y no actuada: pericia pendiente | AZ74: Nulidad concatenada: anulada la Res. 41 (que prescindió de la pericia), la pericia queda pendiente; sentencia dictada sin ella. | BA74: 3770 2019 SV.doc | BB74: Clasificacion_SV_ABR24_Llamoja_defectos | BC74: 1 | BD74: ABREVIADO | BE74: NULA | BF74: AN
A75: 74 | B75: 03819-2022 | C75: 03819-2022-0-0401-JR-CI-04 | D75: Matriz sumarísimos — grupo 2024 | E75: Desalojo por precario | F75: 2SC | G75: SV 496-2024-2SC | H75: Res. 30 (tres-2SC) | I75: 06/11/2024 | J75: 2024 | K75: María Bellido Angulo | M75: NULA (reenvío) | N75: 2 | O75: 2 | AA75: DECLARADO — «el Juzgado basó su decisión en una resolución emitida en el marco de este procedimiento administrativo inconcluso, lo cual resulta inadecuado» | AL75: DECLARADO — «a través de la sentencia apelada no se ha dado una respuesta debidamente razonada al justiciable, evidenciándose una afectación a la debida argumentación y a la tutela jurisdiccional efectiva del recurrente» | AP75: Baja D11→— · Migración D13→D23 · Baja D20→— | AZ75: Se declaró la falta de legitimidad para obrar activa con base en un acto administrativo no firme (reversión del predio a la Municipalidad). | BB75: Matriz_defectos_procesales_1ra_SV | BC75: 1 | BD75: SUMARISIMO | BE75: NULA | BF75: SN
A76: 75 | B76: 03996-2023 | C76: 03996-2023-0-0401-JR-CI-04 | D76: Llamoja — SV de control (2021-2023) | E76: División y partición | F76: 1SC | H76: 22 | I76: dos mil veinticinco, enero treinta y uno | J76: 2025 | L76: Fernández Dávila Mercado | M76: NULA | N76: 2 | O76: 2 | U76: DECLARADO — (evidencia en las columnas «Cita textual 1–3» de esta misma fila) | X76: DECLARADO — (evidencia en las columnas «Cita textual 1–3» de esta misma fila) | AO76: D09: la Sala admite ella misma la prueba de oficio y reenvía para que el A quo la valore con contradictorio; verificar si califica de irregular el ejercicio del A quo o solo aplica el X Pleno. | AQ76: — Sin vicio de motivación como causal | AS76: No | AT76: «Con el objetivo de evitar limitar el derecho de apelación de las partes procesales, este colegiado considera correcto anular la sentencia materia de apelación y devolver los actuados al juzgado de origen, a efecto de que la A quo se pronuncie sobre el acta de Conciliación con Acuerdo Total N.° 251-2021, de ser el caso cumpla con señalar nuevos puntos de controversia, permita el derecho de contradicción de las partes procesales y en su oportunidad el derecho de apelación.» | AU76: Prueba de oficio admitida por la Sala; reenvío para valorarla con contradictorio | AV76: «La tercera regla del X Pleno Casatorio Civil, ha establecido que: “El juez de primera o segunda instancia, en el ejercicio y trámite de la prueba de oficio deberá cumplir de manera obligatoria con los siguientes límites: a) Excepcionalidad, b) pertinencia, c) fuentes de prueba, d) motivación, e) contradictorio, f) no suplir a las partes y g) en una sola oportunidad” (subrayado nuestro)» | AW76: Marco: límites de la prueba de oficio, X Pleno Casatorio (art. 194 CPC) | AZ76: La Sala admite de oficio el acta de conciliación 251-2021 (aparente pacto de indivisión) y anula para que el A quo la valore con contradictorio y fije nuevos puntos controvertidos (X Pleno). | BA76: 3996 2023 2025 SV.doc | BB76: Clasificacion_SV_ABR24_Llamoja_defectos | BC76: 1 | BD76: ABREVIADO | BE76: NULA | BF76: AN
A77: 76 | B77: 04008-2010 | C77: 04008-2010 | D77: Pre-2019 | F77: 2SC | G77: SV N° 654-2019-2SC | I77: 27/09/2019 | J77: 2019 | M77: Nula | N77: 2 | O77: 2 | X77: DECLARADO — “…y Ruben Huaracha Narrea sobre reivindicación, ORDENARON que el juzgador ponga en conocimiento de las partes, el contenido del auto 18, en que se admiten medios probatorios de oficio, y en atención a ello, de surgir controversia sobre el título de dominio obtenido por los demandados, mediante usucapion, disponer de así considerarlo…” | Y77: DECLARADO — “…citada por las partes en el proceso. Con esta actuación probatoria el Juez cuidará de no reemplazar a las partes en su carga probatoria, y deberá asegurarles el derecho de contradicción de la prueba. La resolución que ordena las pruebas de oficio debe estar…” | AO77: D10: la cita reproduce el texto del art. 194 CPC. Sustituir por el considerando aplicativo. | BB77: Comparativa_defectos_2018_vs_2024 + Defectos_procesales_SV_CSJA | BC77: 2 | BD77: CONOCIMIENTO | BE77: NULA | BF77: CN
A78: 77 | B78: 04033-2016 | C78: 04033-2016-0-0401-JR-CI-10 | D78: Matriz sumarísimos — anteriores a 2019 | E78: Desalojo por precario y cancelación de anticresis | F78: 1SC | G78: SV 500-2018-1SC | H78: Res. 25 (cuatro-1SC) | I78: 12/10/2018 | J78: 2018 | K78: Zoraida Salas Flores | M78: REVOCADA → FUNDADA | N78: 0 | O78: 1 | AC78: ALEGADO — «criterio con el cual debió declararse improcedente la valoración de medios probatorios sobre la existencia de una deuda distinta… corroborando una motivación aparente» | AZ78: La Sala no declara vicio: resuelve el fondo (validez del pago consignado, arts. 1220, 1256 CC) y revoca. | BB78: Matriz_defectos_procesales_1ra_SV | BC78: 1 | BD78: SUMARISIMO | BE78: REVOCADA | BF78: SR
A79: 78 | B79: 04034-2022 | C79: 04034-2022-0-0401-JR-CI-04 | D79: Llamoja — SV de control (2021-2023) | E79: Nulidad de acto jurídico | F79: 2SC | G79: 277-2025-2SC | H79: 21 | I79: dos mil veinticinco, Junio veinticinco | J79: 2025 | L79: de la Cuba Chirinos | M79: NULA | N79: 1 | O79: 1 | AB79: DECLARADO — (evidencia en las columnas «Cita textual 1–3» de esta misma fila) | AP79: Baja D20→— | AQ79: d) Motivación insuficiente | AS79: No | AT79: «En consecuencia, se incurre en causa de nulidad de la recurrida al no analizar el precedente vinculante ni la causal contemplada en el inciso 8) del artículo 219º del código civil, es decir, “El acto jurídico es nulo: (…) En el caso del artículo V del Título Preliminar, salvo que la ley establezca sanción diversa”.» | AU79: d) Motivación insuficiente: omite precedente vinculante y art. 219.8 CC | AV79: «En ese sentido, el juzgado de primera instancia deberá emitir nuevo pronunciamiento conforme a los argumentos aquí señalados, sobre la calificación jurídica de la causal de nulidad que se indica en la presente sentencia, garantizando el principio de contradicción y defensa, a fin de no vulnerar ninguno derecho de las partes, todo ello con la finalidad de obtener un pronunciamiento integral que logre dilucidar, bajo un razonamiento lógico y jurídico, la solución al conflicto de intereses que ha sometido a sede jurisdiccional el demandante, lo que no obsta ni restringe que también se deban analizar con ese mismo vigor y detalle, las pruebas presentadas por las partes demandadas.» | AW79: Alcance del reenvío: nueva calificación con contradictorio | AZ79: Omite analizar precedente vinculante y la causal del art. 219.8 CC; ordena nuevo pronunciamiento con contradictorio sobre la calificación. | BA79: 4034 2022 SV 2025.doc | BB79: Clasificacion_SV_ABR24_Llamoja_defectos | BC79: 1 | BD79: ABREVIADO | BE79: NULA | BF79: AN
A80: 79 | B80: 04040-2015 | C80: 04040-2015 | D80: Pre-2019 | F80: 2SC | G80: SV N° 488-2019-2SC | I80: 21/08/2019 | J80: 2019 | M80: Nula | N80: 1 | O80: 1 | AB80: DECLARADO — “…siderando quinto de la sentencia impugnada, se advierte que no se ha expresado suficientemente las razones, sustentadas en elementos técnicos de prueba, que respalde la convicción del A quo, respecto a que el bien sub litis, cuya reivindicación se pretende, no forme parte del predio inscrito en la partida 01092586; ello en tanto que, de la escritura…” | AP80: Baja D08→— | BB80: Comparativa_defectos_2018_vs_2024 + Defectos_procesales_SV_CSJA | BC80: 2 | BD80: CONOCIMIENTO | BE80: NULA | BF80: CN
A81: 80 | B81: 04049-2015 | C81: 04049-2015-0-0401-JR-CI-05 | D81: Matriz sumarísimos — anteriores a 2019 | E81: Interdicto de recobrar | F81: 2SC | G81: SV 21-2019-2SC | H81: Res. 36 (once-2SC) | I81: 21/01/2019 | J81: 2019 | K81: Yuri Filamir Corrales Cuba | M81: REVOCADA → INFUNDADA | N81: 0 | O81: 1 | AA81: ADVERTIDO — «el A quo, en efecto, ha sustentado la recurrida en el título posesorio derivado del derecho de propiedad del demandante… sin embargo… el interdicto de recobrar procede sólo frente al desapoderamiento del bien» | AZ81: Error de enfoque probatorio: se juzgó la propiedad y no la posesión fáctica al momento del despojo. La Sala corrige en instancia (RA 002-2014-CE-PJ) sin anular. | BB81: Matriz_defectos_procesales_1ra_SV | BC81: 1 | BD81: SUMARISIMO | BE81: REVOCADA | BF81: SR
A82: 81 | B82: 04109-2011 | C82: 04109-2011-0-0401-JR-CI-04 | D82: Matriz sumarísimos — anteriores a 2019 | E82: Desalojo por ocupación precaria | F82: 2SC | G82: SV 094-2019-2SC | H82: Res. 88 (cuatro-2SC) | I82: 08/04/2019 | J82: 2019 | K82: Justo Quispe Apaza | M82: REVOCADA → FUNDADA | N82: 0 | O82: 2 | Q82: ALEGADO — «pese a estar recusado el Juez emite o completa la sentencia, lo que determina evidentemente la nulidad del proceso por vulneración del debido proceso, específicamente a la imparcialidad judicial» | AB82: ALEGADO — «no existe valoración probatoria de los hechos propuestos (falta de motivación), sino básicamente discute el cumplimiento de requisitos establecidos en una casación» | AZ82: La Sala no se pronuncia expresamente sobre la recusación ni sobre los vicios de motivación alegados; revoca por el fondo. | BB82: Matriz_defectos_procesales_1ra_SV | BC82: 1 | BD82: SUMARISIMO | BE82: REVOCADA | BF82: SR
A83: 82 | B83: 04126-2021 | C83: 04126-2021 | D83: 2024 | F83: 1SC | G83: SV N° 32-2024-1SC | I83: 21/01/2024 | J83: 2024 | M83: Nula | N83: 2 | O83: 2 | AE83: DECLARADO — “…teriores, vamos que el A quo se pronunció erróneamente respecto al primer punto controvertido; pues, fundamento su decisión en analizar la figura jurídica de la "vocación hereditaria" (entendemos de la primigenia sucesión) y de la figura de la "representación sucesoria"; situaciones totalmente ajenas a este proceso, que trata meram…” | AL83: DECLARADO — “…olece de nulidad, tal cual lo prevén los artículos 121 y 122 del Código Procesal Civil en sus incisos tercero y cuarto; al no pronunciarse motivada y correctamente sobre la pretensión incoada. PARTE RESOLUTIVA Fundamentos por los cuales: DECLARAMOS NU…” | AP83: Migración D06→D16 · Migración D15→D23 | BB83: Comparativa_defectos_2018_vs_2024 + Defectos_procesales_SV_CSJA | BC83: 2 | BD83: CONOCIMIENTO | BE83: NULA | BF83: CN
A84: 83 | B84: 04138-2022 | C84: 04138-2022-0-0401-JR-CI-02 | D84: Matriz sumarísimos — grupo 2024 | E84: Desalojo por ocupación precaria y pago de alquileres | F84: 2SC | G84: SV 282-2025-2SC | H84: Res. 19 (cuatro-2SC) | I84: 20/06/2025 | J84: 2025 | K84: Edgard Pineda Gamarra | M84: NULA (reenvío) | N84: 1 | O84: 1 | AA84: DECLARADO — «las cartas notariales de folios treinta y ocho y cuarenta, únicamente han sido cursadas a la subarrendataria Emma Pascuala Olmedo Cardeña; a pesar de que… la empresa debía comunicar al arrendatario su decisión mediante carta notarial… situación que no ha sido advertida por el A quo» | AP84: Baja D11→— · Baja D13→— | AZ84: Cláusula resolutoria expresa comunicada a persona distinta del arrendatario; falta de valoración conjunta (art. 197 CPC). | BB84: Matriz_defectos_procesales_1ra_SV | BC84: 1 | BD84: SUMARISIMO | BE84: NULA | BF84: SN
A85: 84 | B85: 04154-2022 | C85: 04154-2022-0-0401-JR-CI-05 | D85: Llamoja — SV de control (2021-2023) | E85: Retracto | F85: 2SC | G85: 368-2024-2SC | H85: 20 | I85: dos mil veinticuatro, Setiembre cinco | J85: 2024 | L85: Paredes Bedregal | M85: NULA | N85: 2 | O85: 2 | AB85: DECLARADO — (evidencia en las columnas «Cita textual 1–3» de esta misma fila) | AC85: DECLARADO — (evidencia en las columnas «Cita textual 1–3» de esta misma fila) | AM85: Sí | AQ85: a) Inexistencia / motivación aparente | AR85: d) Motivación insuficiente | AS85: Sí | AT85: «Igualmente, si bien es cierto en la resolución sólo serán expresadas las valoraciones esenciales y determinantes que sustentan la decisión, ello no es óbice para que se dejen de contestar los argumentos de la parte demandada, quien ha alegado expresamente la no existencia de copropiedad indivisa; todo lo cual evidencia que la recurrida no ha sido emitida con el debido estudio de autos, por lo que se puede concluir que ésta ha sido emitida sin una debida motivación sin dar cuenta de razones suficientes que sustenten la decisión, a la luz de lo que se está dilucidando.» | AU85: d) Motivación insuficiente (sin debido estudio de autos) | AV85: «Si bien, como ha establecido este Tribunal, no se trata de dar respuestas a cada una de las alegaciones planteadas, la insuficiencia, vista aquí en términos generales, sólo resultará relevante desde una perspectiva constitucional si es que la ausencia de argumentos o la “insuficiencia” de fundamentos resulta manifiesta a la luz de lo que en sustancia se está decidiendo […]”; siendo que para el caso de autos se configura una motivación insuficiente y aparente.» | AW85: a) + d): etiqueta expresa 'insuficiente y aparente' | AX85: «En ese entendido, es claro que este Colegiado considera que la nulidad es el último remedio que debe imponerse respecto a la revisión de una decisión judicial, bajo dicha premisa si bien comprende que es posible complementar una decisión judicial que es materia de impugnación, ya sea para confirmar o revocar la misma, sin embargo, ello no es posible particularmente en este caso, debido a que el error en la motivación de la recurrida, vulnera las garantías constitucionales contempladas en los numerales 3) y 5) del artículo 139 de la Constitución Política del Perú de la parte demandada; consecuentemente, en salvaguarda del derecho a la instancia plural de las partes y el derecho de defensa contenidos en los numerales 6) y 14) del artículo 139 de la Constitución, corresponde declarar la nulidad de la recurrida, en mérito al primer párrafo del artículo 171 y artículo 176 in fine del Código Adjetivo (de aplicación supletoria al caso), a fin de que la A quo emita nuevo pronunciamiento de acuerdo a ley y conforme a los antecedentes del proceso.» | AY85: Efecto: nulidad, vicio insubsanable | AZ85: Etiqueta expresa: 'motivación insuficiente y aparente'. SV 368-2024-2SC (se conservó por menor año; existe SV 555-2025-2SC posterior). | BA85: 4154 2022 SV 2024.doc | BB85: Clasificacion_SV_ABR24_Llamoja_defectos | BC85: 1 | BD85: ABREVIADO | BE85: NULA | BF85: AN
A86: 85 | B86: 04275-2015 | C86: 04275-2015 | D86: Pre-2019 | F86: 2SC | G86: SV N° 383-2019-2SC | I86: 23/07/2019 | J86: 2019 | M86: Nula | N86: 2 | O86: 2 | AA86: DECLARADO — “…ho objetivos y constatables, pues contiene una decisión que no se sustenta en la valoración o conjunta y razonada de los medios probatorios aportados al proceso, sino en apreciaciones subjetivas, carentes de fundamentación fáctica y jurídica, que impiden que se establezca la verdad jurídica objetiva en el caso concreto; por tanto, se trata de una resolución…” | AJ86: DECLARADO — “…al adolecer la sentencia materia de revisión de una indebida motivación, por no sustentarse en elementos fácticos y objetivos se desprende que no resulta acorde con lo actuado en el proceso, por lo que debe ser declarada nula. En conclusión, en mérito a lo expuesto prece…” | AP86: Baja D11→— · Migración D15→D21 | BB86: Comparativa_defectos_2018_vs_2024 + Defectos_procesales_SV_CSJA | BC86: 2 | BD86: CONOCIMIENTO | BE86: NULA | BF86: CN
A87: 86 | B87: 04280-2017 | C87: 04280-2017 | D87: Pre-2019 | F87: 3SC | G87: SV N° 157-2019-3SC | I87: 08/04/2019 | J87: 2019 | M87: Revocada | N87: 0 | O87: 2 | U87: ADVERTIDO — “…puntos controvertidos surgen de lo afirmado por una parte y negado por la otra, el juez debió cumplir con señalar como punto controvertido el “Determinar si el contrato de transferencia de dominio del demandante se encuentra caducado o no vigente, así como determinar si la Resolución Gerencial número 323-2016-MPA/GDU/SGAHC, ha sido impugnada y no establece…” | AB87: ADVERTIDO — “…tencia recurrida, la cuestión a resolver por la Sala Superior, está centrada en determinar si la recurrida adolece de insuficiente motivación, y si los demandantes son propietarios o no del inmueble materia de reivindicación, calidad que los legitimaría para pretender la reivindicación. Segundo.- En cuanto a la motivación insuficiente denu…” | AO87: D13: la cita delimita el objeto de la apelación («la cuestión a resolver está centrada en determinar si la recurrida adolece de insuficiente motivación»), no el hallazgo. Sustituir por el considerando conclusivo. | AP87: Reclasificación de estatus —→ADV | BB87: Comparativa_defectos_2018_vs_2024 + Defectos_procesales_SV_CSJA | BC87: 2 | BD87: CONOCIMIENTO | BE87: REVOCADA | BF87: CR
A88: 87 | B88: 04352-2014 | C88: 04352-2014 | D88: Pre-2019 | F88: 1SC | G88: SV N° 385-2018-1SC | I88: 01/08/2018 | J88: 2018 | M88: Revocada | N88: 0 | O88: 0 | BB88: Comparativa_defectos_2018_vs_2024 + Defectos_procesales_SV_CSJA | BC88: 2 | BD88: CONOCIMIENTO | BE88: REVOCADA | BF88: CR
A89: 88 | B89: 04370-2022 | C89: 04370-2022-0-0401-JR-CI-05 | D89: Matriz sumarísimos — grupo 2024 | E89: Ineficacia de acto jurídico | F89: 3SC | G89: SV 306-2024-3SC | H89: Res. 24 (cinco) | I89: 16/08/2024 | J89: 2024 | K89: Ronald Valencia de Romaña | M89: NULA E INSUBSISTENTE (reenvío) | N89: 1 | O89: 2 | Q89: DERIVADO — «dejando en estado de indefensión al indicado esposo, atentando contra el derecho de defensa, el contradictorio y debido proceso»; «habiéndose infringido las reglas del derecho al debido proceso» | R89: DECLARADO — «disponer que el Juez a quo integre a la relación procesal a los herederos de quien fue Máximo Lucas Diaz Rojas» | AP89: Baja D01→— · Baja D20→— · Reclasificación de estatus D02→D02 (derivado) | AZ89: Litisconsorcio necesario pasivo (arts. 93, 95 y 96 CPC): no se integró a los herederos del cotransferente fallecido. | BB89: Matriz_defectos_procesales_1ra_SV | BC89: 1 | BD89: SUMARISIMO | BE89: NULA | BF89: SN
A90: 89 | B90: 04393-2023 | C90: 04393-2023-0-0401-JR-CI-07 | D90: Llamoja — SV de control (2021-2023) | E90: Indemnización (Rímac) | F90: 3SC | G90: 258-2025-3SC | H90: 25 | I90: dos mil veinticinco, Junio veinte | J90: 2025 | L90: Burga Cervantes | M90: REVOCA → FUNDADA EN PARTE | N90: 0 | O90: 0 | AQ90: — Sin vicio de motivación como causal | AS90: No | AT90: «Fundamentos por los cuales, REVOCARON la Sentencia número ciento treinta y seis-dos mil veinticuatro de fecha nueve de octubre de dos mil veinticuatro, de fojas trescientos cinco y siguientes, que resuelve declarar infundada la demanda de indemnización de daños y perjuicios, interpuesta por Máximo Arivilca Bedoya en contra de RIMAC SEGUROS Y REASEGUROS.» | AU90: Error de juicio: revoca y reforma | AV90: «Se dispone la conclusión y archivo del presente proceso (…); en consecuencia, REFORMÁNDOLA Declararon: 1) Fundada en parte la demanda de indemnización por responsabilidad civil contractual interpuesta por Máximo Arivilca Bedoya, en contra de RIMAC SEGUROS Y REASEGUROS; en consecuencia se Ordena que la demandada pague al demandante la suma de S/ 20 000.00 (Veinte mil con 00/100 soles) por concepto de indemnización de daño moral; pago que se efectuara en el término de diez días de consentida o ejecutoriada a presente, bajo apercibimiento de iniciarse ejecución forzada; más los intereses leales que serán calculado en ejecución de sentencia.» | AW90: Fallo reformado (fundada en parte) | AZ90: Error de juicio; sin anulación. | BA90: 4393 2023 SV.doc | BB90: Clasificacion_SV_ABR24_Llamoja_defectos | BC90: 1 | BD90: ABREVIADO | BE90: REVOCADA | BF90: AR
A91: 90 | B91: 04414-2023 | C91: 04414-2023-0-0401-JR-CI-08 | D91: Matriz sumarísimos — grupo 2024 | E91: Otorgamiento de escritura pública | F91: 2SC | G91: SV 508-2025-2SC | H91: Res. 29 (nueve-2SC) | I91: 17/10/2025 | J91: 2025 | K91: Omar del Carpio Medina | M91: NULA (reenvío) | N91: 1 | O91: 1 | AK91: DECLARADO — «nulo todo lo actuado, debiendo retrotraerse el proceso hasta la notificación con la demanda y actuados pertinentes a José Antonio García Nieto» | AP91: Migración D01→D22 · Baja D02→— · Baja D20→— | AZ91: Nulidad refleja del auto de saneamiento anulado por el Auto de Vista precedente; la SV queda sin objeto respecto de los agravios de fondo. | BB91: Matriz_defectos_procesales_1ra_SV | BC91: 1 | BD91: SUMARISIMO | BE91: NULA | BF91: SN
A92: 91 | B92: 04420-2015 | C92: 04420-2015 | D92: Pre-2019 | F92: 2SC | G92: SV N° 515-2018-2SC | I92: 27/09/2018 | J92: 2018 | M92: Nula | N92: 1 | O92: 1 | AE92: DECLARADO — “…al haberse emitido pronunciamiento incongruente con el petitorio de la demanda, genera la nulidad de la impugnada en el extremo que indebidamente se pronuncia por la nulidad de un acto jurídico -no peticionado-, debiendo declararse así de conformidad con el artículo 139° inciso 5 de la Constitució…” | BB92: Comparativa_defectos_2018_vs_2024 + Defectos_procesales_SV_CSJA | BC92: 2 | BD92: CONOCIMIENTO | BE92: NULA | BF92: CN
A93: 92 | B93: 04428-2022 | C93: 04428-2022-0-0401-JR-CI-03 | D93: Matriz sumarísimos — grupo 2024 | E93: Otorgamiento de escritura pública | F93: 1SC | G93: SV 508-2024-1SC | H93: Res. 34 (doce-1SC) | I93: 22/10/2024 | J93: 2024 | K93: Zoilo Alcides Chávez Mamani | M93: REVOCADA → FUNDADA (con voto en discordia) | N93: 0 | O93: 1 | AA93: ADVERTIDO — «La demandada, por su parte ha manifestado que sus causantes le dijeron que no les habían cancelado el precio, afirmación que carece de medio probatorio, pero ha sido validada por el juez» | AZ93: Distribución defectuosa de la carga probatoria (art. 196 CPC) y confusión entre fe notarial del pago y pago mismo. Voto en discordia (Madariaga Condori) por confirmar. | BB93: Matriz_defectos_procesales_1ra_SV | BC93: 1 | BD93: SUMARISIMO | BE93: REVOCADA | BF93: SR
A94: 93 | B94: 04492-2023 | C94: 04492-2023-0-0401-JR-CI-06 | D94: Llamoja — SV de control (2021-2023) | E94: Indemnización (ONP) | F94: 2SC | G94: 219-2025-2SC | H94: 16 | I94: dos mil veinticinco, Mayo quince | J94: 2025 | L94: de la Cuba Chirinos | M94: NULA | N94: 2 | O94: 2 | AD94: DECLARADO — (evidencia en las columnas «Cita textual 1–3» de esta misma fila) | AE94: DECLARADO — (evidencia en las columnas «Cita textual 1–3» de esta misma fila) | AM94: Sí | AQ94: b) Falta de motivación interna | AR94: e) Motivación sustancialmente incongruente | AS94: Sí | AT94: «Lo anterior denota una incongruencia procesal de lo sustentado en la demanda como la normativa empleada en la sentencia apelada.» | AU94: e) Incongruencia procesal (norma aplicada vs. demanda) | AV94: «Por lo que, al no haber analizado la relación jurídica entre la parte demandante y la Oficina de Normalización Previsional y aplicado la normativa correcta, se han configurado vicios en la motivación de la sentencia apelada, que afectan a su razonamiento interno.» | AW94: b) Defecto interno de motivación | AX94: «En tal virtud, esta instancia superior no puede subsanar los referidos vicios de motivación, al tratarse de defectos graves e insubsanables.» | AY94: Efecto: vicio insubsanable, no subsanable en 2.ª instancia | AZ94: La Sala: 'vicios en la motivación... que afectan a su razonamiento interno'; normativa aplicada incongruente con la relación jurídica demandada. | BA94: 4492 2023 SV 2025.doc | BB94: Clasificacion_SV_ABR24_Llamoja_defectos | BC94: 1 | BD94: ABREVIADO | BE94: NULA | BF94: AN
A95: 94 | B95: 04528-2010 | C95: 04528-2010 | D95: Pre-2019 | F95: 1SC | G95: SV N° 457-2018-1SC | I95: 12/09/2018 | J95: 2018 | M95: Revocada | N95: 0 | O95: 0 | BB95: Comparativa_defectos_2018_vs_2024 + Defectos_procesales_SV_CSJA | BC95: 2 | BD95: CONOCIMIENTO | BE95: REVOCADA | BF95: CR
A96: 95 | B96: 04543-2023 | C96: 04543-2023-0-0401-JR-CI-06 | D96: Llamoja — SV de control (2021-2023) | F96: 1SC | H96: 30 | I96: dos mil veinticinco, marzo tres | J96: 2025 | L96: Cervantes López | M96: NULA | N96: 2 | O96: 2 | AH96: DECLARADO — (evidencia en las columnas «Cita textual 1–3» de esta misma fila) | AK96: DECLARADO — «estando pendiente dicha actuación y atendiendo a los efectos que produce la apelada conforme lo previsto en el artículo 380 del Código Procesal Civil» | AP96: Baja D08→— · Alta —→D22 | AQ96: — Sin vicio de motivación como causal | AS96: No | AT96: «En consecuencia, estando pendiente dicha actuación y atendiendo a los efectos que produce la apelada conforme lo previsto en el artículo 380 del Código Procesal Civil, el colegiado concluye que la recurrida adolece de causal de nulidad por no encontrarse aun la causa para resolver hasta que se proceda conforme lo señalado en el auto de vista indicado.» | AU96: Causa no expedita para sentenciar (art. 380 CPC) | AV96: «En tal sentido de conformidad con lo dispuesto en el artículo 171 concordante con el artículo 122 del Código Procesal Civil, debe declararse la nulidad de la recurrida y disponerse que en su oportunidad se expida nueva resolución.» | AW96: Efecto: nulidad (arts. 171 y 122 CPC) y nueva resolución | AZ96: Art. 380 CPC: auto de vista previo anuló la improcedencia de pruebas y ordenó nuevo pronunciamiento; la causa no estaba expedita para sentenciar. Se menciona falta de notificación al rebelde. | BA96: 4543 2023 SV.doc | BB96: Clasificacion_SV_ABR24_Llamoja_defectos | BC96: 1 | BD96: ABREVIADO | BE96: NULA | BF96: AN
A97: 96 | B97: 04554-2022 | C97: 04554-2022-0-0401-JR-CI-05 | D97: Llamoja — SV de control (2021-2023) | E97: Nulidad de acto jurídico (simulación) | F97: 3SC | G97: 413-2024-3SC | H97: 30 | I97: dos mil veinticuatro, Setiembre veintitrés | J97: 2024 | L97: Marroquín Mogrovejo | M97: NULA | N97: 2 | O97: 2 | AE97: DECLARADO — (evidencia en las columnas «Cita textual 1–3» de esta misma fila) | AJ97: DECLARADO — (evidencia en las columnas «Cita textual 1–3» de esta misma fila) | AP97: Migración D20→D21 | AQ97: c) Deficiencia de motivación externa | AS97: Parcial | AT97: «En conclusión, la decisión del Juez de emitir una sentencia inhibitoria es errada, al sostener que se pretende la nulidad por simulación relativa al amparo de la causal contemplada en el inciso 5 del artículo 219 del Código Civil que prevé la nulidad por simulación absoluta, y con ello, que lo pretendido sea jurídicamente imposible; por lo que, al no haberse resuelto en mérito a lo actuado como lo exige el inciso 3 del artículo 122° del Código Procesal Civil, se ha incurrido en nulidad que debe ser declarada por esta Sala Superior.» | AU97: c) Premisa jurídica errónea → inhibitoria errada (art. 122.3 CPC) | AV97: «Por otro lado, no pasa inadvertido que los demandantes no sustentaron jurídicamente la nulidad en el supuesto específico de simulación absoluta prevista en el inciso 5 del artículo 219 del Código Civil; no obstante ello, en aplicación de lo establecido en el Artículo VII del Título Preliminar del Código Procesal Civil por el que “El Juez debe aplicar el derecho que corresponda al proceso, aunque no haya sido invocado por las partes o lo haya sido erróneamente”, corresponde al juez del proceso, aplicar el derecho a los hechos invocados en la demanda de los que resulta inequívoco las alegaciones sobre la simulación relativa, que es, lo que en todo caso, debe ser objeto de pronunciamiento al estar impedido el Juez de la causa, de ir más allá del petitorio.» | AW97: Iura novit curia: corresponde al juez calificar los hechos invocados | AZ97: Premisa jurídica errónea (trata como simulación absoluta lo demandado como relativa) → inhibitoria errada. Cita 'justificación de las premisas'. Clasificación c) tentativa. | BA97: 4554 2022 SVV.doc | BB97: Clasificacion_SV_ABR24_Llamoja_defectos | BC97: 1 | BD97: ABREVIADO | BE97: NULA | BF97: AN
A98: 97 | B98: 04585-2017 | C98: 04585-2017-0-0401-JR-CI-07 | D98: Matriz sumarísimos — anteriores a 2019 | E98: Desalojo por ocupación precaria | F98: 3SC | G98: SV 383-2018-3SC | H98: Res. 9 (tres) | I98: 31/07/2018 | J98: 2018 | K98: Carlos Polanco Gutiérrez | M98: REVOCADA → INFUNDADA | N98: 0 | O98: 1 | AE98: ADVERTIDO — «no obstante haberse declarado por el Juez de origen, (formalmente), improcedente la demanda, en los fundamentos de la sentencia apelada, ha expresado motivaciones referidas al fondo de la cuestión controvertida» | AZ98: Incongruencia interna entre parte considerativa (fondo) y resolutiva (inhibitoria); contraviene la regla 6 del IV Pleno Casatorio. Corregido en instancia. | BB98: Matriz_defectos_procesales_1ra_SV | BC98: 1 | BD98: SUMARISIMO | BE98: REVOCADA | BF98: SR
A99: 98 | B99: 04605-2022 | C99: 04605-2022 | D99: 2024 | F99: 3SC | G99: SV N° 362-2025-3SC | I99: 16/09/2025 | J99: 2025 | M99: Revocada | N99: 0 | O99: 1 | Z99: ALEGADO — “…el Juez yerra al omitir valorar la escritura pública número 4659 celebrada por los herederos declarados y demandados en este proceso Víctor Héctor Torres Valencia y Marlube Maritza Yane Torres Valencia, sobre donación de derechos y transacción extrajudicial; 2.4) El Juez yerra de der…” | AO99: El texto registrado enumera agravios («El Juez yerra al omitir valorar…; 2.4) El Juez yerra…»). Verificar si la Sala hace suya la constatación antes de computarla como declarada. | AP99: Reclasificación de estatus D11→D11 (alegado) | BB99: Comparativa_defectos_2018_vs_2024 + Defectos_procesales_SV_CSJA | BC99: 2 | BD99: CONOCIMIENTO | BE99: REVOCADA | BF99: CR
A100: 99 | B100: 04667-2022 | C100: 04667-2022-0-0401-JR-CI-02 | D100: Llamoja — SV de control (2021-2023) | E100: Impugnación de acuerdos | F100: 1SC | H100: 18 | I100: dos mil veinticinco, agosto once | J100: 2025 | L100: Zamalloa Campero | M100: NULA E INSUBSISTENTE | N100: 0 | O100: 0 | AN100: Sí | AP100: Baja D20→— | AQ100: — Sin vicio de motivación como causal | AS100: No | AT100: «En ese sentido, resulta notorio para este colegiado que la demandante se encontraba dentro del plazo de sesenta días para impugnar dichos acuerdos en tanto no tuvo acceso a las actas hasta el año dos mil veintidós, lo cual era un requisito.» | AU100: Error de juicio: cómputo del plazo del art. 92 CC | AV100: «Pese a ello, este colegiado advierte que, para impugnar un acuerdo -conforme lo dispuesto en el artículo 92 del Código Civil-, es necesario que la parte impugnante cuente con el acta que contiene dicho acuerdo, lo cual no se ha suscitado en el presente caso por cuanto a la carta notarial notificada en fecha siete de abril de dos mil veintiuno no se ha anexado ninguna de las actas materias de impugnación, siendo que la demandante afirma que recién tuvo acceso a las actas de las asambleas extraordinarias en fecha catorce de junio de dos mil veintidós, cuando se le notificó con la contestación de la demanda de amparo que interpuso en contra de la asociación demandada.» | AW100: Fundamento: sin acta no corre el plazo de impugnación | AZ100: Error de juicio (cómputo del plazo art. 92 CC) resuelto vía nulidad; sin vicio de motivación. Candidato a 'nulidad evitable' (tesis Huánuco). | BA100: 4667 2022 SV.doc | BB100: Clasificacion_SV_ABR24_Llamoja_defectos | BC100: 1 | BD100: ABREVIADO | BE100: NULA | BF100: AN
...

Sheet Marcas_declaradas
A1: Solo registros DECLARADOS por la Sala como fundamento de la decisión (ratio). Es la base de conteo recomendada para la tesis.
A2: N° | B2: Clave expediente | C2: Corpus / grupo | D2: Año SV | E2: Sala | F2: D01 | G2: D02 | H2: D03 | I2: D04 | J2: D05 | K2: D06 | L2: D07 | M2: D08 | N2: D09 | O2: D10 | P2: D11 | Q2: D12 | R2: D13 | S2: D14 | T2: D15 | U2: D16 | V2: D17 | W2: D18 | X2: D19 | Y2: D20 | Z2: D21 | AA2: D22 | AB2: D23 | AC2: Total
A3: 1 | B3: 00001-2018 | C3: Matriz sumarísimos — anteriores a 2019 | D3: 2019 | E3: 2SC | F3: 0 | G3: 0 | H3: 0 | I3: 0 | J3: 0 | K3: 0 | L3: 0 | M3: 0 | N3: 0 | O3: 0 | P3: 0 | Q3: 1 | R3: 0 | S3: 0 | T3: 1 | U3: 0 | V3: 0 | W3: 0 | X3: 0 | Y3: 0 | Z3: 0 | AA3: 0 | AB3: 0 | AC3: 2
A4: 2 | B4: 00072-2023 | C4: Matriz sumarísimos — grupo 2024 | D4: 2025 | E4: 2SC | F4: 0 | G4: 0 | H4: 0 | I4: 0 | J4: 0 | K4: 0 | L4: 0 | M4: 0 | N4: 0 | O4: 0 | P4: 1 | Q4: 0 | R4: 0 | S4: 0 | T4: 1 | U4: 1 | V4: 0 | W4: 0 | X4: 0 | Y4: 0 | Z4: 1 | AA4: 0 | AB4: 0 | AC4: 4
A5: 3 | B5: 00115-2012 | C5: Matriz sumarísimos — anteriores a 2019 | D5: 2018 | E5: 2SC | F5: 1 | G5: 0 | H5: 0 | I5: 0 | J5: 0 | K5: 0 | L5: 0 | M5: 0 | N5: 0 | O5: 0 | P5: 0 | Q5: 0 | R5: 0 | S5: 0 | T5: 0 | U5: 0 | V5: 0 | W5: 0 | X5: 0 | Y5: 0 | Z5: 0 | AA5: 0 | AB5: 0 | AC5: 1
A6: 4 | B6: 00129-2022 | C6: Matriz sumarísimos — grupo 2024 | D6: 2024 | E6: 2SC | F6: 0 | G6: 0 | H6: 0 | I6: 0 | J6: 0 | K6: 0 | L6: 0 | M6: 0 | N6: 0 | O6: 0 | P6: 0 | Q6: 0 | R6: 0 | S6: 0 | T6: 0 | U6: 0 | V6: 0 | W6: 0 | X6: 0 | Y6: 0 | Z6: 0 | AA6: 0 | AB6: 0 | AC6: 0
A7: 5 | B7: 00132-2015 | C7: Pre-2019 | D7: 2018 | E7: 2SC | F7: 0 | G7: 0 | H7: 0 | I7: 0 | J7: 0 | K7: 0 | L7: 0 | M7: 0 | N7: 0 | O7: 0 | P7: 0 | Q7: 0 | R7: 0 | S7: 0 | T7: 0 | U7: 0 | V7: 0 | W7: 0 | X7: 0 | Y7: 0 | Z7: 0 | AA7: 0 | AB7: 0 | AC7: 0
A8: 6 | B8: 00153-2022 | C8: Matriz sumarísimos — grupo 2024 | D8: 2025 | E8: 3SC | F8: 0 | G8: 0 | H8: 0 | I8: 0 | J8: 0 | K8: 0 | L8: 0 | M8: 0 | N8: 0 | O8: 0 | P8: 0 | Q8: 0 | R8: 0 | S8: 0 | T8: 0 | U8: 0 | V8: 0 | W8: 0 | X8: 0 | Y8: 0 | Z8: 0 | AA8: 0 | AB8: 0 | AC8: 0
A9: 7 | B9: 00192-2021 | C9: 2024 | D9: 2026 | F9: 0 | G9: 0 | H9: 0 | I9: 0 | J9: 0 | K9: 0 | L9: 0 | M9: 0 | N9: 0 | O9: 0 | P9: 0 | Q9: 0 | R9: 0 | S9: 0 | T9: 0 | U9: 0 | V9: 0 | W9: 0 | X9: 0 | Y9: 0 | Z9: 0 | AA9: 0 | AB9: 0 | AC9: 0
A10: 8 | B10: 00234-2018 | C10: Matriz sumarísimos — anteriores a 2019 | D10: 2019 | E10: 3SC | F10: 0 | G10: 0 | H10: 0 | I10: 0 | J10: 0 | K10: 0 | L10: 0 | M10: 0 | N10: 0 | O10: 0 | P10: 0 | Q10: 0 | R10: 0 | S10: 0 | T10: 0 | U10: 0 | V10: 0 | W10: 0 | X10: 0 | Y10: 0 | Z10: 0 | AA10: 0 | AB10: 0 | AC10: 0
A11: 9 | B11: 00320-2023 | C11: 2024 | D11: 2025 | E11: 2SC | F11: 0 | G11: 0 | H11: 0 | I11: 0 | J11: 0 | K11: 0 | L11: 0 | M11: 0 | N11: 0 | O11: 0 | P11: 0 | Q11: 0 | R11: 1 | S11: 0 | T11: 0 | U11: 0 | V11: 0 | W11: 0 | X11: 0 | Y11: 0 | Z11: 0 | AA11: 0 | AB11: 0 | AC11: 1
A12: 10 | B12: 00340-2002 | C12: Pre-2019 | D12: 2018 | E12: 2SC | F12: 0 | G12: 1 | H12: 0 | I12: 0 | J12: 0 | K12: 0 | L12: 0 | M12: 0 | N12: 0 | O12: 0 | P12: 0 | Q12: 0 | R12: 0 | S12: 0 | T12: 0 | U12: 1 | V12: 0 | W12: 0 | X12: 0 | Y12: 0 | Z12: 0 | AA12: 0 | AB12: 0 | AC12: 2
A13: 11 | B13: 00367-2024 | C13: Matriz sumarísimos — grupo 2024 | D13: 2024 | E13: 1SC | F13: 0 | G13: 0 | H13: 0 | I13: 0 | J13: 0 | K13: 0 | L13: 0 | M13: 0 | N13: 0 | O13: 0 | P13: 0 | Q13: 0 | R13: 0 | S13: 0 | T13: 0 | U13: 0 | V13: 0 | W13: 0 | X13: 0 | Y13: 0 | Z13: 0 | AA13: 0 | AB13: 0 | AC13: 0
A14: 12 | B14: 00414-2023 | C14: Llamoja — SV de control (2021-2023) | D14: 2025 | E14: 3SC | F14: 0 | G14: 0 | H14: 0 | I14: 0 | J14: 0 | K14: 0 | L14: 0 | M14: 0 | N14: 0 | O14: 0 | P14: 0 | Q14: 0 | R14: 1 | S14: 0 | T14: 0 | U14: 1 | V14: 0 | W14: 0 | X14: 0 | Y14: 0 | Z14: 0 | AA14: 0 | AB14: 0 | AC14: 2
A15: 13 | B15: 00428-2017 | C15: Matriz sumarísimos — anteriores a 2019 | D15: 2020 | E15: 2SC | F15: 0 | G15: 0 | H15: 0 | I15: 0 | J15: 0 | K15: 0 | L15: 0 | M15: 0 | N15: 0 | O15: 0 | P15: 0 | Q15: 0 | R15: 0 | S15: 0 | T15: 0 | U15: 0 | V15: 0 | W15: 0 | X15: 0 | Y15: 0 | Z15: 0 | AA15: 0 | AB15: 0 | AC15: 0
A16: 14 | B16: 00598-2022 | C16: 2024 | D16: 2025 | E16: 3SC | F16: 0 | G16: 0 | H16: 0 | I16: 0 | J16: 0 | K16: 0 | L16: 0 | M16: 0 | N16: 0 | O16: 0 | P16: 0 | Q16: 1 | R16: 1 | S16: 0 | T16: 0 | U16: 0 | V16: 0 | W16: 0 | X16: 0 | Y16: 0 | Z16: 0 | AA16: 0 | AB16: 0 | AC16: 2
A17: 15 | B17: 00646-2024 | C17: Matriz sumarísimos — grupo 2024 | D17: 2025 | E17: 2SC | F17: 0 | G17: 0 | H17: 0 | I17: 0 | J17: 0 | K17: 0 | L17: 0 | M17: 0 | N17: 0 | O17: 0 | P17: 0 | Q17: 1 | R17: 0 | S17: 0 | T17: 0 | U17: 1 | V17: 0 | W17: 0 | X17: 0 | Y17: 0 | Z17: 0 | AA17: 0 | AB17: 1 | AC17: 3
A18: 16 | B18: 00661-2023 | C18: Matriz sumarísimos — grupo 2024 | D18: 2025 | E18: 2SC | F18: 0 | G18: 0 | H18: 0 | I18: 0 | J18: 0 | K18: 0 | L18: 0 | M18: 0 | N18: 0 | O18: 0 | P18: 0 | Q18: 1 | R18: 1 | S18: 0 | T18: 0 | U18: 0 | V18: 0 | W18: 0 | X18: 0 | Y18: 0 | Z18: 0 | AA18: 0 | AB18: 0 | AC18: 2
A19: 17 | B19: 00742-2022 | C19: 2024 | D19: 2025 | F19: 0 | G19: 1 | H19: 0 | I19: 1 | J19: 0 | K19: 0 | L19: 0 | M19: 0 | N19: 0 | O19: 0 | P19: 1 | Q19: 0 | R19: 0 | S19: 0 | T19: 0 | U19: 1 | V19: 0 | W19: 0 | X19: 0 | Y19: 0 | Z19: 0 | AA19: 0 | AB19: 0 | AC19: 4
A20: 18 | B20: 00748-2013 | C20: Pre-2019 | D20: 2018 | E20: 2SC | F20: 0 | G20: 0 | H20: 0 | I20: 0 | J20: 0 | K20: 0 | L20: 0 | M20: 0 | N20: 0 | O20: 0 | P20: 0 | Q20: 0 | R20: 0 | S20: 0 | T20: 1 | U20: 0 | V20: 0 | W20: 0 | X20: 0 | Y20: 0 | Z20: 0 | AA20: 0 | AB20: 0 | AC20: 1
A21: 19 | B21: 00760-2021 | C21: Llamoja — SV de control (2021-2023) | D21: 2025 | E21: 3SC | F21: 0 | G21: 0 | H21: 0 | I21: 0 | J21: 0 | K21: 0 | L21: 0 | M21: 1 | N21: 0 | O21: 1 | P21: 0 | Q21: 0 | R21: 0 | S21: 0 | T21: 0 | U21: 0 | V21: 0 | W21: 0 | X21: 0 | Y21: 0 | Z21: 0 | AA21: 0 | AB21: 0 | AC21: 2
A22: 20 | B22: 00774-2021 | C22: Llamoja — SV de control (2021-2023) | D22: 2025 | E22: 2SC | F22: 0 | G22: 0 | H22: 0 | I22: 0 | J22: 0 | K22: 0 | L22: 0 | M22: 0 | N22: 0 | O22: 0 | P22: 0 | Q22: 0 | R22: 0 | S22: 0 | T22: 0 | U22: 1 | V22: 0 | W22: 0 | X22: 0 | Y22: 0 | Z22: 1 | AA22: 0 | AB22: 0 | AC22: 2
A23: 21 | B23: 00788-2013 | C23: Pre-2019 | D23: 2021 | E23: 2SC | F23: 0 | G23: 0 | H23: 0 | I23: 0 | J23: 0 | K23: 0 | L23: 0 | M23: 0 | N23: 0 | O23: 0 | P23: 0 | Q23: 0 | R23: 0 | S23: 0 | T23: 0 | U23: 1 | V23: 0 | W23: 0 | X23: 0 | Y23: 0 | Z23: 0 | AA23: 0 | AB23: 0 | AC23: 1
A24: 22 | B24: 00848-2011 | C24: Matriz sumarísimos — anteriores a 2019 | D24: 2019 | E24: 3SC | F24: 0 | G24: 0 | H24: 0 | I24: 0 | J24: 0 | K24: 0 | L24: 0 | M24: 0 | N24: 0 | O24: 0 | P24: 0 | Q24: 0 | R24: 0 | S24: 0 | T24: 0 | U24: 0 | V24: 0 | W24: 0 | X24: 0 | Y24: 0 | Z24: 0 | AA24: 0 | AB24: 0 | AC24: 0
A25: 23 | B25: 00856-2017 | C25: Pre-2019 | D25: 2019 | E25: 1SC | F25: 0 | G25: 0 | H25: 0 | I25: 0 | J25: 0 | K25: 0 | L25: 0 | M25: 0 | N25: 0 | O25: 0 | P25: 0 | Q25: 0 | R25: 0 | S25: 0 | T25: 0 | U25: 1 | V25: 0 | W25: 0 | X25: 0 | Y25: 0 | Z25: 0 | AA25: 0 | AB25: 0 | AC25: 1
A26: 24 | B26: 00879-2022 | C26: Llamoja — SV de control (2021-2023) | D26: 2025 | E26: 1SC | F26: 0 | G26: 0 | H26: 0 | I26: 0 | J26: 0 | K26: 0 | L26: 0 | M26: 0 | N26: 0 | O26: 0 | P26: 0 | Q26: 0 | R26: 0 | S26: 0 | T26: 1 | U26: 1 | V26: 0 | W26: 0 | X26: 0 | Y26: 0 | Z26: 0 | AA26: 0 | AB26: 0 | AC26: 2
A27: 25 | B27: 00898-2013 | C27: Pre-2019 | D27: 2018 | E27: 3SC | F27: 0 | G27: 0 | H27: 0 | I27: 0 | J27: 0 | K27: 0 | L27: 0 | M27: 0 | N27: 0 | O27: 0 | P27: 0 | Q27: 0 | R27: 0 | S27: 0 | T27: 0 | U27: 0 | V27: 0 | W27: 0 | X27: 0 | Y27: 0 | Z27: 0 | AA27: 0 | AB27: 0 | AC27: 0
A28: 26 | B28: 00933-2022 | C28: Llamoja — SV de control (2021-2023) | D28: 2024 | E28: 3SC | F28: 0 | G28: 0 | H28: 0 | I28: 0 | J28: 0 | K28: 0 | L28: 0 | M28: 0 | N28: 0 | O28: 0 | P28: 0 | Q28: 0 | R28: 0 | S28: 1 | T28: 0 | U28: 1 | V28: 0 | W28: 0 | X28: 0 | Y28: 0 | Z28: 0 | AA28: 0 | AB28: 0 | AC28: 2
A29: 27 | B29: 00965-2015 | C29: Pre-2019 | D29: 2019 | E29: 3SC | F29: 0 | G29: 0 | H29: 0 | I29: 0 | J29: 0 | K29: 1 | L29: 0 | M29: 0 | N29: 0 | O29: 0 | P29: 0 | Q29: 0 | R29: 0 | S29: 0 | T29: 0 | U29: 0 | V29: 0 | W29: 0 | X29: 0 | Y29: 0 | Z29: 0 | AA29: 0 | AB29: 1 | AC29: 2
A30: 28 | B30: 00979-2024 | C30: Matriz sumarísimos — grupo 2024 | D30: 2025 | E30: 1SC | F30: 0 | G30: 0 | H30: 0 | I30: 0 | J30: 0 | K30: 0 | L30: 0 | M30: 0 | N30: 0 | O30: 0 | P30: 0 | Q30: 0 | R30: 0 | S30: 0 | T30: 0 | U30: 0 | V30: 0 | W30: 0 | X30: 0 | Y30: 0 | Z30: 0 | AA30: 0 | AB30: 0 | AC30: 0
A31: 29 | B31: 00992-2016 | C31: Pre-2019 | D31: 2019 | E31: 3SC | F31: 0 | G31: 0 | H31: 0 | I31: 0 | J31: 0 | K31: 0 | L31: 0 | M31: 0 | N31: 0 | O31: 0 | P31: 0 | Q31: 0 | R31: 0 | S31: 0 | T31: 0 | U31: 1 | V31: 0 | W31: 0 | X31: 0 | Y31: 0 | Z31: 0 | AA31: 0 | AB31: 1 | AC31: 2
... A40: 38 | B40: 01647-2019 | C40: 2024 | D40: 2026 | E40: 2SC | F40: 0 | G40: 0 | H40: 0 | I40: 0 | J40: 0 | K40: 0 | L40: 0 | M40: 0 | N40: 0 | O40: 0 | P40: 0 | Q40: 1 | R40: 0 | S40: 1 | T40: 0 | U40: 0 | V40: 0 | W40: 0 | X40: 0 | Y40: 0 | Z40: 0 | AA40: 0 | AB40: 0 | AC40: 2
A41: 39 | B41: 01650-2023 | C41: 2024 | D41: 2025 | F41: 0 | G41: 0 | H41: 0 | I41: 0 | J41: 0 | K41: 0 | L41: 0 | M41: 0 | N41: 0 | O41: 0 | P41: 0 | Q41: 0 | R41: 0 | S41: 0 | T41: 0 | U41: 0 | V41: 0 | W41: 0 | X41: 0 | Y41: 0 | Z41: 0 | AA41: 0 | AB41: 0 | AC41: 0
A42: 40 | B42: 01681-2023 | C42: Llamoja — SV de control (2021-2023) | D42: 2025 | E42: 3SC | F42: 0 | G42: 0 | H42: 0 | I42: 0 | J42: 0 | K42: 1 | L42: 0 | M42: 0 | N42: 0 | O42: 0 | P42: 0 | Q42: 0 | R42: 0 | S42: 0 | T42: 1 | U42: 0 | V42: 0 | W42: 0 | X42: 0 | Y42: 0 | Z42: 0 | AA42: 0 | AB42: 0 | AC42: 2
A43: 41 | B43: 01723-2022 | C43: Llamoja — SV de control (2021-2023) | D43: 2025 | E43: 2SC | F43: 0 | G43: 0 | H43: 0 | I43: 0 | J43: 0 | K43: 0 | L43: 0 | M43: 0 | N43: 0 | O43: 0 | P43: 0 | Q43: 0 | R43: 0 | S43: 0 | T43: 0 | U43: 0 | V43: 0 | W43: 0 | X43: 0 | Y43: 0 | Z43: 0 | AA43: 0 | AB43: 0 | AC43: 0
A44: 42 | B44: 01734-2017 | C44: Pre-2019 | D44: 2019 | E44: 2SC | F44: 0 | G44: 0 | H44: 0 | I44: 0 | J44: 0 | K44: 0 | L44: 0 | M44: 0 | N44: 0 | O44: 0 | P44: 0 | Q44: 0 | R44: 0 | S44: 0 | T44: 1 | U44: 0 | V44: 0 | W44: 0 | X44: 0 | Y44: 0 | Z44: 0 | AA44: 0 | AB44: 0 | AC44: 1
A45: 43 | B45: 01835-2024 | C45: 2024 | D45: 2025 | E45: 1SC | F45: 0 | G45: 0 | H45: 0 | I45: 0 | J45: 0 | K45: 0 | L45: 0 | M45: 0 | N45: 0 | O45: 0 | P45: 0 | Q45: 0 | R45: 0 | S45: 0 | T45: 0 | U45: 0 | V45: 0 | W45: 0 | X45: 0 | Y45: 0 | Z45: 0 | AA45: 0 | AB45: 0 | AC45: 0
A46: 44 | B46: 01869-2023 | C46: Llamoja — SV de control (2021-2023) | D46: 2026 | E46: 2SC | F46: 0 | G46: 0 | H46: 0 | I46: 0 | J46: 0 | K46: 0 | L46: 0 | M46: 0 | N46: 0 | O46: 0 | P46: 0 | Q46: 1 | R46: 1 | S46: 0 | T46: 0 | U46: 0 | V46: 0 | W46: 0 | X46: 0 | Y46: 0 | Z46: 1 | AA46: 0 | AB46: 0 | AC46: 3
A47: 45 | B47: 01879-2022 | C47: 2024 | D47: 2025 | E47: 2SC | F47: 0 | G47: 0 | H47: 0 | I47: 0 | J47: 0 | K47: 0 | L47: 0 | M47: 0 | N47: 0 | O47: 0 | P47: 0 | Q47: 0 | R47: 0 | S47: 0 | T47: 0 | U47: 0 | V47: 0 | W47: 0 | X47: 0 | Y47: 0 | Z47: 0 | AA47: 0 | AB47: 1 | AC47: 1
A48: 46 | B48: 01888-2011 | C48: Pre-2019 | D48: 2020 | E48: 2SC | F48: 0 | G48: 0 | H48: 0 | I48: 0 | J48: 0 | K48: 0 | L48: 0 | M48: 0 | N48: 0 | O48: 0 | P48: 0 | Q48: 0 | R48: 0 | S48: 0 | T48: 0 | U48: 0 | V48: 0 | W48: 0 | X48: 1 | Y48: 0 | Z48: 0 | AA48: 0 | AB48: 0 | AC48: 1
A49: 47 | B49: 01946-2016 | C49: Pre-2019 | D49: 2019 | E49: 3SC | F49: 0 | G49: 0 | H49: 0 | I49: 0 | J49: 0 | K49: 0 | L49: 0 | M49: 0 | N49: 0 | O49: 0 | P49: 0 | Q49: 0 | R49: 0 | S49: 0 | T49: 0 | U49: 0 | V49: 0 | W49: 0 | X49: 0 | Y49: 0 | Z49: 0 | AA49: 0 | AB49: 0 | AC49: 0
A50: 48 | B50: 02167-2023 | C50: Matriz sumarísimos — grupo 2024 | D50: 2025 | E50: 2SC | F50: 0 | G50: 0 | H50: 0 | I50: 0 | J50: 0 | K50: 0 | L50: 0 | M50: 0 | N50: 0 | O50: 0 | P50: 0 | Q50: 0 | R50: 0 | S50: 0 | T50: 0 | U50: 0 | V50: 0 | W50: 0 | X50: 0 | Y50: 0 | Z50: 0 | AA50: 0 | AB50: 0 | AC50: 0
A51: 49 | B51: 02275-2023 | C51: Llamoja — SV de control (2021-2023) | D51: 2025 | E51: 3SC | F51: 1 | G51: 0 | H51: 0 | I51: 1 | J51: 0 | K51: 0 | L51: 0 | M51: 0 | N51: 0 | O51: 0 | P51: 0 | Q51: 0 | R51: 0 | S51: 0 | T51: 0 | U51: 0 | V51: 0 | W51: 0 | X51: 0 | Y51: 0 | Z51: 0 | AA51: 0 | AB51: 0 | AC51: 2
A52: 50 | B52: 02371-2021 | C52: 2024 | D52: 2025 | F52: 0 | G52: 0 | H52: 0 | I52: 0 | J52: 0 | K52: 0 | L52: 0 | M52: 0 | N52: 0 | O52: 0 | P52: 0 | Q52: 0 | R52: 0 | S52: 0 | T52: 0 | U52: 0 | V52: 0 | W52: 0 | X52: 0 | Y52: 0 | Z52: 0 | AA52: 0 | AB52: 0 | AC52: 0
A53: 51 | B53: 02483-2021 | C53: Llamoja — SV de control (2021-2023) | D53: 2023 | E53: 2SC | F53: 0 | G53: 0 | H53: 1 | I53: 0 | J53: 0 | K53: 0 | L53: 0 | M53: 0 | N53: 0 | O53: 0 | P53: 0 | Q53: 0 | R53: 0 | S53: 0 | T53: 0 | U53: 0 | V53: 0 | W53: 0 | X53: 0 | Y53: 0 | Z53: 0 | AA53: 0 | AB53: 0 | AC53: 1
A54: 52 | B54: 02505-2009 | C54: Pre-2019 | D54: 2019 | E54: 3SC | F54: 0 | G54: 1 | H54: 0 | I54: 0 | J54: 0 | K54: 0 | L54: 0 | M54: 0 | N54: 0 | O54: 0 | P54: 0 | Q54: 0 | R54: 0 | S54: 0 | T54: 0 | U54: 1 | V54: 0 | W54: 0 | X54: 0 | Y54: 0 | Z54: 0 | AA54: 0 | AB54: 0 | AC54: 2
A55: 53 | B55: 02532-2017 | C55: Matriz sumarísimos — anteriores a 2019 | D55: 2018 | E55: 1SC | F55: 1 | G55: 0 | H55: 1 | I55: 0 | J55: 0 | K55: 0 | L55: 0 | M55: 0 | N55: 0 | O55: 0 | P55: 0 | Q55: 0 | R55: 0 | S55: 0 | T55: 0 | U55: 0 | V55: 0 | W55: 0 | X55: 0 | Y55: 0 | Z55: 0 | AA55: 0 | AB55: 0 | AC55: 2
A56: 54 | B56: 02635-2019 | C56: 2024 | D56: 2023 | F56: 0 | G56: 0 | H56: 0 | I56: 0 | J56: 0 | K56: 0 | L56: 0 | M56: 0 | N56: 0 | O56: 0 | P56: 1 | Q56: 0 | R56: 0 | S56: 1 | T56: 0 | U56: 0 | V56: 0 | W56: 0 | X56: 0 | Y56: 0 | Z56: 0 | AA56: 0 | AB56: 0 | AC56: 2
A57: 55 | B57: 02641-2010 | C57: Pre-2019 | D57: 2018 | E57: 1SC | F57: 0 | G57: 0 | H57: 0 | I57: 0 | J57: 0 | K57: 0 | L57: 1 | M57: 0 | N57: 0 | O57: 0 | P57: 0 | Q57: 0 | R57: 0 | S57: 0 | T57: 0 | U57: 0 | V57: 0 | W57: 0 | X57: 0 | Y57: 0 | Z57: 0 | AA57: 0 | AB57: 0 | AC57: 1
A58: 56 | B58: 02706-2015 | C58: Pre-2019 | D58: 2019 | E58: 2SC | F58: 0 | G58: 0 | H58: 1 | I58: 0 | J58: 0 | K58: 0 | L58: 0 | M58: 0 | N58: 0 | O58: 0 | P58: 0 | Q58: 0 | R58: 0 | S58: 0 | T58: 0 | U58: 0 | V58: 0 | W58: 0 | X58: 0 | Y58: 0 | Z58: 0 | AA58: 0 | AB58: 0 | AC58: 1
A59: 57 | B59: 02706-2016 | C59: Matriz sumarísimos — anteriores a 2019 | D59: 2021 | E59: 2SC | F59: 0 | G59: 0 | H59: 0 | I59: 0 | J59: 0 | K59: 0 | L59: 0 | M59: 0 | N59: 0 | O59: 0 | P59: 0 | Q59: 0 | R59: 0 | S59: 0 | T59: 0 | U59: 0 | V59: 0 | W59: 0 | X59: 0 | Y59: 0 | Z59: 0 | AA59: 0 | AB59: 0 | AC59: 0
A60: 58 | B60: 02712-2023 | C60: Llamoja — SV de control (2021-2023) | D60: 2025 | E60: 2SC | F60: 0 | G60: 0 | H60: 0 | I60: 0 | J60: 0 | K60: 0 | L60: 0 | M60: 0 | N60: 0 | O60: 0 | P60: 0 | Q60: 0 | R60: 0 | S60: 0 | T60: 0 | U60: 0 | V60: 0 | W60: 0 | X60: 0 | Y60: 0 | Z60: 0 | AA60: 0 | AB60: 0 | AC60: 0
A61: 59 | B61: 02718-2015 | C61: Matriz sumarísimos — anteriores a 2019 | D61: 2018 | E61: 1SC | F61: 0 | G61: 0 | H61: 0 | I61: 0 | J61: 0 | K61: 0 | L61: 1 | M61: 0 | N61: 0 | O61: 0 | P61: 0 | Q61: 0 | R61: 0 | S61: 0 | T61: 0 | U61: 1 | V61: 0 | W61: 0 | X61: 0 | Y61: 0 | Z61: 0 | AA61: 0 | AB61: 1 | AC61: 3
A62: 60 | B62: 02723-2023 | C62: Llamoja — SV de control (2021-2023) | D62: 2025 | E62: 2SC | F62: 0 | G62: 0 | H62: 0 | I62: 0 | J62: 0 | K62: 0 | L62: 0 | M62: 0 | N62: 0 | O62: 0 | P62: 0 | Q62: 0 | R62: 0 | S62: 0 | T62: 0 | U62: 0 | V62: 0 | W62: 0 | X62: 0 | Y62: 0 | Z62: 0 | AA62: 0 | AB62: 0 | AC62: 0
A63: 61 | B63: 02792-2023 | C63: Llamoja — SV de control (2021-2023) | D63: 2025 | E63: 1SC | F63: 0 | G63: 0 | H63: 0 | I63: 0 | J63: 0 | K63: 0 | L63: 0 | M63: 0 | N63: 0 | O63: 0 | P63: 0 | Q63: 0 | R63: 0 | S63: 0 | T63: 0 | U63: 0 | V63: 0 | W63: 0 | X63: 0 | Y63: 0 | Z63: 0 | AA63: 0 | AB63: 0 | AC63: 0
A64: 62 | B64: 02814-2015 | C64: Pre-2019 | D64: 2019 | E64: 3SC | F64: 0 | G64: 0 | H64: 0 | I64: 0 | J64: 0 | K64: 0 | L64: 0 | M64: 0 | N64: 0 | O64: 0 | P64: 0 | Q64: 0 | R64: 0 | S64: 1 | T64: 0 | U64: 0 | V64: 0 | W64: 0 | X64: 0 | Y64: 0 | Z64: 0 | AA64: 0 | AB64: 0 | AC64: 1
A65: 63 | B65: 02851-2023 | C65: Llamoja — SV de control (2021-2023) | D65: 2025 | E65: 1SC | F65: 0 | G65: 0 | H65: 0 | I65: 0 | J65: 0 | K65: 0 | L65: 0 | M65: 0 | N65: 0 | O65: 0 | P65: 0 | Q65: 0 | R65: 0 | S65: 0 | T65: 0 | U65: 0 | V65: 0 | W65: 0 | X65: 1 | Y65: 0 | Z65: 0 | AA65: 1 | AB65: 0 | AC65: 2
A66: 64 | B66: 02943-2016 | C66: Pre-2019 | D66: 2018 | E66: 2SC | F66: 0 | G66: 0 | H66: 0 | I66: 0 | J66: 0 | K66: 0 | L66: 0 | M66: 0 | N66: 0 | O66: 0 | P66: 0 | Q66: 0 | R66: 0 | S66: 0 | T66: 0 | U66: 1 | V66: 0 | W66: 0 | X66: 0 | Y66: 0 | Z66: 0 | AA66: 0 | AB66: 1 | AC66: 2
A67: 65 | B67: 02973-2022 | C67: Llamoja — SV de control (2021-2023) | D67: 2025 | E67: 2SC | F67: 0 | G67: 0 | H67: 0 | I67: 0 | J67: 0 | K67: 0 | L67: 0 | M67: 0 | N67: 0 | O67: 0 | P67: 0 | Q67: 0 | R67: 0 | S67: 0 | T67: 0 | U67: 0 | V67: 0 | W67: 0 | X67: 0 | Y67: 0 | Z67: 1 | AA67: 0 | AB67: 0 | AC67: 1
A68: 66 | B68: 03228-2013 | C68: Pre-2019 | D68: 2018 | E68: 2SC | F68: 0 | G68: 0 | H68: 0 | I68: 0 | J68: 0 | K68: 0 | L68: 0 | M68: 0 | N68: 0 | O68: 0 | P68: 0 | Q68: 1 | R68: 0 | S68: 1 | T68: 0 | U68: 1 | V68: 0 | W68: 0 | X68: 0 | Y68: 0 | Z68: 0 | AA68: 0 | AB68: 0 | AC68: 3
... A73: 71 | B73: 03731-2015 | C73: Matriz sumarísimos — anteriores a 2019 | D73: 2018 | E73: 1SC | F73: 0 | G73: 0 | H73: 0 | I73: 0 | J73: 0 | K73: 0 | L73: 0 | M73: 0 | N73: 0 | O73: 0 | P73: 0 | Q73: 0 | R73: 0 | S73: 0 | T73: 0 | U73: 0 | V73: 0 | W73: 0 | X73: 0 | Y73: 0 | Z73: 0 | AA73: 1 | AB73: 0 | AC73: 1
A74: 72 | B74: 03754-2015 | C74: Matriz sumarísimos — anteriores a 2019 | F74: 0 | G74: 0 | H74: 0 | I74: 0 | J74: 0 | K74: 0 | L74: 0 | M74: 0 | N74: 0 | O74: 0 | P74: 0 | Q74: 0 | R74: 0 | S74: 0 | T74: 0 | U74: 0 | V74: 0 | W74: 0 | X74: 0 | Y74: 0 | Z74: 0 | AA74: 0 | AB74: 0 | AC74: 0
A75: 73 | B75: 03770-2019 | C75: Llamoja — SV de control (2021-2023) | D75: 2024 | E75: 1SC | F75: 0 | G75: 0 | H75: 0 | I75: 0 | J75: 0 | K75: 0 | L75: 1 | M75: 0 | N75: 0 | O75: 0 | P75: 0 | Q75: 0 | R75: 0 | S75: 0 | T75: 0 | U75: 0 | V75: 0 | W75: 0 | X75: 0 | Y75: 0 | Z75: 0 | AA75: 1 | AB75: 0 | AC75: 2
A76: 74 | B76: 03819-2022 | C76: Matriz sumarísimos — grupo 2024 | D76: 2024 | E76: 2SC | F76: 0 | G76: 0 | H76: 0 | I76: 0 | J76: 0 | K76: 0 | L76: 0 | M76: 0 | N76: 0 | O76: 0 | P76: 0 | Q76: 1 | R76: 0 | S76: 0 | T76: 0 | U76: 0 | V76: 0 | W76: 0 | X76: 0 | Y76: 0 | Z76: 0 | AA76: 0 | AB76: 1 | AC76: 2
A77: 75 | B77: 03996-2023 | C77: Llamoja — SV de control (2021-2023) | D77: 2025 | E77: 1SC | F77: 0 | G77: 0 | H77: 0 | I77: 0 | J77: 0 | K77: 1 | L77: 0 | M77: 0 | N77: 1 | O77: 0 | P77: 0 | Q77: 0 | R77: 0 | S77: 0 | T77: 0 | U77: 0 | V77: 0 | W77: 0 | X77: 0 | Y77: 0 | Z77: 0 | AA77: 0 | AB77: 0 | AC77: 2
A78: 76 | B78: 04008-2010 | C78: Pre-2019 | D78: 2019 | E78: 2SC | F78: 0 | G78: 0 | H78: 0 | I78: 0 | J78: 0 | K78: 0 | L78: 0 | M78: 0 | N78: 1 | O78: 1 | P78: 0 | Q78: 0 | R78: 0 | S78: 0 | T78: 0 | U78: 0 | V78: 0 | W78: 0 | X78: 0 | Y78: 0 | Z78: 0 | AA78: 0 | AB78: 0 | AC78: 2
A79: 77 | B79: 04033-2016 | C79: Matriz sumarísimos — anteriores a 2019 | D79: 2018 | E79: 1SC | F79: 0 | G79: 0 | H79: 0 | I79: 0 | J79: 0 | K79: 0 | L79: 0 | M79: 0 | N79: 0 | O79: 0 | P79: 0 | Q79: 0 | R79: 0 | S79: 0 | T79: 0 | U79: 0 | V79: 0 | W79: 0 | X79: 0 | Y79: 0 | Z79: 0 | AA79: 0 | AB79: 0 | AC79: 0
A80: 78 | B80: 04034-2022 | C80: Llamoja — SV de control (2021-2023) | D80: 2025 | E80: 2SC | F80: 0 | G80: 0 | H80: 0 | I80: 0 | J80: 0 | K80: 0 | L80: 0 | M80: 0 | N80: 0 | O80: 0 | P80: 0 | Q80: 0 | R80: 1 | S80: 0 | T80: 0 | U80: 0 | V80: 0 | W80: 0 | X80: 0 | Y80: 0 | Z80: 0 | AA80: 0 | AB80: 0 | AC80: 1
A81: 79 | B81: 04040-2015 | C81: Pre-2019 | D81: 2019 | E81: 2SC | F81: 0 | G81: 0 | H81: 0 | I81: 0 | J81: 0 | K81: 0 | L81: 0 | M81: 0 | N81: 0 | O81: 0 | P81: 0 | Q81: 0 | R81: 1 | S81: 0 | T81: 0 | U81: 0 | V81: 0 | W81: 0 | X81: 0 | Y81: 0 | Z81: 0 | AA81: 0 | AB81: 0 | AC81: 1
A82: 80 | B82: 04049-2015 | C82: Matriz sumarísimos — anteriores a 2019 | D82: 2019 | E82: 2SC | F82: 0 | G82: 0 | H82: 0 | I82: 0 | J82: 0 | K82: 0 | L82: 0 | M82: 0 | N82: 0 | O82: 0 | P82: 0 | Q82: 0 | R82: 0 | S82: 0 | T82: 0 | U82: 0 | V82: 0 | W82: 0 | X82: 0 | Y82: 0 | Z82: 0 | AA82: 0 | AB82: 0 | AC82: 0
A83: 81 | B83: 04109-2011 | C83: Matriz sumarísimos — anteriores a 2019 | D83: 2019 | E83: 2SC | F83: 0 | G83: 0 | H83: 0 | I83: 0 | J83: 0 | K83: 0 | L83: 0 | M83: 0 | N83: 0 | O83: 0 | P83: 0 | Q83: 0 | R83: 0 | S83: 0 | T83: 0 | U83: 0 | V83: 0 | W83: 0 | X83: 0 | Y83: 0 | Z83: 0 | AA83: 0 | AB83: 0 | AC83: 0
A84: 82 | B84: 04126-2021 | C84: 2024 | D84: 2024 | E84: 1SC | F84: 0 | G84: 0 | H84: 0 | I84: 0 | J84: 0 | K84: 0 | L84: 0 | M84: 0 | N84: 0 | O84: 0 | P84: 0 | Q84: 0 | R84: 0 | S84: 0 | T84: 0 | U84: 1 | V84: 0 | W84: 0 | X84: 0 | Y84: 0 | Z84: 0 | AA84: 0 | AB84: 1 | AC84: 2
A85: 83 | B85: 04138-2022 | C85: Matriz sumarísimos — grupo 2024 | D85: 2025 | E85: 2SC | F85: 0 | G85: 0 | H85: 0 | I85: 0 | J85: 0 | K85: 0 | L85: 0 | M85: 0 | N85: 0 | O85: 0 | P85: 0 | Q85: 1 | R85: 0 | S85: 0 | T85: 0 | U85: 0 | V85: 0 | W85: 0 | X85: 0 | Y85: 0 | Z85: 0 | AA85: 0 | AB85: 0 | AC85: 1
A86: 84 | B86: 04154-2022 | C86: Llamoja — SV de control (2021-2023) | D86: 2024 | E86: 2SC | F86: 0 | G86: 0 | H86: 0 | I86: 0 | J86: 0 | K86: 0 | L86: 0 | M86: 0 | N86: 0 | O86: 0 | P86: 0 | Q86: 0 | R86: 1 | S86: 1 | T86: 0 | U86: 0 | V86: 0 | W86: 0 | X86: 0 | Y86: 0 | Z86: 0 | AA86: 0 | AB86: 0 | AC86: 2
... A118: 116 | B118: 06175-2022 | C118: 2024 | D118: 2025 | E118: 2SC | F118: 0 | G118: 0 | H118: 0 | I118: 0 | J118: 0 | K118: 0 | L118: 0 | M118: 0 | N118: 0 | O118: 0 | P118: 0 | Q118: 0 | R118: 0 | S118: 0 | T118: 0 | U118: 0 | V118: 0 | W118: 0 | X118: 0 | Y118: 0 | Z118: 0 | AA118: 0 | AB118: 0 | AC118: 0
A119: 117 | B119: 06374-2019 | C119: 2024 | D119: 2025 | F119: 1 | G119: 0 | H119: 0 | I119: 0 | J119: 0 | K119: 0 | L119: 0 | M119: 0 | N119: 0 | O119: 0 | P119: 0 | Q119: 0 | R119: 0 | S119: 0 | T119: 0 | U119: 0 | V119: 0 | W119: 0 | X119: 0 | Y119: 0 | Z119: 0 | AA119: 0 | AB119: 0 | AC119: 1
A120: 118 | B120: 06385-2023 | C120: Llamoja — SV de control (2021-2023) | D120: 2025 | E120: 2SC | F120: 0 | G120: 0 | H120: 0 | I120: 0 | J120: 0 | K120: 0 | L120: 0 | M120: 0 | N120: 0 | O120: 0 | P120: 0 | Q120: 0 | R120: 0 | S120: 0 | T120: 0 | U120: 1 | V120: 0 | W120: 0 | X120: 0 | Y120: 0 | Z120: 0 | AA120: 0 | AB120: 0 | AC120: 1
A121: 119 | B121: 06402-2022 | C121: 2024 | D121: 2025 | F121: 0 | G121: 0 | H121: 0 | I121: 0 | J121: 0 | K121: 0 | L121: 0 | M121: 0 | N121: 0 | O121: 0 | P121: 1 | Q121: 0 | R121: 0 | S121: 0 | T121: 0 | U121: 0 | V121: 0 | W121: 0 | X121: 0 | Y121: 0 | Z121: 0 | AA121: 0 | AB121: 1 | AC121: 2
A122: 120 | B122: 06607-2021 | C122: 2024 | D122: 2025 | E122: 2SC | F122: 0 | G122: 1 | H122: 0 | I122: 0 | J122: 0 | K122: 0 | L122: 0 | M122: 0 | N122: 0 | O122: 0 | P122: 0 | Q122: 0 | R122: 0 | S122: 0 | T122: 0 | U122: 1 | V122: 0 | W122: 0 | X122: 0 | Y122: 0 | Z122: 0 | AA122: 0 | AB122: 1 | AC122: 3
A123: 121 | B123: 06834-2022 | C123: Llamoja — SV de control (2021-2023) | D123: 2025 | E123: 2SC | F123: 0 | G123: 0 | H123: 0 | I123: 0 | J123: 0 | K123: 0 | L123: 1 | M123: 0 | N123: 0 | O123: 0 | P123: 0 | Q123: 1 | R123: 1 | S123: 0 | T123: 0 | U123: 0 | V123: 0 | W123: 0 | X123: 0 | Y123: 0 | Z123: 0 | AA123: 0 | AB123: 0 | AC123: 3
A124: 122 | B124: 06842-2014 | C124: Pre-2019 | D124: 2018 | E124: 1SC | F124: 0 | G124: 0 | H124: 0 | I124: 0 | J124: 0 | K124: 0 | L124: 0 | M124: 0 | N124: 0 | O124: 0 | P124: 0 | Q124: 0 | R124: 0 | S124: 0 | T124: 0 | U124: 0 | V124: 0 | W124: 0 | X124: 0 | Y124: 0 | Z124: 0 | AA124: 0 | AB124: 0 | AC124: 0
A125: 123 | B125: 06866-2022 | C125: Llamoja — SV de control (2021-2023) | D125: 2025 | E125: 3SC | F125: 0 | G125: 0 | H125: 0 | I125: 0 | J125: 0 | K125: 0 | L125: 0 | M125: 0 | N125: 0 | O125: 0 | P125: 0 | Q125: 0 | R125: 0 | S125: 0 | T125: 0 | U125: 0 | V125: 0 | W125: 0 | X125: 0 | Y125: 0 | Z125: 1 | AA125: 0 | AB125: 0 | AC125: 1
A126: 124 | B126: 06942-2023 | C126: Matriz sumarísimos — grupo 2024 | D126: 2025 | E126: 1SC | F126: 0 | G126: 0 | H126: 0 | I126: 0 | J126: 0 | K126: 0 | L126: 0 | M126: 0 | N126: 0 | O126: 0 | P126: 0 | Q126: 0 | R126: 0 | S126: 0 | T126: 0 | U126: 0 | V126: 0 | W126: 0 | X126: 0 | Y126: 0 | Z126: 0 | AA126: 0 | AB126: 0 | AC126: 0
A127: 125 | B127: 07287-2022 | C127: Llamoja — SV de control (2021-2023) | D127: 2024 | E127: 1SC | F127: 0 | G127: 0 | H127: 0 | I127: 0 | J127: 0 | K127: 0 | L127: 0 | M127: 0 | N127: 0 | O127: 0 | P127: 0 | Q127: 0 | R127: 0 | S127: 0 | T127: 0 | U127: 0 | V127: 0 | W127: 0 | X127: 1 | Y127: 0 | Z127: 0 | AA127: 0 | AB127: 0 | AC127: 1
A128: 126 | B128: 07288-2022 | C128: Matriz sumarísimos — grupo 2024 | D128: 2025 | E128: 3SC | F128: 0 | G128: 0 | H128: 0 | I128: 0 | J128: 0 | K128: 0 | L128: 0 | M128: 0 | N128: 0 | O128: 0 | P128: 0 | Q128: 0 | R128: 0 | S128: 0 | T128: 0 | U128: 0 | V128: 0 | W128: 0 | X128: 0 | Y128: 0 | Z128: 0 | AA128: 0 | AB128: 0 | AC128: 0
A129: 127 | B129: 07296-2022 | C129: Llamoja — SV de control (2021-2023) | D129: 2025 | E129: 3SC | F129: 0 | G129: 0 | H129: 0 | I129: 0 | J129: 0 | K129: 0 | L129: 0 | M129: 0 | N129: 0 | O129: 0 | P129: 0 | Q129: 1 | R129: 1 | S129: 0 | T129: 0 | U129: 0 | V129: 0 | W129: 0 | X129: 0 | Y129: 0 | Z129: 0 | AA129: 0 | AB129: 0 | AC129: 2
A130: 128 | B130: 07480-2014 | C130: Pre-2019 | D130: 2018 | E130: 2SC | F130: 0 | G130: 0 | H130: 0 | I130: 0 | J130: 0 | K130: 0 | L130: 0 | M130: 0 | N130: 0 | O130: 0 | P130: 0 | Q130: 0 | R130: 0 | S130: 0 | T130: 0 | U130: 0 | V130: 0 | W130: 0 | X130: 1 | Y130: 0 | Z130: 0 | AA130: 0 | AB130: 0 | AC130: 1
A131: 129 | B131: 07590-2022 | C131: Matriz sumarísimos — grupo 2024 | D131: 2024 | E131: 1SC | F131: 0 | G131: 0 | H131: 0 | I131: 0 | J131: 0 | K131: 0 | L131: 0 | M131: 0 | N131: 0 | O131: 0 | P131: 0 | Q131: 0 | R131: 0 | S131: 0 | T131: 0 | U131: 0 | V131: 0 | W131: 0 | X131: 0 | Y131: 0 | Z131: 0 | AA131: 0 | AB131: 0 | AC131: 0
A132: 130 | B132: 07595-2022 | C132: Llamoja — SV de control (2021-2023) | D132: 2025 | E132: 2SC | F132: 0 | G132: 0 | H132: 0 | I132: 0 | J132: 0 | K132: 0 | L132: 0 | M132: 0 | N132: 0 | O132: 0 | P132: 0 | Q132: 0 | R132: 0 | S132: 0 | T132: 0 | U132: 0 | V132: 0 | W132: 0 | X132: 0 | Y132: 1 | Z132: 0 | AA132: 0 | AB132: 0 | AC132: 1
A133: 131 | B133: 07606-2013 | C133: Matriz sumarísimos — anteriores a 2019 | D133: 2019 | E133: 2SC | F133: 0 | G133: 0 | H133: 0 | I133: 0 | J133: 0 | K133: 0 | L133: 0 | M133: 0 | N133: 0 | O133: 0 | P133: 0 | Q133: 0 | R133: 0 | S133: 0 | T133: 1 | U133: 1 | V133: 0 | W133: 0 | X133: 0 | Y133: 0 | Z133: 0 | AA133: 0 | AB133: 0 | AC133: 2
... A165: 163 | B165: 00925-2017 | C165: Abreviado — anteriores a 2019 (ABR18_SV) | D165: 2020 | E165: 2SC | F165: 0 | G165: 0 | H165: 0 | I165: 0 | J165: 0 | K165: 0 | L165: 0 | M165: 0 | N165: 0 | O165: 0 | P165: 0 | Q165: 0 | R165: 0 | S165: 0 | T165: 0 | U165: 0 | V165: 0 | W165: 0 | X165: 0 | Y165: 0 | Z165: 0 | AA165: 0 | AB165: 0 | AC165: 0
B166: TOTAL | F166: 8 | G166: 5 | H166: 7 | I166: 3 | J166: 0 | K166: 4 | L166: 5 | M166: 3 | N166: 2 | O166: 2 | P166: 9 | Q166: 25 | R166: 18 | S166: 10 | T166: 10 | U166: 32 | V166: 0 | W166: 2 | X166: 9 | Y166: 2 | Z166: 9 | AA166: 10 | AB166: 21 | AC166: 196

Sheet Marcas_todas
A1: Todos los registros, cualquiera sea su estatus (declarado, derivado, alegado, voto en minoría, advertido). Úsese solo para rastreo, no para frecuencias.
A2: N° | B2: Clave expediente | C2: Corpus / grupo | D2: Año SV | E2: Sala | F2: D01 | G2: D02 | H2: D03 | I2: D04 | J2: D05 | K2: D06 | L2: D07 | M2: D08 | N2: D09 | O2: D10 | P2: D11 | Q2: D12 | R2: D13 | S2: D14 | T2: D15 | U2: D16 | V2: D17 | W2: D18 | X2: D19 | Y2: D20 | Z2: D21 | AA2: D22 | AB2: D23 | AC2: Total
A3: 1 | B3: 00001-2018 | C3: Matriz sumarísimos — anteriores a 2019 | D3: 2019 | E3: 2SC | F3: 0 | G3: 0 | H3: 0 | I3: 0 | J3: 0 | K3: 0 | L3: 0 | M3: 0 | N3: 0 | O3: 0 | P3: 0 | Q3: 1 | R3: 0 | S3: 0 | T3: 1 | U3: 0 | V3: 0 | W3: 0 | X3: 0 | Y3: 0 | Z3: 0 | AA3: 0 | AB3: 0 | AC3: 2
A4: 2 | B4: 00072-2023 | C4: Matriz sumarísimos — grupo 2024 | D4: 2025 | E4: 2SC | F4: 0 | G4: 0 | H4: 0 | I4: 0 | J4: 0 | K4: 0 | L4: 0 | M4: 0 | N4: 0 | O4: 0 | P4: 1 | Q4: 0 | R4: 0 | S4: 0 | T4: 1 | U4: 1 | V4: 0 | W4: 0 | X4: 0 | Y4: 0 | Z4: 1 | AA4: 0 | AB4: 0 | AC4: 4
A5: 3 | B5: 00115-2012 | C5: Matriz sumarísimos — anteriores a 2019 | D5: 2018 | E5: 2SC | F5: 1 | G5: 1 | H5: 0 | I5: 0 | J5: 0 | K5: 0 | L5: 0 | M5: 0 | N5: 0 | O5: 0 | P5: 0 | Q5: 0 | R5: 0 | S5: 0 | T5: 0 | U5: 0 | V5: 0 | W5: 0 | X5: 0 | Y5: 0 | Z5: 0 | AA5: 0 | AB5: 0 | AC5: 2
A6: 4 | B6: 00129-2022 | C6: Matriz sumarísimos — grupo 2024 | D6: 2024 | E6: 2SC | F6: 0 | G6: 0 | H6: 0 | I6: 0 | J6: 0 | K6: 0 | L6: 0 | M6: 0 | N6: 0 | O6: 0 | P6: 0 | Q6: 0 | R6: 0 | S6: 0 | T6: 0 | U6: 0 | V6: 0 | W6: 0 | X6: 0 | Y6: 0 | Z6: 0 | AA6: 0 | AB6: 0 | AC6: 0
A7: 5 | B7: 00132-2015 | C7: Pre-2019 | D7: 2018 | E7: 2SC | F7: 0 | G7: 0 | H7: 0 | I7: 0 | J7: 0 | K7: 0 | L7: 0 | M7: 0 | N7: 0 | O7: 0 | P7: 0 | Q7: 0 | R7: 0 | S7: 0 | T7: 0 | U7: 0 | V7: 0 | W7: 0 | X7: 0 | Y7: 0 | Z7: 0 | AA7: 0 | AB7: 0 | AC7: 0
A8: 6 | B8: 00153-2022 | C8: Matriz sumarísimos — grupo 2024 | D8: 2025 | E8: 3SC | F8: 0 | G8: 0 | H8: 0 | I8: 0 | J8: 0 | K8: 0 | L8: 0 | M8: 0 | N8: 0 | O8: 0 | P8: 0 | Q8: 0 | R8: 0 | S8: 0 | T8: 0 | U8: 0 | V8: 0 | W8: 0 | X8: 0 | Y8: 0 | Z8: 0 | AA8: 0 | AB8: 0 | AC8: 0
A9: 7 | B9: 00192-2021 | C9: 2024 | D9: 2026 | F9: 0 | G9: 0 | H9: 0 | I9: 0 | J9: 0 | K9: 0 | L9: 0 | M9: 0 | N9: 0 | O9: 0 | P9: 0 | Q9: 0 | R9: 0 | S9: 0 | T9: 0 | U9: 0 | V9: 0 | W9: 0 | X9: 0 | Y9: 0 | Z9: 0 | AA9: 0 | AB9: 0 | AC9: 0
A10: 8 | B10: 00234-2018 | C10: Matriz sumarísimos — anteriores a 2019 | D10: 2019 | E10: 3SC | F10: 0 | G10: 0 | H10: 0 | I10: 0 | J10: 0 | K10: 0 | L10: 0 | M10: 0 | N10: 0 | O10: 0 | P10: 0 | Q10: 0 | R10: 0 | S10: 0 | T10: 0 | U10: 0 | V10: 0 | W10: 0 | X10: 1 | Y10: 0 | Z10: 0 | AA10: 0 | AB10: 0 | AC10: 1
A11: 9 | B11: 00320-2023 | C11: 2024 | D11: 2025 | E11: 2SC | F11: 0 | G11: 0 | H11: 0 | I11: 0 | J11: 0 | K11: 0 | L11: 0 | M11: 0 | N11: 0 | O11: 0 | P11: 0 | Q11: 0 | R11: 1 | S11: 0 | T11: 0 | U11: 0 | V11: 0 | W11: 0 | X11: 0 | Y11: 0 | Z11: 0 | AA11: 0 | AB11: 0 | AC11: 1
A12: 10 | B12: 00340-2002 | C12: Pre-2019 | D12: 2018 | E12: 2SC | F12: 0 | G12: 1 | H12: 0 | I12: 0 | J12: 0 | K12: 0 | L12: 0 | M12: 0 | N12: 0 | O12: 0 | P12: 0 | Q12: 0 | R12: 0 | S12: 0 | T12: 0 | U12: 1 | V12: 0 | W12: 0 | X12: 0 | Y12: 0 | Z12: 0 | AA12: 0 | AB12: 0 | AC12: 2
A13: 11 | B13: 00367-2024 | C13: Matriz sumarísimos — grupo 2024 | D13: 2024 | E13: 1SC | F13: 0 | G13: 0 | H13: 0 | I13: 0 | J13: 0 | K13: 0 | L13: 0 | M13: 0 | N13: 0 | O13: 0 | P13: 0 | Q13: 0 | R13: 0 | S13: 0 | T13: 0 | U13: 0 | V13: 0 | W13: 0 | X13: 0 | Y13: 0 | Z13: 0 | AA13: 0 | AB13: 0 | AC13: 0
A14: 12 | B14: 00414-2023 | C14: Llamoja — SV de control (2021-2023) | D14: 2025 | E14: 3SC | F14: 0 | G14: 0 | H14: 0 | I14: 0 | J14: 0 | K14: 0 | L14: 0 | M14: 0 | N14: 0 | O14: 0 | P14: 0 | Q14: 0 | R14: 1 | S14: 0 | T14: 0 | U14: 1 | V14: 0 | W14: 0 | X14: 0 | Y14: 0 | Z14: 0 | AA14: 0 | AB14: 0 | AC14: 2
A15: 13 | B15: 00428-2017 | C15: Matriz sumarísimos — anteriores a 2019 | D15: 2020 | E15: 2SC | F15: 0 | G15: 0 | H15: 0 | I15: 0 | J15: 0 | K15: 0 | L15: 0 | M15: 0 | N15: 0 | O15: 0 | P15: 0 | Q15: 0 | R15: 1 | S15: 0 | T15: 0 | U15: 0 | V15: 0 | W15: 0 | X15: 0 | Y15: 0 | Z15: 1 | AA15: 0 | AB15: 0 | AC15: 2
A16: 14 | B16: 00598-2022 | C16: 2024 | D16: 2025 | E16: 3SC | F16: 0 | G16: 0 | H16: 0 | I16: 0 | J16: 0 | K16: 0 | L16: 0 | M16: 0 | N16: 0 | O16: 0 | P16: 0 | Q16: 1 | R16: 1 | S16: 0 | T16: 0 | U16: 0 | V16: 0 | W16: 0 | X16: 0 | Y16: 0 | Z16: 0 | AA16: 0 | AB16: 0 | AC16: 2
A17: 15 | B17: 00646-2024 | C17: Matriz sumarísimos — grupo 2024 | D17: 2025 | E17: 2SC | F17: 0 | G17: 0 | H17: 0 | I17: 0 | J17: 0 | K17: 0 | L17: 0 | M17: 0 | N17: 0 | O17: 0 | P17: 0 | Q17: 1 | R17: 0 | S17: 0 | T17: 0 | U17: 1 | V17: 0 | W17: 0 | X17: 0 | Y17: 0 | Z17: 0 | AA17: 0 | AB17: 1 | AC17: 3
A18: 16 | B18: 00661-2023 | C18: Matriz sumarísimos — grupo 2024 | D18: 2025 | E18: 2SC | F18: 0 | G18: 0 | H18: 0 | I18: 0 | J18: 0 | K18: 0 | L18: 0 | M18: 0 | N18: 0 | O18: 0 | P18: 0 | Q18: 1 | R18: 1 | S18: 0 | T18: 0 | U18: 0 | V18: 0 | W18: 0 | X18: 0 | Y18: 0 | Z18: 0 | AA18: 0 | AB18: 0 | AC18: 2
A19: 17 | B19: 00742-2022 | C19: 2024 | D19: 2025 | F19: 0 | G19: 1 | H19: 0 | I19: 1 | J19: 0 | K19: 0 | L19: 0 | M19: 0 | N19: 0 | O19: 0 | P19: 1 | Q19: 0 | R19: 0 | S19: 0 | T19: 0 | U19: 1 | V19: 0 | W19: 0 | X19: 0 | Y19: 0 | Z19: 0 | AA19: 0 | AB19: 0 | AC19: 4
A20: 18 | B20: 00748-2013 | C20: Pre-2019 | D20: 2018 | E20: 2SC | F20: 0 | G20: 0 | H20: 0 | I20: 0 | J20: 0 | K20: 0 | L20: 0 | M20: 0 | N20: 0 | O20: 0 | P20: 0 | Q20: 0 | R20: 0 | S20: 0 | T20: 1 | U20: 0 | V20: 0 | W20: 0 | X20: 0 | Y20: 0 | Z20: 0 | AA20: 0 | AB20: 0 | AC20: 1
A21: 19 | B21: 00760-2021 | C21: Llamoja — SV de control (2021-2023) | D21: 2025 | E21: 3SC | F21: 0 | G21: 0 | H21: 0 | I21: 0 | J21: 0 | K21: 0 | L21: 0 | M21: 1 | N21: 0 | O21: 1 | P21: 0 | Q21: 0 | R21: 0 | S21: 0 | T21: 0 | U21: 0 | V21: 0 | W21: 0 | X21: 0 | Y21: 0 | Z21: 0 | AA21: 0 | AB21: 0 | AC21: 2
A22: 20 | B22: 00774-2021 | C22: Llamoja — SV de control (2021-2023) | D22: 2025 | E22: 2SC | F22: 0 | G22: 0 | H22: 0 | I22: 0 | J22: 0 | K22: 0 | L22: 0 | M22: 0 | N22: 0 | O22: 0 | P22: 0 | Q22: 0 | R22: 0 | S22: 0 | T22: 0 | U22: 1 | V22: 0 | W22: 0 | X22: 0 | Y22: 0 | Z22: 1 | AA22: 0 | AB22: 0 | AC22: 2
A23: 21 | B23: 00788-2013 | C23: Pre-2019 | D23: 2021 | E23: 2SC | F23: 0 | G23: 0 | H23: 0 | I23: 0 | J23: 0 | K23: 0 | L23: 0 | M23: 0 | N23: 0 | O23: 0 | P23: 0 | Q23: 0 | R23: 0 | S23: 0 | T23: 0 | U23: 1 | V23: 0 | W23: 0 | X23: 0 | Y23: 0 | Z23: 0 | AA23: 0 | AB23: 0 | AC23: 1
A24: 22 | B24: 00848-2011 | C24: Matriz sumarísimos — anteriores a 2019 | D24: 2019 | E24: 3SC | F24: 0 | G24: 0 | H24: 0 | I24: 0 | J24: 0 | K24: 0 | L24: 0 | M24: 0 | N24: 0 | O24: 0 | P24: 0 | Q24: 1 | R24: 0 | S24: 0 | T24: 0 | U24: 0 | V24: 0 | W24: 0 | X24: 0 | Y24: 0 | Z24: 0 | AA24: 0 | AB24: 0 | AC24: 1
A25: 23 | B25: 00856-2017 | C25: Pre-2019 | D25: 2019 | E25: 1SC | F25: 0 | G25: 0 | H25: 0 | I25: 0 | J25: 0 | K25: 0 | L25: 0 | M25: 0 | N25: 0 | O25: 0 | P25: 0 | Q25: 0 | R25: 0 | S25: 0 | T25: 0 | U25: 1 | V25: 0 | W25: 0 | X25: 0 | Y25: 0 | Z25: 0 | AA25: 0 | AB25: 0 | AC25: 1
A26: 24 | B26: 00879-2022 | C26: Llamoja — SV de control (2021-2023) | D26: 2025 | E26: 1SC | F26: 0 | G26: 0 | H26: 0 | I26: 0 | J26: 0 | K26: 0 | L26: 0 | M26: 0 | N26: 0 | O26: 0 | P26: 0 | Q26: 0 | R26: 0 | S26: 0 | T26: 1 | U26: 1 | V26: 0 | W26: 0 | X26: 0 | Y26: 0 | Z26: 0 | AA26: 0 | AB26: 0 | AC26: 2
A27: 25 | B27: 00898-2013 | C27: Pre-2019 | D27: 2018 | E27: 3SC | F27: 0 | G27: 0 | H27: 0 | I27: 0 | J27: 0 | K27: 0 | L27: 0 | M27: 0 | N27: 0 | O27: 0 | P27: 0 | Q27: 0 | R27: 0 | S27: 0 | T27: 0 | U27: 1 | V27: 0 | W27: 0 | X27: 0 | Y27: 0 | Z27: 0 | AA27: 0 | AB27: 0 | AC27: 1
A28: 26 | B28: 00933-2022 | C28: Llamoja — SV de control (2021-2023) | D28: 2024 | E28: 3SC | F28: 0 | G28: 0 | H28: 0 | I28: 0 | J28: 0 | K28: 0 | L28: 0 | M28: 0 | N28: 0 | O28: 0 | P28: 0 | Q28: 0 | R28: 0 | S28: 1 | T28: 0 | U28: 1 | V28: 0 | W28: 0 | X28: 0 | Y28: 0 | Z28: 0 | AA28: 0 | AB28: 0 | AC28: 2
A29: 27 | B29: 00965-2015 | C29: Pre-2019 | D29: 2019 | E29: 3SC | F29: 0 | G29: 0 | H29: 0 | I29: 0 | J29: 0 | K29: 1 | L29: 0 | M29: 0 | N29: 0 | O29: 0 | P29: 0 | Q29: 0 | R29: 0 | S29: 0 | T29: 0 | U29: 0 | V29: 0 | W29: 0 | X29: 0 | Y29: 0 | Z29: 0 | AA29: 0 | AB29: 1 | AC29: 2
A30: 28 | B30: 00979-2024 | C30: Matriz sumarísimos — grupo 2024 | D30: 2025 | E30: 1SC | F30: 0 | G30: 0 | H30: 0 | I30: 0 | J30: 0 | K30: 0 | L30: 0 | M30: 0 | N30: 0 | O30: 0 | P30: 0 | Q30: 0 | R30: 0 | S30: 0 | T30: 0 | U30: 0 | V30: 0 | W30: 0 | X30: 0 | Y30: 0 | Z30: 0 | AA30: 0 | AB30: 0 | AC30: 0
A31: 29 | B31: 00992-2016 | C31: Pre-2019 | D31: 2019 | E31: 3SC | F31: 0 | G31: 0 | H31: 0 | I31: 0 | J31: 0 | K31: 0 | L31: 0 | M31: 0 | N31: 0 | O31: 0 | P31: 0 | Q31: 0 | R31: 0 | S31: 0 | T31: 0 | U31: 1 | V31: 0 | W31: 0 | X31: 0 | Y31: 0 | Z31: 0 | AA31: 0 | AB31: 1 | AC31: 2
... A40: 38 | B40: 01647-2019 | C40: 2024 | D40: 2026 | E40: 2SC | F40: 0 | G40: 0 | H40: 0 | I40: 0 | J40: 0 | K40: 0 | L40: 0 | M40: 0 | N40: 0 | O40: 0 | P40: 0 | Q40: 1 | R40: 0 | S40: 1 | T40: 0 | U40: 0 | V40: 0 | W40: 0 | X40: 0 | Y40: 0 | Z40: 0 | AA40: 0 | AB40: 0 | AC40: 2
A41: 39 | B41: 01650-2023 | C41: 2024 | D41: 2025 | F41: 0 | G41: 0 | H41: 0 | I41: 0 | J41: 0 | K41: 0 | L41: 0 | M41: 0 | N41: 0 | O41: 0 | P41: 0 | Q41: 0 | R41: 0 | S41: 0 | T41: 0 | U41: 0 | V41: 0 | W41: 0 | X41: 0 | Y41: 0 | Z41: 0 | AA41: 0 | AB41: 0 | AC41: 0
A42: 40 | B42: 01681-2023 | C42: Llamoja — SV de control (2021-2023) | D42: 2025 | E42: 3SC | F42: 0 | G42: 0 | H42: 0 | I42: 0 | J42: 0 | K42: 1 | L42: 0 | M42: 0 | N42: 0 | O42: 0 | P42: 0 | Q42: 0 | R42: 0 | S42: 0 | T42: 1 | U42: 0 | V42: 0 | W42: 0 | X42: 0 | Y42: 0 | Z42: 0 | AA42: 0 | AB42: 0 | AC42: 2
A43: 41 | B43: 01723-2022 | C43: Llamoja — SV de control (2021-2023) | D43: 2025 | E43: 2SC | F43: 0 | G43: 0 | H43: 0 | I43: 0 | J43: 0 | K43: 0 | L43: 0 | M43: 0 | N43: 0 | O43: 0 | P43: 0 | Q43: 0 | R43: 0 | S43: 0 | T43: 0 | U43: 0 | V43: 0 | W43: 0 | X43: 0 | Y43: 0 | Z43: 0 | AA43: 0 | AB43: 0 | AC43: 0
A44: 42 | B44: 01734-2017 | C44: Pre-2019 | D44: 2019 | E44: 2SC | F44: 0 | G44: 0 | H44: 0 | I44: 0 | J44: 0 | K44: 0 | L44: 0 | M44: 0 | N44: 0 | O44: 0 | P44: 0 | Q44: 0 | R44: 0 | S44: 0 | T44: 1 | U44: 0 | V44: 0 | W44: 0 | X44: 0 | Y44: 0 | Z44: 0 | AA44: 0 | AB44: 0 | AC44: 1
A45: 43 | B45: 01835-2024 | C45: 2024 | D45: 2025 | E45: 1SC | F45: 0 | G45: 0 | H45: 0 | I45: 0 | J45: 0 | K45: 0 | L45: 0 | M45: 0 | N45: 0 | O45: 0 | P45: 0 | Q45: 0 | R45: 0 | S45: 0 | T45: 0 | U45: 0 | V45: 0 | W45: 0 | X45: 0 | Y45: 0 | Z45: 0 | AA45: 0 | AB45: 0 | AC45: 0
A46: 44 | B46: 01869-2023 | C46: Llamoja — SV de control (2021-2023) | D46: 2026 | E46: 2SC | F46: 0 | G46: 0 | H46: 0 | I46: 0 | J46: 0 | K46: 0 | L46: 0 | M46: 0 | N46: 0 | O46: 0 | P46: 0 | Q46: 1 | R46: 1 | S46: 0 | T46: 0 | U46: 0 | V46: 0 | W46: 0 | X46: 0 | Y46: 0 | Z46: 1 | AA46: 0 | AB46: 0 | AC46: 3
A47: 45 | B47: 01879-2022 | C47: 2024 | D47: 2025 | E47: 2SC | F47: 0 | G47: 0 | H47: 0 | I47: 0 | J47: 0 | K47: 0 | L47: 0 | M47: 0 | N47: 0 | O47: 0 | P47: 0 | Q47: 0 | R47: 0 | S47: 0 | T47: 0 | U47: 0 | V47: 0 | W47: 0 | X47: 0 | Y47: 0 | Z47: 0 | AA47: 0 | AB47: 1 | AC47: 1
A48: 46 | B48: 01888-2011 | C48: Pre-2019 | D48: 2020 | E48: 2SC | F48: 0 | G48: 0 | H48: 0 | I48: 0 | J48: 0 | K48: 0 | L48: 0 | M48: 0 | N48: 0 | O48: 0 | P48: 0 | Q48: 0 | R48: 0 | S48: 0 | T48: 0 | U48: 0 | V48: 0 | W48: 0 | X48: 1 | Y48: 0 | Z48: 0 | AA48: 0 | AB48: 0 | AC48: 1
A49: 47 | B49: 01946-2016 | C49: Pre-2019 | D49: 2019 | E49: 3SC | F49: 0 | G49: 0 | H49: 0 | I49: 0 | J49: 0 | K49: 0 | L49: 0 | M49: 0 | N49: 0 | O49: 0 | P49: 0 | Q49: 0 | R49: 0 | S49: 0 | T49: 0 | U49: 0 | V49: 0 | W49: 0 | X49: 0 | Y49: 0 | Z49: 0 | AA49: 0 | AB49: 0 | AC49: 0
A50: 48 | B50: 02167-2023 | C50: Matriz sumarísimos — grupo 2024 | D50: 2025 | E50: 2SC | F50: 0 | G50: 0 | H50: 0 | I50: 0 | J50: 0 | K50: 1 | L50: 0 | M50: 0 | N50: 1 | O50: 0 | P50: 0 | Q50: 0 | R50: 0 | S50: 0 | T50: 0 | U50: 0 | V50: 0 | W50: 0 | X50: 0 | Y50: 0 | Z50: 0 | AA50: 0 | AB50: 1 | AC50: 3
A51: 49 | B51: 02275-2023 | C51: Llamoja — SV de control (2021-2023) | D51: 2025 | E51: 3SC | F51: 1 | G51: 0 | H51: 0 | I51: 1 | J51: 0 | K51: 0 | L51: 0 | M51: 0 | N51: 0 | O51: 0 | P51: 0 | Q51: 0 | R51: 0 | S51: 0 | T51: 0 | U51: 0 | V51: 0 | W51: 0 | X51: 0 | Y51: 0 | Z51: 0 | AA51: 0 | AB51: 0 | AC51: 2
A52: 50 | B52: 02371-2021 | C52: 2024 | D52: 2025 | F52: 0 | G52: 0 | H52: 0 | I52: 0 | J52: 0 | K52: 0 | L52: 0 | M52: 0 | N52: 0 | O52: 0 | P52: 0 | Q52: 0 | R52: 0 | S52: 0 | T52: 0 | U52: 0 | V52: 0 | W52: 0 | X52: 0 | Y52: 0 | Z52: 0 | AA52: 0 | AB52: 0 | AC52: 0
A53: 51 | B53: 02483-2021 | C53: Llamoja — SV de control (2021-2023) | D53: 2023 | E53: 2SC | F53: 0 | G53: 0 | H53: 1 | I53: 0 | J53: 0 | K53: 0 | L53: 0 | M53: 0 | N53: 0 | O53: 0 | P53: 0 | Q53: 0 | R53: 0 | S53: 0 | T53: 0 | U53: 0 | V53: 0 | W53: 0 | X53: 0 | Y53: 0 | Z53: 0 | AA53: 0 | AB53: 0 | AC53: 1
A54: 52 | B54: 02505-2009 | C54: Pre-2019 | D54: 2019 | E54: 3SC | F54: 0 | G54: 1 | H54: 0 | I54: 0 | J54: 0 | K54: 0 | L54: 0 | M54: 0 | N54: 0 | O54: 0 | P54: 0 | Q54: 0 | R54: 0 | S54: 0 | T54: 0 | U54: 1 | V54: 0 | W54: 0 | X54: 0 | Y54: 0 | Z54: 0 | AA54: 0 | AB54: 0 | AC54: 2
A55: 53 | B55: 02532-2017 | C55: Matriz sumarísimos — anteriores a 2019 | D55: 2018 | E55: 1SC | F55: 1 | G55: 1 | H55: 1 | I55: 0 | J55: 0 | K55: 0 | L55: 0 | M55: 0 | N55: 0 | O55: 0 | P55: 0 | Q55: 0 | R55: 0 | S55: 0 | T55: 0 | U55: 0 | V55: 0 | W55: 0 | X55: 0 | Y55: 0 | Z55: 0 | AA55: 0 | AB55: 0 | AC55: 3
A56: 54 | B56: 02635-2019 | C56: 2024 | D56: 2023 | F56: 0 | G56: 0 | H56: 0 | I56: 0 | J56: 0 | K56: 0 | L56: 0 | M56: 0 | N56: 0 | O56: 0 | P56: 1 | Q56: 0 | R56: 0 | S56: 1 | T56: 0 | U56: 0 | V56: 0 | W56: 0 | X56: 0 | Y56: 0 | Z56: 0 | AA56: 0 | AB56: 0 | AC56: 2
A57: 55 | B57: 02641-2010 | C57: Pre-2019 | D57: 2018 | E57: 1SC | F57: 0 | G57: 0 | H57: 0 | I57: 0 | J57: 0 | K57: 0 | L57: 1 | M57: 0 | N57: 0 | O57: 0 | P57: 0 | Q57: 0 | R57: 0 | S57: 0 | T57: 0 | U57: 0 | V57: 0 | W57: 0 | X57: 0 | Y57: 0 | Z57: 0 | AA57: 0 | AB57: 0 | AC57: 1
A58: 56 | B58: 02706-2015 | C58: Pre-2019 | D58: 2019 | E58: 2SC | F58: 0 | G58: 0 | H58: 1 | I58: 0 | J58: 0 | K58: 0 | L58: 0 | M58: 0 | N58: 0 | O58: 0 | P58: 0 | Q58: 0 | R58: 0 | S58: 0 | T58: 0 | U58: 0 | V58: 0 | W58: 0 | X58: 0 | Y58: 0 | Z58: 0 | AA58: 0 | AB58: 0 | AC58: 1
A59: 57 | B59: 02706-2016 | C59: Matriz sumarísimos — anteriores a 2019 | D59: 2021 | E59: 2SC | F59: 0 | G59: 0 | H59: 0 | I59: 0 | J59: 0 | K59: 1 | L59: 0 | M59: 1 | N59: 0 | O59: 0 | P59: 0 | Q59: 0 | R59: 0 | S59: 0 | T59: 0 | U59: 0 | V59: 0 | W59: 0 | X59: 0 | Y59: 0 | Z59: 0 | AA59: 0 | AB59: 0 | AC59: 2
A60: 58 | B60: 02712-2023 | C60: Llamoja — SV de control (2021-2023) | D60: 2025 | E60: 2SC | F60: 0 | G60: 0 | H60: 0 | I60: 0 | J60: 0 | K60: 0 | L60: 0 | M60: 0 | N60: 0 | O60: 0 | P60: 0 | Q60: 0 | R60: 0 | S60: 0 | T60: 0 | U60: 0 | V60: 0 | W60: 0 | X60: 0 | Y60: 0 | Z60: 0 | AA60: 0 | AB60: 0 | AC60: 0
A61: 59 | B61: 02718-2015 | C61: Matriz sumarísimos — anteriores a 2019 | D61: 2018 | E61: 1SC | F61: 0 | G61: 0 | H61: 0 | I61: 0 | J61: 0 | K61: 0 | L61: 1 | M61: 0 | N61: 0 | O61: 0 | P61: 0 | Q61: 0 | R61: 0 | S61: 0 | T61: 0 | U61: 1 | V61: 0 | W61: 0 | X61: 0 | Y61: 0 | Z61: 0 | AA61: 0 | AB61: 1 | AC61: 3
A62: 60 | B62: 02723-2023 | C62: Llamoja — SV de control (2021-2023) | D62: 2025 | E62: 2SC | F62: 0 | G62: 0 | H62: 0 | I62: 0 | J62: 0 | K62: 0 | L62: 0 | M62: 0 | N62: 0 | O62: 0 | P62: 0 | Q62: 0 | R62: 0 | S62: 0 | T62: 0 | U62: 0 | V62: 0 | W62: 0 | X62: 0 | Y62: 0 | Z62: 0 | AA62: 0 | AB62: 0 | AC62: 0
A63: 61 | B63: 02792-2023 | C63: Llamoja — SV de control (2021-2023) | D63: 2025 | E63: 1SC | F63: 0 | G63: 0 | H63: 0 | I63: 0 | J63: 0 | K63: 0 | L63: 0 | M63: 0 | N63: 0 | O63: 0 | P63: 0 | Q63: 0 | R63: 0 | S63: 1 | T63: 1 | U63: 0 | V63: 0 | W63: 0 | X63: 0 | Y63: 0 | Z63: 0 | AA63: 0 | AB63: 0 | AC63: 2
A64: 62 | B64: 02814-2015 | C64: Pre-2019 | D64: 2019 | E64: 3SC | F64: 0 | G64: 0 | H64: 0 | I64: 0 | J64: 0 | K64: 0 | L64: 0 | M64: 0 | N64: 0 | O64: 0 | P64: 0 | Q64: 0 | R64: 0 | S64: 1 | T64: 0 | U64: 0 | V64: 0 | W64: 0 | X64: 0 | Y64: 0 | Z64: 0 | AA64: 0 | AB64: 0 | AC64: 1
A65: 63 | B65: 02851-2023 | C65: Llamoja — SV de control (2021-2023) | D65: 2025 | E65: 1SC | F65: 0 | G65: 0 | H65: 0 | I65: 0 | J65: 0 | K65: 0 | L65: 0 | M65: 0 | N65: 0 | O65: 0 | P65: 0 | Q65: 0 | R65: 0 | S65: 0 | T65: 0 | U65: 0 | V65: 0 | W65: 0 | X65: 1 | Y65: 0 | Z65: 0 | AA65: 1 | AB65: 0 | AC65: 2
A66: 64 | B66: 02943-2016 | C66: Pre-2019 | D66: 2018 | E66: 2SC | F66: 0 | G66: 0 | H66: 0 | I66: 0 | J66: 0 | K66: 0 | L66: 0 | M66: 0 | N66: 0 | O66: 0 | P66: 0 | Q66: 0 | R66: 0 | S66: 0 | T66: 0 | U66: 1 | V66: 0 | W66: 0 | X66: 0 | Y66: 0 | Z66: 0 | AA66: 0 | AB66: 1 | AC66: 2
A67: 65 | B67: 02973-2022 | C67: Llamoja — SV de control (2021-2023) | D67: 2025 | E67: 2SC | F67: 0 | G67: 0 | H67: 0 | I67: 0 | J67: 0 | K67: 0 | L67: 0 | M67: 0 | N67: 0 | O67: 0 | P67: 0 | Q67: 0 | R67: 0 | S67: 0 | T67: 0 | U67: 0 | V67: 0 | W67: 0 | X67: 0 | Y67: 0 | Z67: 1 | AA67: 0 | AB67: 0 | AC67: 1
A68: 66 | B68: 03228-2013 | C68: Pre-2019 | D68: 2018 | E68: 2SC | F68: 0 | G68: 0 | H68: 0 | I68: 0 | J68: 0 | K68: 0 | L68: 0 | M68: 0 | N68: 0 | O68: 0 | P68: 0 | Q68: 1 | R68: 0 | S68: 1 | T68: 0 | U68: 1 | V68: 0 | W68: 0 | X68: 0 | Y68: 0 | Z68: 0 | AA68: 0 | AB68: 0 | AC68: 3
... A73: 71 | B73: 03731-2015 | C73: Matriz sumarísimos — anteriores a 2019 | D73: 2018 | E73: 1SC | F73: 0 | G73: 0 | H73: 0 | I73: 0 | J73: 0 | K73: 0 | L73: 0 | M73: 0 | N73: 0 | O73: 0 | P73: 0 | Q73: 0 | R73: 0 | S73: 0 | T73: 0 | U73: 0 | V73: 0 | W73: 0 | X73: 0 | Y73: 0 | Z73: 0 | AA73: 1 | AB73: 0 | AC73: 1
A74: 72 | B74: 03754-2015 | C74: Matriz sumarísimos — anteriores a 2019 | F74: 0 | G74: 0 | H74: 0 | I74: 0 | J74: 0 | K74: 0 | L74: 0 | M74: 0 | N74: 0 | O74: 0 | P74: 0 | Q74: 0 | R74: 0 | S74: 0 | T74: 0 | U74: 0 | V74: 0 | W74: 0 | X74: 0 | Y74: 0 | Z74: 0 | AA74: 0 | AB74: 0 | AC74: 0
A75: 73 | B75: 03770-2019 | C75: Llamoja — SV de control (2021-2023) | D75: 2024 | E75: 1SC | F75: 0 | G75: 0 | H75: 0 | I75: 0 | J75: 0 | K75: 0 | L75: 1 | M75: 0 | N75: 0 | O75: 0 | P75: 0 | Q75: 0 | R75: 0 | S75: 0 | T75: 0 | U75: 0 | V75: 0 | W75: 0 | X75: 0 | Y75: 0 | Z75: 0 | AA75: 1 | AB75: 0 | AC75: 2
A76: 74 | B76: 03819-2022 | C76: Matriz sumarísimos — grupo 2024 | D76: 2024 | E76: 2SC | F76: 0 | G76: 0 | H76: 0 | I76: 0 | J76: 0 | K76: 0 | L76: 0 | M76: 0 | N76: 0 | O76: 0 | P76: 0 | Q76: 1 | R76: 0 | S76: 0 | T76: 0 | U76: 0 | V76: 0 | W76: 0 | X76: 0 | Y76: 0 | Z76: 0 | AA76: 0 | AB76: 1 | AC76: 2
A77: 75 | B77: 03996-2023 | C77: Llamoja — SV de control (2021-2023) | D77: 2025 | E77: 1SC | F77: 0 | G77: 0 | H77: 0 | I77: 0 | J77: 0 | K77: 1 | L77: 0 | M77: 0 | N77: 1 | O77: 0 | P77: 0 | Q77: 0 | R77: 0 | S77: 0 | T77: 0 | U77: 0 | V77: 0 | W77: 0 | X77: 0 | Y77: 0 | Z77: 0 | AA77: 0 | AB77: 0 | AC77: 2
A78: 76 | B78: 04008-2010 | C78: Pre-2019 | D78: 2019 | E78: 2SC | F78: 0 | G78: 0 | H78: 0 | I78: 0 | J78: 0 | K78: 0 | L78: 0 | M78: 0 | N78: 1 | O78: 1 | P78: 0 | Q78: 0 | R78: 0 | S78: 0 | T78: 0 | U78: 0 | V78: 0 | W78: 0 | X78: 0 | Y78: 0 | Z78: 0 | AA78: 0 | AB78: 0 | AC78: 2
A79: 77 | B79: 04033-2016 | C79: Matriz sumarísimos — anteriores a 2019 | D79: 2018 | E79: 1SC | F79: 0 | G79: 0 | H79: 0 | I79: 0 | J79: 0 | K79: 0 | L79: 0 | M79: 0 | N79: 0 | O79: 0 | P79: 0 | Q79: 0 | R79: 0 | S79: 1 | T79: 0 | U79: 0 | V79: 0 | W79: 0 | X79: 0 | Y79: 0 | Z79: 0 | AA79: 0 | AB79: 0 | AC79: 1
A80: 78 | B80: 04034-2022 | C80: Llamoja — SV de control (2021-2023) | D80: 2025 | E80: 2SC | F80: 0 | G80: 0 | H80: 0 | I80: 0 | J80: 0 | K80: 0 | L80: 0 | M80: 0 | N80: 0 | O80: 0 | P80: 0 | Q80: 0 | R80: 1 | S80: 0 | T80: 0 | U80: 0 | V80: 0 | W80: 0 | X80: 0 | Y80: 0 | Z80: 0 | AA80: 0 | AB80: 0 | AC80: 1
A81: 79 | B81: 04040-2015 | C81: Pre-2019 | D81: 2019 | E81: 2SC | F81: 0 | G81: 0 | H81: 0 | I81: 0 | J81: 0 | K81: 0 | L81: 0 | M81: 0 | N81: 0 | O81: 0 | P81: 0 | Q81: 0 | R81: 1 | S81: 0 | T81: 0 | U81: 0 | V81: 0 | W81: 0 | X81: 0 | Y81: 0 | Z81: 0 | AA81: 0 | AB81: 0 | AC81: 1
A82: 80 | B82: 04049-2015 | C82: Matriz sumarísimos — anteriores a 2019 | D82: 2019 | E82: 2SC | F82: 0 | G82: 0 | H82: 0 | I82: 0 | J82: 0 | K82: 0 | L82: 0 | M82: 0 | N82: 0 | O82: 0 | P82: 0 | Q82: 1 | R82: 0 | S82: 0 | T82: 0 | U82: 0 | V82: 0 | W82: 0 | X82: 0 | Y82: 0 | Z82: 0 | AA82: 0 | AB82: 0 | AC82: 1
A83: 81 | B83: 04109-2011 | C83: Matriz sumarísimos — anteriores a 2019 | D83: 2019 | E83: 2SC | F83: 0 | G83: 1 | H83: 0 | I83: 0 | J83: 0 | K83: 0 | L83: 0 | M83: 0 | N83: 0 | O83: 0 | P83: 0 | Q83: 0 | R83: 1 | S83: 0 | T83: 0 | U83: 0 | V83: 0 | W83: 0 | X83: 0 | Y83: 0 | Z83: 0 | AA83: 0 | AB83: 0 | AC83: 2
A84: 82 | B84: 04126-2021 | C84: 2024 | D84: 2024 | E84: 1SC | F84: 0 | G84: 0 | H84: 0 | I84: 0 | J84: 0 | K84: 0 | L84: 0 | M84: 0 | N84: 0 | O84: 0 | P84: 0 | Q84: 0 | R84: 0 | S84: 0 | T84: 0 | U84: 1 | V84: 0 | W84: 0 | X84: 0 | Y84: 0 | Z84: 0 | AA84: 0 | AB84: 1 | AC84: 2
A85: 83 | B85: 04138-2022 | C85: Matriz sumarísimos — grupo 2024 | D85: 2025 | E85: 2SC | F85: 0 | G85: 0 | H85: 0 | I85: 0 | J85: 0 | K85: 0 | L85: 0 | M85: 0 | N85: 0 | O85: 0 | P85: 0 | Q85: 1 | R85: 0 | S85: 0 | T85: 0 | U85: 0 | V85: 0 | W85: 0 | X85: 0 | Y85: 0 | Z85: 0 | AA85: 0 | AB85: 0 | AC85: 1
A86: 84 | B86: 04154-2022 | C86: Llamoja — SV de control (2021-2023) | D86: 2024 | E86: 2SC | F86: 0 | G86: 0 | H86: 0 | I86: 0 | J86: 0 | K86: 0 | L86: 0 | M86: 0 | N86: 0 | O86: 0 | P86: 0 | Q86: 0 | R86: 1 | S86: 1 | T86: 0 | U86: 0 | V86: 0 | W86: 0 | X86: 0 | Y86: 0 | Z86: 0 | AA86: 0 | AB86: 0 | AC86: 2
... A118: 116 | B118: 06175-2022 | C118: 2024 | D118: 2025 | E118: 2SC | F118: 0 | G118: 0 | H118: 0 | I118: 0 | J118: 0 | K118: 0 | L118: 0 | M118: 0 | N118: 0 | O118: 0 | P118: 0 | Q118: 0 | R118: 0 | S118: 0 | T118: 0 | U118: 0 | V118: 0 | W118: 0 | X118: 0 | Y118: 0 | Z118: 0 | AA118: 0 | AB118: 0 | AC118: 0
A119: 117 | B119: 06374-2019 | C119: 2024 | D119: 2025 | F119: 1 | G119: 1 | H119: 0 | I119: 0 | J119: 0 | K119: 0 | L119: 0 | M119: 0 | N119: 0 | O119: 0 | P119: 0 | Q119: 0 | R119: 0 | S119: 0 | T119: 0 | U119: 0 | V119: 0 | W119: 0 | X119: 0 | Y119: 0 | Z119: 0 | AA119: 0 | AB119: 0 | AC119: 2
A120: 118 | B120: 06385-2023 | C120: Llamoja — SV de control (2021-2023) | D120: 2025 | E120: 2SC | F120: 0 | G120: 0 | H120: 0 | I120: 0 | J120: 0 | K120: 0 | L120: 0 | M120: 0 | N120: 0 | O120: 0 | P120: 0 | Q120: 0 | R120: 0 | S120: 0 | T120: 0 | U120: 1 | V120: 0 | W120: 0 | X120: 0 | Y120: 0 | Z120: 0 | AA120: 0 | AB120: 0 | AC120: 1
A121: 119 | B121: 06402-2022 | C121: 2024 | D121: 2025 | F121: 0 | G121: 0 | H121: 0 | I121: 0 | J121: 0 | K121: 0 | L121: 0 | M121: 0 | N121: 0 | O121: 0 | P121: 1 | Q121: 0 | R121: 0 | S121: 0 | T121: 0 | U121: 0 | V121: 0 | W121: 0 | X121: 0 | Y121: 0 | Z121: 0 | AA121: 0 | AB121: 1 | AC121: 2
A122: 120 | B122: 06607-2021 | C122: 2024 | D122: 2025 | E122: 2SC | F122: 0 | G122: 1 | H122: 0 | I122: 0 | J122: 0 | K122: 0 | L122: 0 | M122: 0 | N122: 0 | O122: 0 | P122: 0 | Q122: 0 | R122: 0 | S122: 0 | T122: 0 | U122: 1 | V122: 0 | W122: 0 | X122: 0 | Y122: 0 | Z122: 0 | AA122: 0 | AB122: 1 | AC122: 3
A123: 121 | B123: 06834-2022 | C123: Llamoja — SV de control (2021-2023) | D123: 2025 | E123: 2SC | F123: 0 | G123: 0 | H123: 0 | I123: 0 | J123: 0 | K123: 0 | L123: 1 | M123: 0 | N123: 0 | O123: 0 | P123: 0 | Q123: 1 | R123: 1 | S123: 0 | T123: 0 | U123: 0 | V123: 0 | W123: 0 | X123: 0 | Y123: 0 | Z123: 0 | AA123: 0 | AB123: 0 | AC123: 3
A124: 122 | B124: 06842-2014 | C124: Pre-2019 | D124: 2018 | E124: 1SC | F124: 0 | G124: 0 | H124: 0 | I124: 0 | J124: 0 | K124: 0 | L124: 0 | M124: 0 | N124: 0 | O124: 0 | P124: 0 | Q124: 0 | R124: 0 | S124: 0 | T124: 0 | U124: 0 | V124: 0 | W124: 0 | X124: 0 | Y124: 0 | Z124: 0 | AA124: 0 | AB124: 0 | AC124: 0
A125: 123 | B125: 06866-2022 | C125: Llamoja — SV de control (2021-2023) | D125: 2025 | E125: 3SC | F125: 0 | G125: 0 | H125: 0 | I125: 0 | J125: 0 | K125: 0 | L125: 0 | M125: 0 | N125: 0 | O125: 0 | P125: 0 | Q125: 0 | R125: 0 | S125: 0 | T125: 0 | U125: 1 | V125: 0 | W125: 0 | X125: 0 | Y125: 0 | Z125: 1 | AA125: 0 | AB125: 0 | AC125: 2
A126: 124 | B126: 06942-2023 | C126: Matriz sumarísimos — grupo 2024 | D126: 2025 | E126: 1SC | F126: 1 | G126: 0 | H126: 0 | I126: 1 | J126: 0 | K126: 0 | L126: 0 | M126: 0 | N126: 0 | O126: 0 | P126: 0 | Q126: 0 | R126: 0 | S126: 0 | T126: 0 | U126: 0 | V126: 0 | W126: 0 | X126: 0 | Y126: 0 | Z126: 0 | AA126: 0 | AB126: 0 | AC126: 2
A127: 125 | B127: 07287-2022 | C127: Llamoja — SV de control (2021-2023) | D127: 2024 | E127: 1SC | F127: 0 | G127: 0 | H127: 0 | I127: 0 | J127: 0 | K127: 0 | L127: 0 | M127: 0 | N127: 0 | O127: 0 | P127: 0 | Q127: 0 | R127: 0 | S127: 0 | T127: 0 | U127: 1 | V127: 0 | W127: 0 | X127: 1 | Y127: 0 | Z127: 0 | AA127: 0 | AB127: 0 | AC127: 2
A128: 126 | B128: 07288-2022 | C128: Matriz sumarísimos — grupo 2024 | D128: 2025 | E128: 3SC | F128: 0 | G128: 0 | H128: 0 | I128: 0 | J128: 0 | K128: 0 | L128: 0 | M128: 0 | N128: 0 | O128: 0 | P128: 0 | Q128: 0 | R128: 1 | S128: 0 | T128: 0 | U128: 0 | V128: 0 | W128: 0 | X128: 0 | Y128: 0 | Z128: 0 | AA128: 0 | AB128: 0 | AC128: 1
A129: 127 | B129: 07296-2022 | C129: Llamoja — SV de control (2021-2023) | D129: 2025 | E129: 3SC | F129: 0 | G129: 0 | H129: 0 | I129: 0 | J129: 0 | K129: 0 | L129: 0 | M129: 0 | N129: 0 | O129: 0 | P129: 0 | Q129: 1 | R129: 1 | S129: 0 | T129: 0 | U129: 0 | V129: 0 | W129: 0 | X129: 0 | Y129: 0 | Z129: 0 | AA129: 0 | AB129: 0 | AC129: 2
A130: 128 | B130: 07480-2014 | C130: Pre-2019 | D130: 2018 | E130: 2SC | F130: 0 | G130: 1 | H130: 0 | I130: 0 | J130: 0 | K130: 0 | L130: 0 | M130: 0 | N130: 0 | O130: 0 | P130: 0 | Q130: 0 | R130: 0 | S130: 0 | T130: 0 | U130: 0 | V130: 0 | W130: 0 | X130: 1 | Y130: 0 | Z130: 0 | AA130: 0 | AB130: 0 | AC130: 2
A131: 129 | B131: 07590-2022 | C131: Matriz sumarísimos — grupo 2024 | D131: 2024 | E131: 1SC | F131: 0 | G131: 0 | H131: 0 | I131: 0 | J131: 0 | K131: 1 | L131: 0 | M131: 0 | N131: 0 | O131: 0 | P131: 1 | Q131: 0 | R131: 0 | S131: 0 | T131: 0 | U131: 0 | V131: 0 | W131: 0 | X131: 0 | Y131: 0 | Z131: 0 | AA131: 0 | AB131: 0 | AC131: 2
A132: 130 | B132: 07595-2022 | C132: Llamoja — SV de control (2021-2023) | D132: 2025 | E132: 2SC | F132: 0 | G132: 0 | H132: 0 | I132: 0 | J132: 0 | K132: 0 | L132: 0 | M132: 0 | N132: 0 | O132: 0 | P132: 0 | Q132: 0 | R132: 0 | S132: 0 | T132: 0 | U132: 0 | V132: 0 | W132: 0 | X132: 0 | Y132: 1 | Z132: 0 | AA132: 0 | AB132: 0 | AC132: 1
A133: 131 | B133: 07606-2013 | C133: Matriz sumarísimos — anteriores a 2019 | D133: 2019 | E133: 2SC | F133: 0 | G133: 0 | H133: 0 | I133: 0 | J133: 0 | K133: 0 | L133: 0 | M133: 0 | N133: 0 | O133: 0 | P133: 0 | Q133: 0 | R133: 0 | S133: 0 | T133: 1 | U133: 1 | V133: 0 | W133: 0 | X133: 0 | Y133: 0 | Z133: 0 | AA133: 0 | AB133: 0 | AC133: 2
... A165: 163 | B165: 00925-2017 | C165: Abreviado — anteriores a 2019 (ABR18_SV) | D165: 2020 | E165: 2SC | F165: 0 | G165: 0 | H165: 0 | I165: 0 | J165: 0 | K165: 0 | L165: 0 | M165: 0 | N165: 0 | O165: 0 | P165: 0 | Q165: 0 | R165: 0 | S165: 0 | T165: 0 | U165: 0 | V165: 0 | W165: 0 | X165: 0 | Y165: 0 | Z165: 0 | AA165: 0 | AB165: 0 | AC165: 0
B166: TOTAL | F166: 9 | G166: 16 | H166: 8 | I166: 4 | J166: 0 | K166: 9 | L166: 5 | M166: 4 | N166: 3 | O166: 2 | P166: 11 | Q166: 28 | R166: 23 | S166: 12 | T166: 11 | U166: 37 | V166: 0 | W166: 2 | X166: 10 | Y166: 2 | Z166: 10 | AA166: 10 | AB166: 22 | AC166: 238

Sheet Resumen_comparado
A1: FRECUENCIA DE DEFECTOS: REGISTRO ORIGINAL FRENTE A REGISTRO CORREGIDO
A2: Corpus: 134 expedientes · Sentencias de vista, Salas Civiles CSJA.
A4: Cód. | B4: Causal | C4: Original | D4: Original sin la fila fantasma | E4: Corregido: declarados | F4: Corregido: todos los estatus | G4: Variación (declarados − original) | H4: Comentario
A5: D01 | B5: Notificación o emplazamiento defectuoso | C5: 11 | D5: 10 | E5: 7 | F5: 8 | G5: -4 | H5: De 11 a 7 declarados. Se retira 04370-2022 (era litisconsorcio), 04414-2023 pasa a D22 y 06942-2023 queda como alegado.
A6: D02 | B6: Vulneración del derecho de defensa | C6: 19 | D6: 18 | E6: 5 | F6: 15 | G6: -14 | H6: De 19 a 5 declarados. Diez registros pasan a estatus DERIVADO: son la indefensión consecuencia de otro defecto ya codificado en la misma fila.
A7: D03 | B7: Litisconsorte necesario omitido | C7: 7 | D7: 6 | E7: 5 | F7: 5 | G7: -2 | H7: De 7 a 5. Se retiran el duplicado de 02706-2015 (idéntico a D02) y los sujetos que no eran litisconsortes necesarios.
A8: D04 | B8: Declaración indebida de rebeldía | C8: 5 | D8: 4 | E8: 3 | F8: 4 | G8: -2 | H8: De 5 a 3 declarados. Quedan los casos genuinos (02275-2023, 00742-2022 y 01286-2022, este con cita por verificar); 06942-2023 pasa a alegado.
A9: D05 | B9: Omisión o irregularidad de audiencia | C9: 2 | D9: 1 | E9: 0 | F9: 0 | G9: -2 | H9: Queda en cero: el único registro solapaba íntegramente con D07 (la audiencia sí se celebró; lo omitido fue actuar la prueba).
A10: D06 | B10: Deficiente fijación de puntos/hechos controvertidos | C10: 17 | D10: 16 | E10: 3 | F10: 8 | G10: -14 | H10: De 17 a 3 declarados, la caída proporcionalmente mayor: once registros describían sentencias que resuelven fuera de los puntos fijados o que omiten pronunciarse sobre ellos, no autos de fijación deficientes.
A11: D07 | B11: Prueba admitida y no actuada | C11: 5 | D11: 4 | E11: 4 | F11: 4 | G11: -1 | H11: Categoría estable y de las mejor sustentadas del corpus: cuatro de sus cinco registros se conservan sin cambio.
A12: D08 | B12: Indebida admisión o exclusión de prueba | C12: 11 | D12: 10 | E12: 2 | F12: 3 | G12: -9 | H12: De 11 a 2. Los demás eran incidencias previas (D19) o pasajes en que la Sala convalida la actuación del A quo.
A13: D09 | B13: Prueba de oficio irregular | C13: 7 | D13: 6 | E13: 2 | F13: 3 | G13: -5 | H13: De 7 a 2. Se retiran la confusión con la nulidad de oficio del acto jurídico (art. V TP CC) y los pasajes que no censuran irregularidad alguna.
A14: D10 | B14: Falta de contradictorio de la prueba | C14: 6 | D14: 5 | E14: 2 | F14: 2 | G14: -4 | H14: De 6 a 2. Queda restringido al contradictorio sobre PRUEBA; el contradictorio sobre causales jurídicas pasa a D02 y D16.
A15: D11 | B15: Omisión de valoración de prueba decisiva | C15: 22 | D15: 21 | E15: 7 | F15: 9 | G15: -15 | H15: De 22 a 7, la caída más fuerte junto con D15 y D20: «no valoró debidamente» y «no valoró en conjunto» son D12, no omisión de valoración.
A16: D12 | B16: Valoración probatoria defectuosa | C16: 16 | D16: 15 | E16: 16 | F16: 19 | G16: 0 | H16: Se mantiene en 16 declarados, pero con otra composición: recibe ocho registros desde D11 y cede los que no recaían sobre prueba. Es hoy la categoría mejor sustentada.
... A27: D23 | B27: Motivación defectuosa sin especificación del supuesto | C27: 0 | D27: 0 | E27: 19 | F27: 20 | G27: +19 | H27: Código nuevo, 19 registros declarados: motivación defectuosa sin especificación del supuesto. Recoge las fórmulas genéricas que inflaban D15.
A28: TOTAL | C28: 265 | D28: 245 | E28: 154 | F28: 194 | G28: -111
A31: DESGLOSE DE LOS REGISTROS CORREGIDOS POR ESTATUS
A32: Cód. | B32: Causal | C32: Declarado por la Sala | D32: Consecuencia derivada | E32: Alegado, no acogido | F32: Voto en minoría / discordia / singular | G32: Advertido sin nulidad | H32: Total
A33: D01 | B33: Notificación o emplazamiento defectuoso | C33: 7 | D33: 0 | E33: 1 | F33: 0 | G33: 0 | H33: 8
A34: D02 | B34: Vulneración del derecho de defensa | C34: 5 | D34: 9 | E34: 1 | F34: 0 | G34: 0 | H34: 15
A35: D03 | B35: Litisconsorte necesario omitido | C35: 5 | D35: 0 | E35: 0 | F35: 0 | G35: 0 | H35: 5
A36: D04 | B36: Declaración indebida de rebeldía | C36: 3 | D36: 0 | E36: 1 | F36: 0 | G36: 0 | H36: 4
A37: D05 | B37: Omisión o irregularidad de audiencia | C37: 0 | D37: 0 | E37: 0 | F37: 0 | G37: 0 | H37: 0
A38: D06 | B38: Deficiente fijación de puntos/hechos controvertidos | C38: 3 | D38: 0 | E38: 1 | F38: 2 | G38: 2 | H38: 8
A39: D07 | B39: Prueba admitida y no actuada | C39: 4 | D39: 0 | E39: 0 | F39: 0 | G39: 0 | H39: 4
A40: D08 | B40: Indebida admisión o exclusión de prueba | C40: 2 | D40: 0 | E40: 0 | F40: 1 | G40: 0 | H40: 3
A41: D09 | B41: Prueba de oficio irregular | C41: 2 | D41: 0 | E41: 0 | F41: 1 | G41: 0 | H41: 3
A42: D10 | B42: Falta de contradictorio de la prueba | C42: 2 | D42: 0 | E42: 0 | F42: 0 | G42: 0 | H42: 2
A43: D11 | B43: Omisión de valoración de prueba decisiva | C43: 7 | D43: 0 | E43: 1 | F43: 0 | G43: 1 | H43: 9
A44: D12 | B44: Valoración probatoria defectuosa | C44: 16 | D44: 0 | E44: 0 | F44: 0 | G44: 3 | H44: 19
... A55: D23 | B55: Motivación defectuosa sin especificación del supuesto | C55: 19 | D55: 0 | E55: 0 | F55: 1 | G55: 0 | H55: 20
A56: TOTAL | C56: 154 | D56: 9 | E56: 11 | F56: 6 | G56: 14 | H56: 194
A59: VARIABLES NUEVAS (sustituyen usos indebidos de D20)
A60: Insubsanabilidad declarada = Sí | C60: 19 | D60: Expedientes en que la Sala califica el vicio de insubsanable. Antes se contabilizaba como una aparición de D20.
A61: Nulidad sin vicio procesal identificado | C61: 1 | D61: Nulidad declarada para corregir un error de juicio, sin defecto procesal. Categoría de interés propio para la tesis.
A62: Filas con verificación de cita pendiente | C62: 13 | D62: Citas que son agravio de parte, parte resolutiva, marco teórico o texto truncado: requieren volver al expediente.

Sheet Cambios_aplicados
A1: REGISTRO DE CAMBIOS: cada corrección, con su motivo
A3: Clave expediente | B3: Acción | C3: De | D3: A | E3: Motivo
A4: 00072-2023 | B4: Alta | C4: — | D4: D21 | E4: La propia cita menciona la «fase externa» de la motivación, supuesto c) de Llamoja que el catálogo D01–D20 no contemplaba.
A5: 00072-2023 | B5: Baja | C5: D20 | D5: — | E5: La cita solo declara la insubsanabilidad de los vicios de motivación ya codificados en D15; se traslada a la variable «Insubsanabilidad declarada».
A6: 00115-2012 | B6: Baja | C6: D20 | D6: — | E6: «Adolece de nulidad insubsanable» es el calificativo del defecto de D01, no un defecto residual.
A7: 00115-2012 | B7: Reclasificación de estatus | C7: D02 | D7: D02 (derivado) | E7: La indefensión es consecuencia del emplazamiento defectuoso de D01, no un defecto autónomo.
A8: 00234-2018 | B8: Migración | C8: D20 | D8: D19 | E8: «Sentencia emitida sin que las resoluciones tres y catorce hayan quedado consentidas» es falta de firmeza de una incidencia condicionante, no un defecto residual. Se mantiene como alegado no acogido: la Sala lo desestima (art. 190 in fine CPC).
A9: 00340-2002 | B9: Baja | C9: D15 | D9: — | E9: Cita genérica (arts. VII TP, 50.6 CPC y 139.5 Const.) que no describe inferencia inválida ni incoherencia; el mismo pasaje sostenía D16.
A10: 00340-2002 | B10: Migración | C10: D06 | D10: D16 | E10: «Se ha sentenciado sobre una causal no determinada como punto controvertido» describe una sentencia extra petita, no un auto de fijación deficiente.
A11: 00340-2002 | B11: Sustitución de cita | C11: D16 | D11: D16 | E11: Se reemplaza la fórmula genérica por el pasaje que describe la incongruencia.
A12: 00428-2017 | B12: Migración | C12: D15 | D12: D21 | E12: «Motivación defectuosa» por uso de casaciones sobre supuestos fácticos distintos es deficiencia de justificación externa de la premisa normativa, no defecto interno.
A13: 00428-2017 | B13: Reclasificación de estatus | C13: — | D13: ADV | E13: La Sala revoca y falla el fondo: el vicio se advierte sin efecto anulatorio.
A14: 00646-2024 | B14: Baja | C14: D11 | D14: — | E14: «No obra en autos instrumento idóneo que acredite» describe ausencia de prueba, no omisión de valorarla; el fenómeno ya está en D12 (carga probatoria).
... A156: 00925-2016 | B156: Baja | C156: D21 (razonamiento propio de la Sala sobre plazo del art. 534 CPC) | D156: — | E156: El vicio declarado y computado es D03 (litisconsorte necesario omitido); la referencia al art. 534 CPC corrige un argumento del A quo pero no es, en sí, una causal autónoma.

Sheet Diccionario_causales
A1: DICCIONARIO DE CAUSALES: definición operacional, subclasificación y regla de deslinde
A2: Las reglas de deslinde recogen los errores detectados en la auditoría de citas. Aplíquense antes de marcar cualquier causal.
A4: Cód. | B4: Causal | C4: Definición operacional | D4: Subclasificación | E4: Regla de deslinde / qué NO marcar
A5: D01 | B5: Notificación o emplazamiento defectuoso | C5: Acto de comunicación inexistente o practicado incumpliendo requisitos relevantes, que impide o compromete el conocimiento oportuno necesario para ejercer una facultad procesal. | D5: Defecto de destinatario, de contenido, de medio, temporal, de constancia, u omisión absoluta. | E5: NO marcar cuando el sujeto no fue emplazado por no haber sido integrado a la relación procesal: eso es D03. NO marcar la orden de notificar contenida en la parte resolutiva: es el remedio, no el vicio.
A6: D02 | B6: Vulneración del derecho de defensa | C6: Privación material de una oportunidad relevante de conocer, alegar, contradecir, probar o impugnar. | D6: Defensa informativa, alegatoria, probatoria, impugnatoria y técnica. | E6: Marcar como DECLARADO solo si es un defecto autónomo (por ejemplo, resolver sobre una causal no alegada sin traslado, o un apercibimiento que impide considerar la defensa). Si la indefensión es consecuencia de D01, D03, D04, D08 o D19 ya marcados en la misma fila, usar estatus DERIVADO.
A7: D03 | B7: Litisconsorte necesario omitido | C7: Falta de incorporación o emplazamiento de un sujeto cuya participación es indispensable para que la decisión afecte válida y uniformemente la relación jurídica debatida (arts. 93, 95 y 96 CPC). | D7: Necesario activo, pasivo o mixto; omisión antes o después del saneamiento; integración sin oportunidad efectiva de defensa. | E7: NO marcar cuando el sujeto omitido es litisconsorte facultativo o tercero con interés.
A8: D04 | B8: Declaración indebida de rebeldía | C8: Declaración de rebeldía sin estar satisfechos sus presupuestos (art. 458 CPC) o atribución de efectos que exceden los legalmente previstos (art. 461 CPC). | D8: Rebeldía sobre emplazamiento inválido; prematura; pese a contestación oportuna; efectos excesivos. | E8: Exige un pasaje en que la Sala censure la declaración o sus efectos. La mera narración de que se declaró la rebeldía no acredita la causal.
A9: D05 | B9: Omisión o irregularidad de audiencia | C9: Omisión de audiencia jurídicamente necesaria, o realización sin garantías esenciales de convocatoria, inmediación, participación o contradicción. | D9: Omisión total; sin notificación válida; sin el juez competente; restricción de la intervención oral; cierre anticipado. | E9: El indicador es «audiencia jurídicamente necesaria omitida», no «no hubo audiencia» (art. 468 CPC vigente). Si la audiencia se celebró y lo omitido fue actuar una prueba admitida, corresponde D07.
A10: D06 | B10: Deficiente fijación de puntos/hechos controvertidos | C10: Delimitación incompleta, excesiva, ambigua o inconexa de las cuestiones controvertidas, en el momento del saneamiento (art. 468 CPC). | D10: Omisión de un hecho esencial; inclusión de hechos admitidos; mera reproducción del petitorio; puntos genéricos; modificación tardía. | E10: REGLA DE DESLINDE CRÍTICA: el defecto debe estar en el AUTO DE FIJACIÓN. Si la sentencia resolvió fuera de los puntos correctamente fijados, u omitió pronunciarse sobre ellos, corresponde D16. La sola mención de la expresión «puntos controvertidos» en la cita no basta.
A11: D07 | B11: Prueba admitida y no actuada | C11: Medio previamente admitido que, requiriendo actuación, no fue practicado o lo fue incompletamente antes de la decisión. | D11: Falta total de actuación; actuación inconclusa; frustrada por responsabilidad del órgano; cierre de etapa antes de ejecutarla. | E11: Se distingue de D08 por el momento: allí el defecto está en la entrada al proceso; aquí, en la actuación de lo ya admitido.
A12: D08 | B12: Indebida admisión o exclusión de prueba | C12: Error en el juicio de admisibilidad: se incorpora un medio que no debía ingresar o se rechaza uno que sí satisfacía las condiciones. | D12: Exclusión indebida y admisión indebida (incluida la valoración de prueba nunca admitida). | E12: NO marcar cuando la Sala convalida la decisión de admisión. NO marcar cuando lo pendiente es la calificación del ofrecimiento: eso es D19.
A13: D09 | B13: Prueba de oficio irregular | C13: Prueba ordenada judicialmente fuera de los presupuestos del art. 194 CPC y del X Pleno Casatorio. | D13: Sin insuficiencia probatoria; fuente no citada por las partes; sustitución de la carga; sin contradicción; sin motivación; no excepcional. | E13: NO confundir con la nulidad manifiesta del acto jurídico declarada de oficio (art. V TP del Código Civil): son institutos distintos. Sugerir al A quo el uso de la prueba de oficio tampoco es una irregularidad.
A14: D10 | B14: Falta de contradictorio de la prueba | C14: Imposibilidad real de conocer, controlar u objetar un elemento PROBATORIO utilizado en la decisión. | D14: Falta de traslado; imposibilidad de tachar u observar; prueba incorporada sorpresivamente; prueba de oficio sin contradicción. | E14: El objeto del contradictorio omitido debe ser prueba. Si lo omitido es el traslado sobre una causal jurídica introducida de oficio, corresponde D02 y D16.
A15: D11 | B15: Omisión de valoración de prueba decisiva | C15: Silencio del razonamiento respecto de un medio incorporado y potencialmente determinante. | D15: Silencio absoluto; omisión de la prueba que contradice la conclusión; omisión de un conjunto convergente; mención sin análisis. | E15: REGLA DE DESLINDE CRÍTICA: «no valoró» es D11; «no valoró DEBIDAMENTE» y «no valoró EN CONJUNTO» son D12. La ausencia de prueba en autos no es omisión de valoración.
... A27: D23 | B27: Motivación defectuosa sin especificación del supuesto | C27: La Sala declara un defecto de motivación pero no especifica el supuesto: emplea fórmulas genéricas o la sola invocación normativa. | D27: «No se encuentra debidamente motivada»; «motivación defectuosa»; «error en la motivación»; invocación aislada de los arts. 122.3 CPC, 50.6 CPC o 139.5 Const. | E27: CÓDIGO NUEVO. Es la categoría residual de la FAMILIA DE MOTIVACIÓN. Evita que las fórmulas genéricas se imputen a D15 y lo conviertan artificialmente en la causal más frecuente. Su frecuencia es, además, un hallazgo en sí: mide cuánto de la motivación se censura sin diagnóstico.

Sheet Leyenda_estatus
A1: ESTATUS DE CADA REGISTRO DE CAUSAL
A2: El prefijo de cada celda de causal en «Corpus_corregido» indica el valor probatorio del registro. Solo los DECLARADOS deben computarse como frecuencia de defectos.
A4: Estatus | B4: Significado | C4: Uso en el conteo
A5: DECLARADO | B5: Declarado por la Sala | C5: SÍ se computa. Es la base de «Marcas_declaradas».
A6: DERIVADO | B6: Consecuencia derivada | C6: NO se computa como defecto autónomo: duplicaría el fenómeno ya contado en la causal de origen. Útil para describir el derecho afectado.
A7: ALEGADO | B7: Alegado, no acogido | C7: NO se computa: es la tesis del apelante, no el juicio del Colegiado. Sirve para estudiar la brecha entre lo alegado y lo declarado.
A8: VOTO MINORÍA | B8: Voto en minoría / discordia / singular | C8: NO se computa en la frecuencia principal: no es la ratio de la sentencia. Analizable por separado como disidencia sobre el control de nulidad.
A9: ADVERTIDO | B9: Advertido sin nulidad | C9: NO se computa entre las nulidades: la Sala detecta el vicio pero corrige en instancia. Es la base para medir el uso de la Circular de reenvío (RA 002-2014-CE-PJ).

Sheet Trazabilidad_fusion
A1: Clave expediente | B1: Fuentes en conflicto | C1: Fuente que aporta la fila base | D1: Campos llenos de la fila base | E1: Campos llenos de las demás filas | F1: Campos completados desde otras fuentes
A2: 00132-2015 | B2: Comparativa_defectos_2018_vs_2024 + Defectos_procesales_SV_CSJA | C2: Comparativa_defectos_2018_vs_2024 | D2: 8 | E2: 8 | F2: 0
A3: 00192-2021 | B3: Comparativa_defectos_2018_vs_2024 + Defectos_procesales_SV_CSJA | C3: Comparativa_defectos_2018_vs_2024 | D3: 7 | E3: 7 | F3: 0
A4: 00320-2023 | B4: Comparativa_defectos_2018_vs_2024 + Defectos_procesales_SV_CSJA | C4: Comparativa_defectos_2018_vs_2024 | D4: 9 | E4: 8 | F4: 0
A5: 00340-2002 | B5: Comparativa_defectos_2018_vs_2024 + Defectos_procesales_SV_CSJA | C5: Comparativa_defectos_2018_vs_2024 | D5: 12 | E5: 10 | F5: 0
A6: 00598-2022 | B6: Comparativa_defectos_2018_vs_2024 + Defectos_procesales_SV_CSJA | C6: Comparativa_defectos_2018_vs_2024 | D6: 10 | E6: 8 | F6: 0
A7: 00742-2022 | B7: Comparativa_defectos_2018_vs_2024 + Defectos_procesales_SV_CSJA | C7: Comparativa_defectos_2018_vs_2024 | D7: 12 | E7: 11 | F7: 0
A8: 00748-2013 | B8: Comparativa_defectos_2018_vs_2024 + Defectos_procesales_SV_CSJA | C8: Comparativa_defectos_2018_vs_2024 | D8: 9 | E8: 8 | F8: 0
A9: 00788-2013 | B9: Comparativa_defectos_2018_vs_2024 + Defectos_procesales_SV_CSJA | C9: Comparativa_defectos_2018_vs_2024 | D9: 10 | E9: 8 | F9: 0
A10: 00856-2017 | B10: Comparativa_defectos_2018_vs_2024 + Defectos_procesales_SV_CSJA | C10: Comparativa_defectos_2018_vs_2024 | D10: 9 | E10: 8 | F10: 0
A11: 00898-2013 | B11: Comparativa_defectos_2018_vs_2024 + Defectos_procesales_SV_CSJA | C11: Comparativa_defectos_2018_vs_2024 | D11: 9 | E11: 8 | F11: 0
A12: 00965-2015 | B12: Comparativa_defectos_2018_vs_2024 + Defectos_procesales_SV_CSJA | C12: Comparativa_defectos_2018_vs_2024 | D12: 10 | E12: 9 | F12: 0
A13: 00992-2016 | B13: Comparativa_defectos_2018_vs_2024 + Defectos_procesales_SV_CSJA | C13: Comparativa_defectos_2018_vs_2024 | D13: 10 | E13: 8 | F13: 0
... A89: 00925-2017 | B89: documento_unificadoABR18_SV | C89: documento_unificadoABR18_SV | D89: 8 | E89: único | F89: 0

Sheet Criterios_y_fuentes
A1: CRITERIOS DE UNIFICACIÓN DE LOS ARCHIVOS
A3: 1. Archivos de origen
A4: Clasificacion_SV_ABR24_Llamoja_defectos (_2_ y _3_): archivos idénticos (mismo MD5); se usó una sola copia.
A5: Matriz_defectos_procesales_1ra_SV (_4_ y _5_): archivos idénticos (mismo MD5); se usó una sola copia.
A6: Comparativa_defectos_2018_vs_2024 (_3_): hojas «Corpus 2018 (pre-2019)» (36 exp.) y «Corpus 2024» (23 exp.).
A7: Defectos_procesales_SV_CSJA (_3_): hoja «Defectos procesales» (59 exp.); mismos expedientes que el archivo anterior, con D1–D11 solamente.
A9: 2. Clave de unificación
A10: Se normalizó el expediente a «NNNNN-AAAA» (número con cinco dígitos y año), porque unas fuentes usan el código corto (00132-2015) y otras el completo (00879-2022-0-0401-JR-CI-02).
A11: En la columna «Expediente (código de origen)» se conserva el código tal como aparece en la fuente que aportó la fila base.
A13: 3. Regla de fusión: se conserva la fila con más información
A14: Cuando un mismo expediente aparecía en más de un archivo, se eligió como fila base la que tenía más campos llenos (desempate: mayor extensión total del texto).
A15: Sobre esa fila base se completaron los campos vacíos con el dato de las demás fuentes.
... A40: Se evaluó también el archivo defectos_primera_sv_antes_2019_con18.xlsx: sus 36 expedientes coinciden exactamente (mismas claves) con el grupo «Pre-2019» ya presente en este corpus, con codificación más completa (estatus DECLARADO/DERIVADO y citas). Por tratarse de una versión preliminar ya superada, no se volvió a incorporar para evitar duplicados.

Sheet Revision_motivacion_163
A1: N | B1: Clave | C1: Grupo | D1: Sala | E1: SV | F1: Fallo | G1: Causales_motivacion_declaradas | H1: Tipo_actual_en_corpus | I1: Categoria_Llamoja | J1: Estado
A2: 1 | B2: 00001-2018 | C2: Matriz sumarísimos — anteriores a 2019 | D2: 2SC | E2: SV 343-2019-2SC | F2: NULA (reenvío) | G2: D15 (DECLARADO — «la resolución apelada contiene una motivación i...) | H2: (vacío) | I2: b) Falta de motivación interna | J2: Pendiente de clasificar — mapeo directo posible
A3: 2 | B3: 00072-2023 | C3: Matriz sumarísimos — grupo 2024 | D3: 2SC | E3: SV 429-2025-2SC | F3: NULA DE OFICIO (reenvío) | G3: D15 (DECLARADO — «la sentencia impugnada adolece de vicios de mot...), D16 (DECLARADO — «se omitió pronunciamiento en relación a la buen...), D21 (DECLARADO — «la sentencia impugnada adolece de vicios de mot...) | H3: (vacío) | I3: (combinación: D15/D16/D21) | J3: Pendiente de clasificar — combinación múltiple, requiere lectura
A4: 3 | B4: 00115-2012 | C4: Matriz sumarísimos — anteriores a 2019 | D4: 2SC | E4: SV 660-2018-2SC | F4: NULA (reenvío) | G4: — | H4: (vacío) | I4: — | J4: Sin vicio de motivación (sin marca explícita)
A5: 4 | B5: 00129-2022 | C5: Matriz sumarísimos — grupo 2024 | D5: 2SC | E5: SV 563-2024-2SC | F5: REVOCADA → IMPROCEDENTE | G5: — | H5: (vacío) | I5: — | J5: Sin vicio de motivación (sin marca explícita)
A6: 5 | B6: 00132-2015 | C6: Pre-2019 | D6: 2SC | E6: SV N° 667-2018-2SC | F6: Revocada | G6: — | H6: (vacío) | I6: — | J6: Sin vicio de motivación (sin marca explícita)
A7: 6 | B7: 00153-2022 | C7: Matriz sumarísimos — grupo 2024 | D7: 3SC | E7: SV 51-2025-3SC | F7: REVOCADA → INFUNDADA | G7: — | H7: (vacío) | I7: — | J7: Sin vicio de motivación (sin marca explícita)
A8: 7 | B8: 00192-2021 | C8: 2024 | E8: SV N° 285-2026 | F8: Revocada | G8: — | H8: (vacío) | I8: — | J8: Sin vicio de motivación (sin marca explícita)
A9: 8 | B9: 00234-2018 | C9: Matriz sumarísimos — anteriores a 2019 | D9: 3SC | E9: SV 638-2019-3SC | F9: REVOCADA → INFUNDADA | G9: — | H9: (vacío) | I9: — | J9: Sin vicio de motivación (sin marca explícita)
A10: 9 | B10: 00320-2023 | C10: 2024 | D10: 2SC | E10: SV N° 398-2025-2SC | F10: Nula | G10: D13 (DECLARADO — “…contractual. En ese sentido, la sentencia mate...) | H10: (vacío) | I10: d) Motivación insuficiente | J10: Pendiente de clasificar — mapeo directo posible
A11: 10 | B11: 00340-2002 | C11: Pre-2019 | D11: 2SC | E11: SV N° 0008-2018-2SC | F11: Nula | G11: D16 (DECLARADO — “…Se ha sentenciado sobre una causal no determin...) | H11: (vacío) | I11: (ambiguo: D16) | J11: Pendiente de clasificar — requiere lectura (D16/D23)
A12: 11 | B12: 00367-2024 | C12: Matriz sumarísimos — grupo 2024 | D12: 1SC | E12: SV 338-2024-1SC | F12: REVOCADA → INFUNDADA | G12: — | H12: (vacío) | I12: — | J12: Sin vicio de motivación (sin marca explícita)
A13: 12 | B13: 00414-2023 | C13: Llamoja — SV de control (2021-2023) | D13: 3SC | E13: 178-2025-3SC | F13: NULA | G13: D13 (DECLARADO — (evidencia en las columnas «Cita textual 1–3» de...), D16 (DECLARADO — (evidencia en las columnas «Cita textual 1–3» de...) | H13: d) Motivación insuficiente | I13: d) Motivación insuficiente | J13: Clasificado (a-f) en el corpus
A14: 13 | B14: 00428-2017 | C14: Matriz sumarísimos — anteriores a 2019 | D14: 2SC | E14: SV 033-2020-2SC | F14: REVOCADA → FUNDADA | G14: — | H14: (vacío) | I14: — | J14: Sin vicio de motivación (sin marca explícita)
A15: 14 | B15: 00598-2022 | C15: 2024 | D15: 3SC | E15: SV N° 256-2025-3SC | F15: Nula | G15: D13 (DECLARADO — “…vierte que el Juez de primera instancia no ha ...) | H15: (vacío) | I15: d) Motivación insuficiente | J15: Pendiente de clasificar — mapeo directo posible
A16: 15 | B16: 00646-2024 | C16: Matriz sumarísimos — grupo 2024 | D16: 2SC | E16: SV 240-2025-2SC | F16: NULA (reenvío) | G16: D16 (DECLARADO — «si bien el A quo se ha pronunciado sobre la cod...), D23 (DECLARADO — «se tiene que se ha vulnerado el inciso 5º del a...) | H16: (vacío) | I16: (ambiguo: D16/D23) | J16: Pendiente de clasificar — requiere lectura (D16/D23)
A17: 16 | B17: 00661-2023 | C17: Matriz sumarísimos — grupo 2024 | D17: 2SC | E17: SV 302-2025-2SC | F17: NULA (reenvío) | G17: D13 (DECLARADO — «incurriéndose en vicio procesal por motivación ...) | H17: (vacío) | I17: d) Motivación insuficiente | J17: Pendiente de clasificar — mapeo directo posible
A18: 17 | B18: 00742-2022 | C18: 2024 | E18: SV N° 196-2025 | F18: Otro | G18: D16 (DECLARADO — “…urídico no invocada. Una forma de verificar qu...) | H18: (vacío) | I18: (ambiguo: D16) | J18: Pendiente de clasificar — requiere lectura (D16/D23)
A19: 18 | B19: 00748-2013 | C19: Pre-2019 | D19: 2SC | E19: SV N° 674-2018-2SC | F19: Nula | G19: D15 (DECLARADO — “…azonamiento conforme al Tribunal Constituciona...) | H19: (vacío) | I19: b) Falta de motivación interna | J19: Pendiente de clasificar — mapeo directo posible
A20: 19 | B20: 00760-2021 | C20: Llamoja — SV de control (2021-2023) | D20: 3SC | E20: 34-2025-3SC | F20: NULA | G20: — | H20: — Sin vicio de motivación como causal | I20: — | J20: Sin vicio de motivación (marcado explícito)
A21: 20 | B21: 00774-2021 | C21: Llamoja — SV de control (2021-2023) | D21: 2SC | E21: 161-2025-2SC | F21: NULA | G21: D16 (DECLARADO — (evidencia en las columnas «Cita textual 1–3» de...), D21 (DECLARADO — (evidencia en las columnas «Cita textual 1–3» de...) | H21: c) Deficiencia de motivación externa | I21: c) Deficiencia de motivación externa | J21: Clasificado (a-f) en el corpus
A22: 21 | B22: 00788-2013 | C22: Pre-2019 | D22: 2SC | E22: SV N° 191-2021-2SC | F22: Nula | G22: D16 (DECLARADO — “…es decir, emitió un pronunciamiento distinto a...) | H22: (vacío) | I22: (ambiguo: D16) | J22: Pendiente de clasificar — requiere lectura (D16/D23)
A23: 22 | B23: 00848-2011 | C23: Matriz sumarísimos — anteriores a 2019 | D23: 3SC | E23: SV 309-2019-3SC | F23: REVOCADA → FUNDADA EN PARTE | G23: — | H23: (vacío) | I23: — | J23: Sin vicio de motivación (sin marca explícita)
A24: 23 | B24: 00856-2017 | C24: Pre-2019 | D24: 1SC | E24: SV N° 525-2019-1SC | F24: Nula e insubsistente | G24: D16 (DECLARADO — “…se ha incurrido en causal de nulidad por falta...) | H24: (vacío) | I24: (ambiguo: D16) | J24: Pendiente de clasificar — requiere lectura (D16/D23)
A25: 24 | B25: 00879-2022 | C25: Llamoja — SV de control (2021-2023) | D25: 1SC | F25: NULA | G25: D15 (DECLARADO — (evidencia en las columnas «Cita textual 1–3» de...), D16 (DECLARADO — (evidencia en las columnas «Cita textual 1–3» de...) | H25: e) Motivación sustancialmente incongruente | I25: e) Motivación sustancialmente incongruente | J25: Clasificado (a-f) en el corpus
A26: 25 | B26: 00898-2013 | C26: Pre-2019 | D26: 3SC | E26: SV N° 550-2018-3SC | F26: Revocada | G26: — | H26: (vacío) | I26: — | J26: Sin vicio de motivación (sin marca explícita)
A27: 26 | B27: 00933-2022 | C27: Llamoja — SV de control (2021-2023) | D27: 3SC | E27: 72-2024-3SC | F27: NULA | G27: D14 (DECLARADO — (evidencia en las columnas «Cita textual 1–3» de...), D16 (DECLARADO — (evidencia en las columnas «Cita textual 1–3» de...) | H27: a) Inexistencia / motivación aparente | I27: a) Inexistencia / motivación aparente | J27: Clasificado (a-f) en el corpus
A28: 27 | B28: 00965-2015 | C28: Pre-2019 | D28: 3SC | E28: SV N° 498-2019-3SC | F28: Nula | G28: D23 (DECLARADO — “…requisitos que deben contener las Resoluciones...) | H28: (vacío) | I28: (ambiguo: D23) | J28: Pendiente de clasificar — requiere lectura (D16/D23)
A29: 28 | B29: 00979-2024 | C29: Matriz sumarísimos — grupo 2024 | D29: 1SC | E29: Auto de Vista 960-2025-1SC | F29: CONFIRMADA | G29: — | H29: (vacío) | I29: — | J29: Sin vicio de motivación (sin marca explícita)
A30: 29 | B30: 00992-2016 | C30: Pre-2019 | D30: 3SC | E30: SV N° 76-2019-3SC | F30: Otro | G30: D16 (DECLARADO — “…o 04003327. Que, la sentencia recurrida ha omi...), D23 (DECLARADO — “…la sentencia apelada incurre en causal de nuli...) | H30: (vacío) | I30: (ambiguo: D16/D23) | J30: Pendiente de clasificar — requiere lectura (D16/D23)
A31: 30 | B31: 01033-2023 | C31: Llamoja — SV de control (2021-2023) | D31: 2SC | E31: 470-2025-2SC | F31: NULA DE OFICIO | G31: D16 (DECLARADO — (evidencia en las columnas «Cita textual 1–3» de...) | H31: e) Motivación sustancialmente incongruente | I31: e) Motivación sustancialmente incongruente | J31: Clasificado (a-f) en el corpus
A32: 31 | B32: 01101-2022 | C32: 2024 | D32: 2SC | E32: SV N° 226-2025-2SC | F32: Nula | G32: D23 (DECLARADO — “…lo no es posible particularmente en este caso,...) | H32: (vacío) | I32: (ambiguo: D23) | J32: Pendiente de clasificar — requiere lectura (D16/D23)
A33: 32 | B33: 01286-2022 | C33: 2024 | D33: 2SC | E33: SV N° 341-2025-2SC | F33: Nula e insubsistente | G33: — | H33: (vacío) | I33: — | J33: Sin vicio de motivación (sin marca explícita)
A34: 33 | B34: 01328-2023 | C34: 2024 | D34: 2SC | E34: SV N° 155-2025-2SC | F34: Revocada | G34: — | H34: (vacío) | I34: — | J34: Sin vicio de motivación (sin marca explícita)
A35: 34 | B35: 01376-2023 | C35: 2024 | D35: 2SC | E35: SV N° 033-2026-2SC | F35: Revocada | G35: — | H35: (vacío) | I35: — | J35: Sin vicio de motivación (sin marca explícita)
A36: 35 | B36: 01417-2017 | C36: Pre-2019 | D36: 2SC | E36: SV N° 004-2020-2SC | F36: Nula | G36: D23 (DECLARADO — “…en mérito a lo expuesto precedentemente se con...) | H36: (vacío) | I36: (ambiguo: D23) | J36: Pendiente de clasificar — requiere lectura (D16/D23)
A37: 36 | B37: 01535-2022 | C37: 2024 | D37: 2SC | E37: SV N° 572-2024-2SC | F37: Nula | G37: D14 (DECLARADO — “…a que a través de la resolución apelada no se ...) | H37: (vacío) | I37: a) Inexistencia / motivación aparente | J37: Pendiente de clasificar — mapeo directo posible
... A39: 38 | B39: 01647-2019 | C39: 2024 | D39: 2SC | E39: SV N° 082-2026-2SC | F39: Nula | G39: D14 (DECLARADO — “…al debido proceso y el de motivación estableci...) | H39: (vacío) | I39: a) Inexistencia / motivación aparente | J39: Pendiente de clasificar — mapeo directo posible
